{"data":{"threaded_conversation_with_injections_v2":{"instructions":[{"type":"TimelineAddEntries","entries":[{"entryId":"conversationthread-1690852006447980544","sortIndex":"7532527556728536997","content":{"entryType":"TimelineTimelineModule","__typename":"TimelineTimelineModule","items":[{"entryId":"conversationthread-1690852006447980544-tweet-1690852006447980544","item":{"itemContent":{"itemType":"TimelineTweet","__typename":"TimelineTweet","tweet_results":{"result":{"__typename":"Tweet","rest_id":"1690852006447980544","has_birdwatch_notes":false,"core":{"user_results":{"result":{"__typename":"User","id":"VXNlcjoxNDkwNzc2Njk0OTY1Mjk3MTU2","rest_id":"1490776694965297156","affiliates_highlighted_label":{},"has_graduated_access":true,"is_blue_verified":true,"legacy":{"can_dm":true,"can_media_tag":true,"created_at":"Mon Feb 07 19:57:26 +0000 2022","default_profile":true,"default_profile_image":false,"description":"Aerospace Engineer by ☀️; Analyzing jpegs at 🌛.\n\nBlogger ✍️\nEmpiricist 📖\nResearcher 🧐\n\nSimplifying the Future of Technology by advocating Common Sense 🧠","entities":{"description":{"urls":[]},"url":{"urls":[{"display_url":"the-non-fungible-blog.ghost.io","expanded_url":"https://the-non-fungible-blog.ghost.io/","url":"https://t.co/LXBZj0UFUS","indices":[0,23]}]}},"fast_followers_count":0,"favourites_count":2591,"followers_count":3926,"friends_count":118,"has_custom_timelines":false,"is_translator":false,"listed_count":1,"location":"Knowhere","media_count":429,"name":"The Coll3ctor","normal_followers_count":3926,"pinned_tweet_ids_str":["1687786537902026752"],"possibly_sensitive":false,"profile_banner_url":"https://pbs.twimg.com/profile_banners/1490776694965297156/1685393539","profile_image_url_https":"https://pbs.twimg.com/profile_images/1559132802402091009/ORIXZM-z_normal.jpg","profile_interstitial_type":"","screen_name":"The_Coll3ctor","statuses_count":2565,"translator_type":"none","url":"https://t.co/LXBZj0UFUS","verified":false,"want_retweets":false,"withheld_in_countries":[]},"smart_blocked_by":false,"smart_blocking":false,"business_account":{}}}},"edit_control":{"edit_tweet_ids":["1690852006447980544"],"editable_until_msecs":"1691969107000","is_edit_eligible":false,"edits_remaining":"5"},"is_translatable":false,"views":{"count":"48794","state":"EnabledWithCount"},"source":"<a href=\"http://twitter.com/download/iphone\" rel=\"nofollow\">Twitter for iPhone</a>","legacy":{"created_at":"Sun Aug 13 22:25:07 +0000 2023","conversation_id_str":"1690844480126238720","display_text_range":[12,75],"entities":{"user_mentions":[{"id_str":"897058816226844672","name":"CCTV IDIOTS","screen_name":"cctvidiots","indices":[0,11]}],"urls":[],"hashtags":[],"symbols":[]},"favorite_count":806,"favorited":false,"full_text":"@cctvidiots This ain’t gang violence but a typical inter school ego clash 🙄","in_reply_to_screen_name":"cctvidiots","in_reply_to_status_id_str":"1690844480126238720","in_reply_to_user_id_str":"897058816226844672","is_quote_status":false,"lang":"en","quote_count":0,"reply_count":2,"retweet_count":1,"retweeted":false,"user_id_str":"1490776694965297156","id_str":"1690852006447980544"},"quick_promote_eligibility":{"eligibility":"IneligibleNotProfessional"}}},"tweetDisplayType":"Tweet"},"clientEventInfo":{"details":{"conversationDetails":{"conversationSection":"HighQuality"},"timelinesDetails":{"controllerData":"DAACDAAEDAABCgABFIgaCCAPABUKAAIAAAAAFARACAAAAAA="}}}}},{"entryId":"conversationthread-1690852006447980544-cursor-showmore-6167248393407210017","item":{"itemContent":{"itemType":"TimelineTimelineCursor","__typename":"TimelineTimelineCursor","value":"PAAAAPAtPBwcFoCAtcGfvI73LhUCAAAYJmNvbnZlcnNhdGlvbnRocmVhZC0xNjkwODUyMDA2NDQ3OTgwNTQ0IgAA","cursorType":"ShowMore","displayTreatment":{"actionText":"Show replies"}},"clientEventInfo":{"details":{"conversationDetails":{"conversationSection":"HighQuality"}}}}}],"displayType":"VerticalConversation","clientEventInfo":{"details":{"conversationDetails":{"conversationSection":"HighQuality"}}}}},{"entryId":"conversationthread-1690907686412398592","sortIndex":"7532527556728536987","content":{"entryType":"TimelineTimelineModule","__typename":"TimelineTimelineModule","items":[{"entryId":"conversationthread-1690907686412398592-tweet-1690907686412398592","item":{"itemContent":{"itemType":"TimelineTweet","__typename":"TimelineTweet","tweet_results":{"result":{"__typename":"Tweet","rest_id":"1690907686412398592","has_birdwatch_notes":false,"core":{"user_results":{"result":{"__typename":"User","id":"VXNlcjoxMTk1ODQzODIxMDM0MTg4ODAz","rest_id":"1195843821034188803","affiliates_highlighted_label":{},"has_graduated_access":true,"is_blue_verified":true,"legacy":{"can_dm":true,"can_media_tag":true,"created_at":"Sat Nov 16 23:19:40 +0000 2019","default_profile":true,"default_profile_image":false,"description":"God - family - gym - games🎮 || Member: @Citadalxyz ⚜️ || DC: Okoli.","entities":{"description":{"urls":[]}},"fast_followers_count":0,"favourites_count":28078,"followers_count":1187,"friends_count":588,"has_custom_timelines":true,"is_translator":false,"listed_count":13,"location":"Web3","media_count":1474,"name":"OKOLI✨","normal_followers_count":1187,"pinned_tweet_ids_str":["1564690593762230273"],"possibly_sensitive":false,"profile_banner_url":"https://pbs.twimg.com/profile_banners/1195843821034188803/1691169266","profile_image_url_https":"https://pbs.twimg.com/profile_images/1682179072267304963/wCgtpPxj_normal.jpg","profile_interstitial_type":"","screen_name":"OKOLIEMMANUELS2","statuses_count":27181,"translator_type":"none","verified":false,"want_retweets":false,"withheld_in_countries":[]},"smart_blocked_by":false,"smart_blocking":false,"business_account":{}}}},"edit_control":{"edit_tweet_ids":["1690907686412398592"],"editable_until_msecs":"1691982382000","is_edit_eligible":false,"edits_remaining":"5"},"is_translatable":false,"views":{"count":"3609","state":"EnabledWithCount"},"source":"<a href=\"http://twitter.com/download/iphone\" rel=\"nofollow\">Twitter for iPhone</a>","legacy":{"created_at":"Mon Aug 14 02:06:22 +0000 2023","conversation_id_str":"1690844480126238720","display_text_range":[12,31],"entities":{"user_mentions":[{"id_str":"897058816226844672","name":"CCTV IDIOTS","screen_name":"cctvidiots","indices":[0,11]}],"urls":[],"hashtags":[],"symbols":[]},"favorite_count":13,"favorited":false,"full_text":"@cctvidiots This is so peaceful","in_reply_to_screen_name":"cctvidiots","in_reply_to_status_id_str":"1690844480126238720","in_reply_to_user_id_str":"897058816226844672","is_quote_status":false,"lang":"en","quote_count":0,"reply_count":1,"retweet_count":0,"retweeted":false,"user_id_str":"1195843821034188803","id_str":"1690907686412398592"},"quick_promote_eligibility":{"eligibility":"IneligibleNotProfessional"}}},"tweetDisplayType":"Tweet"},"clientEventInfo":{"details":{"conversationDetails":{"conversationSection":"HighQuality"},"timelinesDetails":{"controllerData":"DAACDAAEDAABCgABFIgKiCILAAUKAAIAAAAAFARACAAAAAA="}}}}}],"displayType":"VerticalConversation","clientEventInfo":{"details":{"conversationDetails":{"conversationSection":"HighQuality"}}}}},{"entryId":"conversationthread-1690967666176233472","sortIndex":"7532527556728536977","content":{"entryType":"TimelineTimelineModule","__typename":"TimelineTimelineModule","items":[{"entryId":"conversationthread-1690967666176233472-tweet-1690967666176233472","item":{"itemContent":{"itemType":"TimelineTweet","__typename":"TimelineTweet","tweet_results":{"result":{"__typename":"Tweet","rest_id":"1690967666176233472","has_birdwatch_notes":false,"core":{"user_results":{"result":{"__typename":"User","id":"VXNlcjo3OTY5MzY2OA==","rest_id":"79693668","affiliates_highlighted_label":{},"has_graduated_access":true,"is_blue_verified":true,"legacy":{"can_dm":true,"can_media_tag":true,"created_at":"Sun Oct 04 09:19:44 +0000 2009","default_profile":false,"default_profile_image":false,"description":"Software Engineer by profession, Student of Vedic Jyotish, Vastu and Adhyatmik shAstras.","entities":{"description":{"urls":[]},"url":{"urls":[{"display_url":"ysbundela.com","expanded_url":"https://ysbundela.com/","url":"https://t.co/JVwLDDWtF9","indices":[0,23]}]}},"fast_followers_count":0,"favourites_count":106635,"followers_count":1209,"friends_count":2157,"has_custom_timelines":true,"is_translator":false,"listed_count":23,"location":"San Francisco, CA","media_count":799,"name":"Yogendra Bundela","normal_followers_count":1209,"pinned_tweet_ids_str":["1654019165903257600"],"possibly_sensitive":false,"profile_banner_url":"https://pbs.twimg.com/profile_banners/79693668/1673501454","profile_image_url_https":"https://pbs.twimg.com/profile_images/1562978304625258497/QvQRLLOe_normal.jpg","profile_interstitial_type":"","screen_name":"YSBundela1008","statuses_count":37599,"translator_type":"none","url":"https://t.co/JVwLDDWtF9","verified":false,"want_retweets":false,"withheld_in_countries":[]},"smart_blocked_by":false,"smart_blocking":false,"business_account":{}}}},"edit_control":{"edit_tweet_ids":["1690967666176233472"],"editable_until_msecs":"1691996682000","is_edit_eligible":false,"edits_remaining":"5"},"is_translatable":false,"views":{"count":"9056","state":"EnabledWithCount"},"source":"<a href=\"http://twitter.com/download/iphone\" rel=\"nofollow\">Twitter for iPhone</a>","legacy":{"created_at":"Mon Aug 14 06:04:42 +0000 2023","conversation_id_str":"1690844480126238720","display_text_range":[12,114],"entities":{"user_mentions":[{"id_str":"897058816226844672","name":"CCTV IDIOTS","screen_name":"cctvidiots","indices":[0,11]}],"urls":[],"hashtags":[],"symbols":[]},"favorite_count":117,"favorited":false,"full_text":"@cctvidiots This is not gang violence, can call it school violence though. Gang violence is never without weapons.","in_reply_to_screen_name":"cctvidiots","in_reply_to_status_id_str":"1690844480126238720","in_reply_to_user_id_str":"897058816226844672","is_quote_status":false,"lang":"en","quote_count":0,"reply_count":2,"retweet_count":1,"retweeted":false,"user_id_str":"79693668","id_str":"1690967666176233472"},"quick_promote_eligibility":{"eligibility":"IneligibleNotProfessional"}}},"tweetDisplayType":"Tweet"},"clientEventInfo":{"details":{"conversationDetails":{"conversationSection":"HighQuality"},"timelinesDetails":{"controllerData":"DAACDAAEDAABCgABFIgaCCQLABUKAAIAAAAAFARACAAAAAA="}}}}}],"displayType":"VerticalConversation","clientEventInfo":{"details":{"conversationDetails":{"conversationSection":"HighQuality"}}}}},{"entryId":"conversationthread-1690847314972233728","sortIndex":"7532527556728536967","content":{"entryType":"TimelineTimelineModule","__typename":"TimelineTimelineModule","items":[{"entryId":"conversationthread-1690847314972233728-tweet-1690847314972233728","item":{"itemContent":{"itemType":"TimelineTweet","__typename":"TimelineTweet","tweet_results":{"result":{"__typename":"Tweet","rest_id":"1690847314972233728","has_birdwatch_notes":false,"core":{"user_results":{"result":{"__typename":"User","id":"VXNlcjo0NTU1MDk0Njk=","rest_id":"455509469","affiliates_highlighted_label":{},"has_graduated_access":true,"is_blue_verified":false,"legacy":{"can_dm":true,"can_media_tag":false,"created_at":"Thu Jan 05 05:50:49 +0000 2012","default_profile":true,"default_profile_image":false,"description":"No_ 1| Life don't just happens! |Heal the 🗺🌍  | Proudly Blues Fan ⚽️| Lover's of  Literatures\n 📚\n#Bitcoin","entities":{"description":{"urls":[]}},"fast_followers_count":0,"favourites_count":6224,"followers_count":1657,"friends_count":2552,"has_custom_timelines":true,"is_translator":false,"listed_count":1,"location":"Somewhere in the Universe. ","media_count":795,"name":"♥♣ Absolute FEM!! 🤫♣♥","normal_followers_count":1657,"pinned_tweet_ids_str":["1360331572533223430"],"possibly_sensitive":false,"profile_banner_url":"https://pbs.twimg.com/profile_banners/455509469/1607068997","profile_image_url_https":"https://pbs.twimg.com/profile_images/1334770235887546370/aXr3-EzN_normal.jpg","profile_interstitial_type":"","screen_name":"Iam_Hydrologist","statuses_count":20827,"translator_type":"none","verified":false,"want_retweets":false,"withheld_in_countries":[]},"smart_blocked_by":false,"smart_blocking":false,"business_account":{}}}},"edit_control":{"edit_tweet_ids":["1690847314972233728"],"editable_until_msecs":"1691967988000","is_edit_eligible":false,"edits_remaining":"5"},"is_translatable":false,"views":{"count":"3182","state":"EnabledWithCount"},"source":"<a href=\"http://twitter.com/download/iphone\" rel=\"nofollow\">Twitter for iPhone</a>","legacy":{"created_at":"Sun Aug 13 22:06:28 +0000 2023","conversation_id_str":"1690844480126238720","display_text_range":[12,93],"entities":{"user_mentions":[{"id_str":"897058816226844672","name":"CCTV IDIOTS","screen_name":"cctvidiots","indices":[0,11]},{"id_str":"69266428","name":"MTN Nigeria","screen_name":"MTNNG","indices":[12,18]},{"id_str":"611632849","name":"MTN Nigeria Support","screen_name":"MTN180","indices":[19,26]}],"urls":[],"hashtags":[],"symbols":[]},"favorite_count":1,"favorited":false,"full_text":"@cctvidiots @MTNNG @MTN180 I can’t even stream lessthan a minute clips in peace… pls fixed up","in_reply_to_screen_name":"cctvidiots","in_reply_to_status_id_str":"1690844480126238720","in_reply_to_user_id_str":"897058816226844672","is_quote_status":false,"lang":"en","quote_count":0,"reply_count":1,"retweet_count":0,"retweeted":false,"user_id_str":"455509469","id_str":"1690847314972233728"},"quick_promote_eligibility":{"eligibility":"IneligibleNotProfessional"}}},"tweetDisplayType":"Tweet"},"clientEventInfo":{"details":{"conversationDetails":{"conversationSection":"HighQuality"},"timelinesDetails":{"controllerData":"DAACDAAEDAABCgABFIgKiCgLAAUKAAIAAAAABQRACAAAAAA="}}}}},{"entryId":"conversationthread-1690847314972233728-tweet-1690849024931196928","item":{"itemContent":{"itemType":"TimelineTweet","__typename":"TimelineTweet","tweet_results":{"result":{"__typename":"Tweet","rest_id":"1690849024931196928","has_birdwatch_notes":false,"core":{"user_results":{"result":{"__typename":"User","id":"VXNlcjo2MTE2MzI4NDk=","rest_id":"611632849","affiliates_highlighted_label":{},"has_graduated_access":true,"is_blue_verified":true,"legacy":{"can_dm":true,"can_media_tag":true,"created_at":"Mon Jun 18 12:05:21 +0000 2012","default_profile":true,"default_profile_image":false,"description":"This is the official twitter page for MTN Nigeria Customer Support","entities":{"description":{"urls":[]}},"fast_followers_count":0,"favourites_count":4827,"followers_count":567570,"friends_count":148790,"has_custom_timelines":true,"is_translator":false,"listed_count":615,"location":"MTN Plaza, Lagos, Nigeria","media_count":15491,"name":"MTN Nigeria Support","normal_followers_count":567570,"pinned_tweet_ids_str":["1605192928934219779"],"possibly_sensitive":false,"profile_banner_url":"https://pbs.twimg.com/profile_banners/611632849/1682581532","profile_image_url_https":"https://pbs.twimg.com/profile_images/1651492669477076992/AGpL0Y5S_normal.jpg","profile_interstitial_type":"","screen_name":"MTN180","statuses_count":792973,"translator_type":"none","verified":false,"want_retweets":false,"withheld_in_countries":[]},"professional":{"rest_id":"1581652187444379650","professional_type":"Business","category":[{"id":934,"name":"Social Media Influencer","icon_name":"IconBriefcaseStroke"}]},"smart_blocked_by":false,"smart_blocking":false,"business_account":{}}}},"edit_control":{"edit_tweet_ids":["1690849024931196928"],"editable_until_msecs":"1691968396000","is_edit_eligible":false,"edits_remaining":"5"},"is_translatable":false,"views":{"count":"3046","state":"EnabledWithCount"},"source":"<a href=\"https://www.ringcentral.com/digital-customer-engagement.html\" rel=\"nofollow\">RC Engage Digital EU</a>","legacy":{"created_at":"Sun Aug 13 22:13:16 +0000 2023","conversation_id_str":"1690844480126238720","display_text_range":[24,194],"entities":{"user_mentions":[{"id_str":"455509469","name":"♥♣ Absolute FEM!! 🤫♣♥","screen_name":"Iam_Hydrologist","indices":[0,16]},{"id_str":"69266428","name":"MTN Nigeria","screen_name":"MTNNG","indices":[17,23]}],"urls":[],"hashtags":[],"symbols":[]},"favorite_count":2,"favorited":false,"full_text":"@Iam_Hydrologist @MTNNG Y'ello. Thank you for contacting the MTN Digital Chat Channel.\nSincere apologies for the experience you had. Please share the affected phone number via DM for checks. ^OA","in_reply_to_screen_name":"Iam_Hydrologist","in_reply_to_status_id_str":"1690847314972233728","in_reply_to_user_id_str":"455509469","is_quote_status":false,"lang":"en","quote_count":0,"reply_count":0,"retweet_count":0,"retweeted":false,"user_id_str":"611632849","id_str":"1690849024931196928"},"quick_promote_eligibility":{"eligibility":"IneligibleNotProfessional"}}},"tweetDisplayType":"Tweet"},"clientEventInfo":{"details":{"conversationDetails":{"conversationSection":"HighQuality"},"timelinesDetails":{"controllerData":"DAACDAAEDAABCgABFMgKkDALAAEKAAIAAAAAFARACAAAAAA="}}}}}],"displayType":"VerticalConversation","clientEventInfo":{"details":{"conversationDetails":{"conversationSection":"HighQuality"}}}}},{"entryId":"conversationthread-1690847665674653696","sortIndex":"7532527556728536957","content":{"entryType":"TimelineTimelineModule","__typename":"TimelineTimelineModule","items":[{"entryId":"conversationthread-1690847665674653696-tweet-1690847665674653696","item":{"itemContent":{"itemType":"TimelineTweet","__typename":"TimelineTweet","tweet_results":{"result":{"__typename":"Tweet","rest_id":"1690847665674653696","has_birdwatch_notes":false,"core":{"user_results":{"result":{"__typename":"User","id":"VXNlcjo0Nzk3NTk4NjY2","rest_id":"4797598666","affiliates_highlighted_label":{},"has_graduated_access":true,"is_blue_verified":true,"legacy":{"can_dm":true,"can_media_tag":false,"created_at":"Wed Jan 13 20:45:07 +0000 2016","default_profile":true,"default_profile_image":false,"description":"Web3, #BTC PFP: @LostMinersEth","entities":{"description":{"urls":[]}},"fast_followers_count":0,"favourites_count":5864,"followers_count":1087,"friends_count":602,"has_custom_timelines":false,"is_translator":false,"listed_count":7,"location":"","media_count":109,"name":"Sung","normal_followers_count":1087,"pinned_tweet_ids_str":[],"possibly_sensitive":false,"profile_banner_url":"https://pbs.twimg.com/profile_banners/4797598666/1675733419","profile_image_url_https":"https://pbs.twimg.com/profile_images/1648026816991449088/h3zWYhuc_normal.png","profile_interstitial_type":"","screen_name":"sung_0701","statuses_count":2792,"translator_type":"none","verified":false,"want_retweets":false,"withheld_in_countries":[]},"professional":{"rest_id":"1647960893303451648","professional_type":"Creator","category":[]},"has_nft_avatar":true,"smart_blocked_by":false,"smart_blocking":false,"business_account":{}}}},"edit_control":{"edit_tweet_ids":["1690847665674653696"],"editable_until_msecs":"1691968072000","is_edit_eligible":false,"edits_remaining":"5"},"is_translatable":false,"views":{"count":"5979","state":"EnabledWithCount"},"source":"<a href=\"http://twitter.com/download/iphone\" rel=\"nofollow\">Twitter for iPhone</a>","legacy":{"created_at":"Sun Aug 13 22:07:52 +0000 2023","conversation_id_str":"1690844480126238720","display_text_range":[12,25],"entities":{"user_mentions":[{"id_str":"897058816226844672","name":"CCTV IDIOTS","screen_name":"cctvidiots","indices":[0,11]}],"urls":[],"hashtags":[],"symbols":[]},"favorite_count":13,"favorited":false,"full_text":"@cctvidiots They slapping","in_reply_to_screen_name":"cctvidiots","in_reply_to_status_id_str":"1690844480126238720","in_reply_to_user_id_str":"897058816226844672","is_quote_status":false,"lang":"en","quote_count":0,"reply_count":1,"retweet_count":0,"retweeted":false,"user_id_str":"4797598666","id_str":"1690847665674653696"},"quick_promote_eligibility":{"eligibility":"IneligibleNotProfessional"}}},"tweetDisplayType":"Tweet"},"clientEventInfo":{"details":{"conversationDetails":{"conversationSection":"HighQuality"},"timelinesDetails":{"controllerData":"DAACDAAEDAABCgABFIgaCCALABUKAAIAAAAAFARACAAAAAA="}}}}}],"displayType":"VerticalConversation","clientEventInfo":{"details":{"conversationDetails":{"conversationSection":"HighQuality"}}}}},{"entryId":"conversationthread-1690846488543313921","sortIndex":"7532527556728536947","content":{"entryType":"TimelineTimelineModule","__typename":"TimelineTimelineModule","items":[{"entryId":"conversationthread-1690846488543313921-tweet-1690846488543313921","item":{"itemContent":{"itemType":"TimelineTweet","__typename":"TimelineTweet","tweet_results":{"result":{"__typename":"Tweet","rest_id":"1690846488543313921","has_birdwatch_notes":false,"core":{"user_results":{"result":{"__typename":"User","id":"VXNlcjoxMTgyNzAwODk3MTMyMDcyOTYx","rest_id":"1182700897132072961","affiliates_highlighted_label":{},"has_graduated_access":true,"is_blue_verified":true,"legacy":{"can_dm":true,"can_media_tag":false,"created_at":"Fri Oct 11 16:54:09 +0000 2019","default_profile":true,"default_profile_image":false,"description":"Application Developer | 4 Years In Crypto | BAYC #9334 - Crypto Punk #9363 | Turn on notifications 📣","entities":{"description":{"urls":[]},"url":{"urls":[{"display_url":"t.me/+eA2eglcuaF5lZ…","expanded_url":"https://t.me/+eA2eglcuaF5lZjI5","url":"https://t.co/tKl3f58VFL","indices":[0,23]}]}},"fast_followers_count":0,"favourites_count":466529,"followers_count":81198,"friends_count":6879,"has_custom_timelines":true,"is_translator":false,"listed_count":19,"location":"Hawaii, USA","media_count":290,"name":"Dints","normal_followers_count":81198,"pinned_tweet_ids_str":[],"possibly_sensitive":false,"profile_banner_url":"https://pbs.twimg.com/profile_banners/1182700897132072961/1686261463","profile_image_url_https":"https://pbs.twimg.com/profile_images/1666927461362221056/Cb5LGjRF_normal.jpg","profile_interstitial_type":"","screen_name":"DintsWGMI","statuses_count":5044,"translator_type":"none","url":"https://t.co/tKl3f58VFL","verified":false,"want_retweets":false,"withheld_in_countries":[]},"professional":{"rest_id":"1580238460346048514","professional_type":"Creator","category":[]},"smart_blocked_by":false,"smart_blocking":false,"business_account":{}}}},"edit_control":{"edit_tweet_ids":["1690846488543313921"],"editable_until_msecs":"1691967791000","is_edit_eligible":false,"edits_remaining":"5"},"is_translatable":false,"views":{"count":"4029","state":"EnabledWithCount"},"source":"<a href=\"http://twitter.com/download/iphone\" rel=\"nofollow\">Twitter for iPhone</a>","legacy":{"created_at":"Sun Aug 13 22:03:11 +0000 2023","conversation_id_str":"1690844480126238720","display_text_range":[12,29],"entities":{"user_mentions":[{"id_str":"897058816226844672","name":"CCTV IDIOTS","screen_name":"cctvidiots","indices":[0,11]}],"urls":[],"hashtags":[],"symbols":[]},"favorite_count":4,"favorited":false,"full_text":"@cctvidiots so just slapping?","in_reply_to_screen_name":"cctvidiots","in_reply_to_status_id_str":"1690844480126238720","in_reply_to_user_id_str":"897058816226844672","is_quote_status":false,"lang":"en","quote_count":0,"reply_count":3,"retweet_count":0,"retweeted":false,"user_id_str":"1182700897132072961","id_str":"1690846488543313921"},"quick_promote_eligibility":{"eligibility":"IneligibleNotProfessional"}}},"tweetDisplayType":"Tweet"},"clientEventInfo":{"details":{"conversationDetails":{"conversationSection":"HighQuality"},"timelinesDetails":{"controllerData":"DAACDAAEDAABCgABFIgaCCALABUKAAIAAAAAFARACAAAAAA="}}}}},{"entryId":"conversationthread-1690846488543313921-cursor-showmore-8797161807570615378","item":{"itemContent":{"itemType":"TimelineTimelineCursor","__typename":"TimelineTimelineCursor","value":"PAAAAPAtPBwcFoKAuvWH-4v3LhUCAAAYJmNvbnZlcnNhdGlvbnRocmVhZC0xNjkwODQ2NDg4NTQzMzEzOTIxIgAA","cursorType":"ShowMore","displayTreatment":{"actionText":"Show replies"}},"clientEventInfo":{"details":{"conversationDetails":{"conversationSection":"HighQuality"}}}}}],"displayType":"VerticalConversation","clientEventInfo":{"details":{"conversationDetails":{"conversationSection":"HighQuality"}}}}},{"entryId":"conversationthread-1690850479499255808","sortIndex":"7532527556728536937","content":{"entryType":"TimelineTimelineModule","__typename":"TimelineTimelineModule","items":[{"entryId":"conversationthread-1690850479499255808-tweet-1690850479499255808","item":{"itemContent":{"itemType":"TimelineTweet","__typename":"TimelineTweet","tweet_results":{"result":{"__typename":"Tweet","rest_id":"1690850479499255808","has_birdwatch_notes":false,"core":{"user_results":{"result":{"__typename":"User","id":"VXNlcjoxNTkyNDIyOTgxOTU0Njk5MjY0","rest_id":"1592422981954699264","affiliates_highlighted_label":{},"has_graduated_access":true,"is_blue_verified":true,"legacy":{"can_dm":true,"can_media_tag":true,"created_at":"Tue Nov 15 07:43:31 +0000 2022","default_profile":true,"default_profile_image":false,"description":"Grandfather, computer scientist, executive, technology scoundrel, alpha nerd (old meaning, nothing to do with Chad wannabes).","entities":{"description":{"urls":[]}},"fast_followers_count":0,"favourites_count":1344,"followers_count":277,"friends_count":175,"has_custom_timelines":false,"is_translator":false,"listed_count":1,"location":"","media_count":68,"name":"Ted Warring","normal_followers_count":277,"pinned_tweet_ids_str":[],"possibly_sensitive":false,"profile_banner_url":"https://pbs.twimg.com/profile_banners/1592422981954699264/1673043432","profile_image_url_https":"https://pbs.twimg.com/profile_images/1592428759918923777/O4_oZKHo_normal.jpg","profile_interstitial_type":"","screen_name":"TedWarring","statuses_count":1677,"translator_type":"none","verified":false,"want_retweets":false,"withheld_in_countries":[]},"professional":{"rest_id":"1595543643313446912","professional_type":"Creator","category":[{"id":713,"name":"Science & Technology","icon_name":"IconBriefcaseStroke"}]},"smart_blocked_by":false,"smart_blocking":false,"business_account":{}}}},"edit_control":{"edit_tweet_ids":["1690850479499255808"],"editable_until_msecs":"1691968743000","is_edit_eligible":false,"edits_remaining":"5"},"is_translatable":false,"views":{"count":"32615","state":"EnabledWithCount"},"source":"<a href=\"https://mobile.twitter.com\" rel=\"nofollow\">Twitter Web App</a>","legacy":{"created_at":"Sun Aug 13 22:19:03 +0000 2023","conversation_id_str":"1690844480126238720","display_text_range":[12,70],"entities":{"user_mentions":[{"id_str":"897058816226844672","name":"CCTV IDIOTS","screen_name":"cctvidiots","indices":[0,11]}],"urls":[],"hashtags":[],"symbols":[]},"favorite_count":215,"favorited":false,"full_text":"@cctvidiots I like that version much better than here in the US style.","in_reply_to_screen_name":"cctvidiots","in_reply_to_status_id_str":"1690844480126238720","in_reply_to_user_id_str":"897058816226844672","is_quote_status":false,"lang":"en","quote_count":0,"reply_count":4,"retweet_count":1,"retweeted":false,"user_id_str":"1592422981954699264","id_str":"1690850479499255808"},"quick_promote_eligibility":{"eligibility":"IneligibleNotProfessional"}}},"tweetDisplayType":"Tweet"},"clientEventInfo":{"details":{"conversationDetails":{"conversationSection":"HighQuality"},"timelinesDetails":{"controllerData":"DAACDAAEDAABCgABFIgKCCALABUKAAIAAAAAFARACAAAAAA="}}}}},{"entryId":"conversationthread-1690850479499255808-cursor-showmore-6897831174318590228","item":{"itemContent":{"itemType":"TimelineTimelineCursor","__typename":"TimelineTimelineCursor","value":"PAAAAPAtPBwcFoCA0e2u4433LhUCAAAYJmNvbnZlcnNhdGlvbnRocmVhZC0xNjkwODUwNDc5NDk5MjU1ODA4IgAA","cursorType":"ShowMore","displayTreatment":{"actionText":"Show replies"}},"clientEventInfo":{"details":{"conversationDetails":{"conversationSection":"HighQuality"}}}}}],"displayType":"VerticalConversation","clientEventInfo":{"details":{"conversationDetails":{"conversationSection":"HighQuality"}}}}},{"entryId":"conversationthread-1690846239137624065","sortIndex":"7532527556728536927","content":{"entryType":"TimelineTimelineModule","__typename":"TimelineTimelineModule","items":[{"entryId":"conversationthread-1690846239137624065-tweet-1690846239137624065","item":{"itemContent":{"itemType":"TimelineTweet","__typename":"TimelineTweet","tweet_results":{"result":{"__typename":"Tweet","rest_id":"1690846239137624065","has_birdwatch_notes":false,"core":{"user_results":{"result":{"__typename":"User","id":"VXNlcjoxMzk1MjM5MzI1Njk3MDczMTYw","rest_id":"1395239325697073160","affiliates_highlighted_label":{},"has_graduated_access":true,"is_blue_verified":true,"legacy":{"can_dm":false,"can_media_tag":true,"created_at":"Thu May 20 04:46:01 +0000 2021","default_profile":true,"default_profile_image":false,"description":"📺 Welcome to Nice Viddies. Twitters #1 source for all viral media | Please feel free to follow and interact on posts |🫙 Crypto Tip Jar: geniu$.eth","entities":{"description":{"urls":[]}},"fast_followers_count":0,"favourites_count":6919,"followers_count":849,"friends_count":223,"has_custom_timelines":true,"is_translator":false,"listed_count":5,"location":"Worldwide","media_count":635,"name":"Nice Viddies","normal_followers_count":849,"pinned_tweet_ids_str":[],"possibly_sensitive":false,"profile_banner_url":"https://pbs.twimg.com/profile_banners/1395239325697073160/1689736818","profile_image_url_https":"https://pbs.twimg.com/profile_images/1681171646156271616/nraFliNH_normal.jpg","profile_interstitial_type":"","screen_name":"niceviddies","statuses_count":5264,"translator_type":"none","verified":false,"want_retweets":false,"withheld_in_countries":[]},"professional":{"rest_id":"1683534070570156032","professional_type":"Business","category":[{"id":15,"name":"Entertainment & Recreation","icon_name":"IconBriefcaseStroke"}]},"smart_blocked_by":false,"smart_blocking":false,"business_account":{}}}},"edit_control":{"edit_tweet_ids":["1690846239137624065"],"editable_until_msecs":"1691967732000","is_edit_eligible":false,"edits_remaining":"5"},"is_translatable":false,"views":{"count":"27230","state":"EnabledWithCount"},"source":"<a href=\"http://twitter.com/download/iphone\" rel=\"nofollow\">Twitter for iPhone</a>","legacy":{"created_at":"Sun Aug 13 22:02:12 +0000 2023","conversation_id_str":"1690844480126238720","display_text_range":[12,51],"entities":{"user_mentions":[{"id_str":"897058816226844672","name":"CCTV IDIOTS","screen_name":"cctvidiots","indices":[0,11]}],"urls":[],"hashtags":[],"symbols":[]},"favorite_count":258,"favorited":false,"full_text":"@cctvidiots Using their hands and not guns. Respect","in_reply_to_screen_name":"cctvidiots","in_reply_to_status_id_str":"1690844480126238720","in_reply_to_user_id_str":"897058816226844672","is_quote_status":false,"lang":"en","quote_count":0,"reply_count":6,"retweet_count":3,"retweeted":false,"user_id_str":"1395239325697073160","id_str":"1690846239137624065"},"quick_promote_eligibility":{"eligibility":"IneligibleNotProfessional"}}},"tweetDisplayType":"Tweet"},"clientEventInfo":{"details":{"conversationDetails":{"conversationSection":"HighQuality"},"timelinesDetails":{"controllerData":"DAACDAAEDAABCgABFIgaCCALABUKAAIAAAAAFARACAAAAAA="}}}}},{"entryId":"conversationthread-1690846239137624065-cursor-showmore-5714376010601200758","item":{"itemContent":{"itemType":"TimelineTimelineCursor","__typename":"TimelineTimelineCursor","value":"PAAAAPAtPBwcFoLA09nF7Iv3LhUCAAAYJmNvbnZlcnNhdGlvbnRocmVhZC0xNjkwODQ2MjM5MTM3NjI0MDY1IgAA","cursorType":"ShowMore","displayTreatment":{"actionText":"Show replies"}},"clientEventInfo":{"details":{"conversationDetails":{"conversationSection":"HighQuality"}}}}}],"displayType":"VerticalConversation","clientEventInfo":{"details":{"conversationDetails":{"conversationSection":"HighQuality"}}}}},{"entryId":"conversationthread-1690844676427767809","sortIndex":"7532527556728536917","content":{"entryType":"TimelineTimelineModule","__typename":"TimelineTimelineModule","items":[{"entryId":"conversationthread-1690844676427767809-tweet-1690844676427767809","item":{"itemContent":{"itemType":"TimelineTweet","__typename":"TimelineTweet","tweet_results":{"result":{"__typename":"Tweet","rest_id":"1690844676427767809","has_birdwatch_notes":false,"core":{"user_results":{"result":{"__typename":"User","id":"VXNlcjozMDk0ODIzMTc=","rest_id":"309482317","affiliates_highlighted_label":{},"has_graduated_access":true,"is_blue_verified":true,"legacy":{"can_dm":true,"can_media_tag":true,"created_at":"Thu Jun 02 04:56:19 +0000 2011","default_profile":false,"default_profile_image":false,"description":"Nutritionist. Pluviophile. Librocubicularist.","entities":{"description":{"urls":[]},"url":{"urls":[{"display_url":"linkedin.com/in/abubakar-um…","expanded_url":"https://www.linkedin.com/in/abubakar-umar-b0367713b","url":"https://t.co/3igLLMpIPJ","indices":[0,23]}]}},"fast_followers_count":0,"favourites_count":1857,"followers_count":767,"friends_count":455,"has_custom_timelines":true,"is_translator":false,"listed_count":4,"location":"Nigeria","media_count":866,"name":"Abubakar Tanimu Umar","normal_followers_count":767,"pinned_tweet_ids_str":["1109354589487284225"],"possibly_sensitive":false,"profile_banner_url":"https://pbs.twimg.com/profile_banners/309482317/1670743988","profile_image_url_https":"https://pbs.twimg.com/profile_images/1601841463129686016/0OmgOIyN_normal.jpg","profile_interstitial_type":"","screen_name":"Prince_Bukar","statuses_count":26858,"translator_type":"none","url":"https://t.co/3igLLMpIPJ","verified":false,"want_retweets":false,"withheld_in_countries":[]},"professional":{"rest_id":"1558843003267055616","professional_type":"Creator","category":[{"id":604,"name":"Nutritionist","icon_name":"IconBriefcaseStroke"}]},"smart_blocked_by":false,"smart_blocking":false,"business_account":{}}}},"edit_control":{"edit_tweet_ids":["1690844676427767809"],"editable_until_msecs":"1691967359000","is_edit_eligible":false,"edits_remaining":"5"},"is_translatable":false,"views":{"count":"8476","state":"EnabledWithCount"},"source":"<a href=\"http://twitter.com/download/iphone\" rel=\"nofollow\">Twitter for iPhone</a>","legacy":{"created_at":"Sun Aug 13 21:55:59 +0000 2023","conversation_id_str":"1690844480126238720","display_text_range":[12,42],"entities":{"user_mentions":[{"id_str":"897058816226844672","name":"CCTV IDIOTS","screen_name":"cctvidiots","indices":[0,11]}],"urls":[],"hashtags":[],"symbols":[]},"favorite_count":5,"favorited":false,"full_text":"@cctvidiots Woah.. That’s a lot of hands 😂","in_reply_to_screen_name":"cctvidiots","in_reply_to_status_id_str":"1690844480126238720","in_reply_to_user_id_str":"897058816226844672","is_quote_status":false,"lang":"en","quote_count":0,"reply_count":1,"retweet_count":0,"retweeted":false,"user_id_str":"309482317","id_str":"1690844676427767809"},"quick_promote_eligibility":{"eligibility":"IneligibleNotProfessional"}}},"tweetDisplayType":"Tweet"},"clientEventInfo":{"details":{"conversationDetails":{"conversationSection":"HighQuality"},"timelinesDetails":{"controllerData":"DAACDAAEDAABCgABFIgKCCALABUKAAIAAAAAFARACAAAAAA="}}}}}],"displayType":"VerticalConversation","clientEventInfo":{"details":{"conversationDetails":{"conversationSection":"HighQuality"}}}}},{"entryId":"cursor-bottom-394979265862220095","sortIndex":"7532527556728536916","content":{"entryType":"TimelineTimelineItem","__typename":"TimelineTimelineItem","itemContent":{"itemType":"TimelineTimelineCursor","__typename":"TimelineTimelineCursor","value":"pAAAAPAOHBn2EYDAusXL-JP3LoKAs83KkYv3LoDA2NHDiMMJAFCyxfiNixsAQbr1h_sbAFG12b38yAkAwMmf5af3LoLAvM3d6yQAUMDT2cXsJABggLXBn7yOCQBQ0e2u440tAFCwncq_jAkAQb6llasJAEHQjaeaGwBR1YGdza8kADGph6ZjAODclZi-ovcuJQISFQQAAA","cursorType":"Bottom"}}}]},{"type":"TimelineTerminateTimeline","direction":"Top"}]}}}