{"data":{"threaded_conversation_with_injections_v2":{"instructions":[{"type":"TimelineAddEntries","entries":[{"entryId":"conversationthread-1682788257711419392","sortIndex":"7540825180044900509","content":{"entryType":"TimelineTimelineModule","__typename":"TimelineTimelineModule","items":[{"entryId":"conversationthread-1682788257711419392-tweet-1682788257711419392","item":{"itemContent":{"itemType":"TimelineTweet","__typename":"TimelineTweet","tweet_results":{"result":{"__typename":"Tweet","rest_id":"1682788257711419392","has_birdwatch_notes":false,"core":{"user_results":{"result":{"__typename":"User","id":"VXNlcjoxNTI3MDg2NTY1MDQxODc2OTky","rest_id":"1527086565041876992","affiliates_highlighted_label":{},"has_graduated_access":true,"is_blue_verified":false,"legacy":{"can_dm":false,"can_media_tag":true,"created_at":"Thu May 19 00:39:53 +0000 2022","default_profile":true,"default_profile_image":false,"description":"Hey y’all welcome to my  “Going deeper with Uniqua” twitter page where we get deep. We heal , when we become more aware, enlightened,&connected.❤️","entities":{"description":{"urls":[]}},"fast_followers_count":0,"favourites_count":2643,"followers_count":46,"friends_count":40,"has_custom_timelines":true,"is_translator":false,"listed_count":0,"location":"","media_count":5,"name":"Going deeper with uniqua","normal_followers_count":46,"pinned_tweet_ids_str":["1666108046773219332"],"possibly_sensitive":false,"profile_banner_url":"https://pbs.twimg.com/profile_banners/1527086565041876992/1652921783","profile_image_url_https":"https://pbs.twimg.com/profile_images/1527093895787646976/dNp-NI4V_normal.jpg","profile_interstitial_type":"","screen_name":"DeeperWitUniqua","statuses_count":2819,"translator_type":"none","verified":false,"want_retweets":false,"withheld_in_countries":[]},"smart_blocked_by":false,"smart_blocking":false,"business_account":{}}}},"edit_control":{"edit_tweet_ids":["1682788257711419392"],"editable_until_msecs":"1690046559000","is_edit_eligible":false,"edits_remaining":"5"},"edit_perspective":{"favorited":false,"retweeted":false},"is_translatable":false,"views":{"count":"57","state":"EnabledWithCount"},"source":"<a href=\"http://twitter.com/download/iphone\" rel=\"nofollow\">Twitter for iPhone</a>","legacy":{"created_at":"Sat Jul 22 16:22:39 +0000 2023","conversation_id_str":"1682546856809873408","display_text_range":[17,193],"entities":{"user_mentions":[{"id_str":"918207822","name":"Shannonnn sharpes Burner (PARODY Account)","screen_name":"shannonsharpeee","indices":[0,16]}],"urls":[],"hashtags":[],"symbols":[]},"favorite_count":1,"favorited":false,"full_text":"@shannonsharpeee Hello levees broke all over rivers and lakes drying up things shifting so this is not uncommon we gone see whole lot in our beaches water before it’s over with so just be aware","in_reply_to_screen_name":"shannonsharpeee","in_reply_to_status_id_str":"1682546856809873408","in_reply_to_user_id_str":"918207822","is_quote_status":false,"lang":"en","quote_count":0,"reply_count":0,"retweet_count":0,"retweeted":false,"user_id_str":"1527086565041876992","id_str":"1682788257711419392"},"quick_promote_eligibility":{"eligibility":"IneligibleNotProfessional"}}},"tweetDisplayType":"Tweet"},"clientEventInfo":{"details":{"conversationDetails":{"conversationSection":"HighQuality"},"timelinesDetails":{"controllerData":"DAACDAAEDAABCgABFIAKiCAPAAUKAAIAAAAABARACAAAAAA="}}}}}],"displayType":"VerticalConversation","clientEventInfo":{"details":{"conversationDetails":{"conversationSection":"HighQuality"}}}}},{"entryId":"conversationthread-1682875951359881216","sortIndex":"7540825180044900499","content":{"entryType":"TimelineTimelineModule","__typename":"TimelineTimelineModule","items":[{"entryId":"conversationthread-1682875951359881216-tweet-1682875951359881216","item":{"itemContent":{"itemType":"TimelineTweet","__typename":"TimelineTweet","tweet_results":{"result":{"__typename":"Tweet","rest_id":"1682875951359881216","has_birdwatch_notes":false,"core":{"user_results":{"result":{"__typename":"User","id":"VXNlcjo5MzUyNTIwMTY3ODMyMjg5Mjg=","rest_id":"935252016783228928","affiliates_highlighted_label":{},"has_graduated_access":true,"is_blue_verified":false,"legacy":{"can_dm":true,"can_media_tag":false,"created_at":"Mon Nov 27 21:00:31 +0000 2017","default_profile":false,"default_profile_image":false,"description":"","entities":{"description":{"urls":[]}},"fast_followers_count":0,"favourites_count":7022,"followers_count":96,"friends_count":1027,"has_custom_timelines":true,"is_translator":false,"listed_count":0,"location":"So cal","media_count":67,"name":"j.b","normal_followers_count":96,"pinned_tweet_ids_str":["1482011068259979264"],"possibly_sensitive":false,"profile_banner_url":"https://pbs.twimg.com/profile_banners/935252016783228928/1677840232","profile_image_url_https":"https://pbs.twimg.com/profile_images/1441461313838858243/aQN496fC_normal.jpg","profile_interstitial_type":"","screen_name":"Ridethewave42","statuses_count":794,"translator_type":"none","verified":false,"want_retweets":false,"withheld_in_countries":[]},"smart_blocked_by":false,"smart_blocking":false,"business_account":{}}}},"edit_control":{"edit_tweet_ids":["1682875951359881216"],"editable_until_msecs":"1690067467000","is_edit_eligible":false,"edits_remaining":"5"},"edit_perspective":{"favorited":false,"retweeted":false},"is_translatable":false,"views":{"count":"4","state":"EnabledWithCount"},"source":"<a href=\"http://twitter.com/download/iphone\" rel=\"nofollow\">Twitter for iPhone</a>","legacy":{"created_at":"Sat Jul 22 22:11:07 +0000 2023","conversation_id_str":"1682546856809873408","display_text_range":[17,160],"entities":{"user_mentions":[{"id_str":"918207822","name":"Shannonnn sharpes Burner (PARODY Account)","screen_name":"shannonsharpeee","indices":[0,16]}],"urls":[],"hashtags":[],"symbols":[]},"favorite_count":0,"favorited":false,"full_text":"@shannonsharpeee They all had the opportunity to yell SHARK! at the top of their lungs and no one took it smh I’ve been wanting to do that ever since I saw jaws","in_reply_to_screen_name":"shannonsharpeee","in_reply_to_status_id_str":"1682546856809873408","in_reply_to_user_id_str":"918207822","is_quote_status":false,"lang":"en","quote_count":0,"reply_count":0,"retweet_count":0,"retweeted":false,"user_id_str":"935252016783228928","id_str":"1682875951359881216"},"quick_promote_eligibility":{"eligibility":"IneligibleNotProfessional"}}},"tweetDisplayType":"Tweet"},"clientEventInfo":{"details":{"conversationDetails":{"conversationSection":"HighQuality"},"timelinesDetails":{"controllerData":"DAACDAAEDAABCgABFIAKiCILAAUKAAIAAAAABARACAAAAAA="}}}}}],"displayType":"VerticalConversation","clientEventInfo":{"details":{"conversationDetails":{"conversationSection":"HighQuality"}}}}},{"entryId":"conversationthread-1682741020218236928","sortIndex":"7540825180044900489","content":{"entryType":"TimelineTimelineModule","__typename":"TimelineTimelineModule","items":[{"entryId":"conversationthread-1682741020218236928-tweet-1682741020218236928","item":{"itemContent":{"itemType":"TimelineTweet","__typename":"TimelineTweet","tweet_results":{"result":{"__typename":"Tweet","rest_id":"1682741020218236928","has_birdwatch_notes":false,"core":{"user_results":{"result":{"__typename":"User","id":"VXNlcjo1NTI4ODAyNjY=","rest_id":"552880266","affiliates_highlighted_label":{},"has_graduated_access":true,"is_blue_verified":false,"legacy":{"can_dm":false,"can_media_tag":false,"created_at":"Fri Apr 13 15:45:37 +0000 2012","default_profile":true,"default_profile_image":false,"description":"Ultimate Life, Pisces, Happiness, 313 is my number, no hate, SPADES 4 LIFE!!! Miami Dolphins HEAT Marlins Hurricanes Florida Panthers since the beginning!!","entities":{"description":{"urls":[]}},"fast_followers_count":0,"favourites_count":5436,"followers_count":135,"friends_count":239,"has_custom_timelines":false,"is_translator":false,"listed_count":1,"location":"","media_count":27,"name":"CURTIS","normal_followers_count":135,"pinned_tweet_ids_str":[],"possibly_sensitive":false,"profile_banner_url":"https://pbs.twimg.com/profile_banners/552880266/1387163053","profile_image_url_https":"https://pbs.twimg.com/profile_images/1605035729662476289/hzevmTom_normal.jpg","profile_interstitial_type":"","screen_name":"curtisnbwoods","statuses_count":4995,"translator_type":"none","verified":false,"want_retweets":false,"withheld_in_countries":[]},"smart_blocked_by":false,"smart_blocking":false,"business_account":{}}}},"edit_control":{"edit_tweet_ids":["1682741020218236928"],"editable_until_msecs":"1690035297000","is_edit_eligible":false,"edits_remaining":"5"},"edit_perspective":{"favorited":false,"retweeted":false},"is_translatable":false,"views":{"count":"26","state":"EnabledWithCount"},"source":"<a href=\"http://twitter.com/download/android\" rel=\"nofollow\">Twitter for Android</a>","legacy":{"created_at":"Sat Jul 22 13:14:57 +0000 2023","conversation_id_str":"1682546856809873408","display_text_range":[17,133],"entities":{"user_mentions":[{"id_str":"918207822","name":"Shannonnn sharpes Burner (PARODY Account)","screen_name":"shannonsharpeee","indices":[0,16]}],"urls":[],"hashtags":[],"symbols":[]},"favorite_count":2,"favorited":false,"full_text":"@shannonsharpeee It's playing like everyone else.. clearly avoiding swimming into anyone..  just welcoming everyone 2 it's front yard","in_reply_to_screen_name":"shannonsharpeee","in_reply_to_status_id_str":"1682546856809873408","in_reply_to_user_id_str":"918207822","is_quote_status":false,"lang":"en","quote_count":0,"reply_count":0,"retweet_count":0,"retweeted":false,"user_id_str":"552880266","id_str":"1682741020218236928"},"quick_promote_eligibility":{"eligibility":"IneligibleNotProfessional"}}},"tweetDisplayType":"Tweet"},"clientEventInfo":{"details":{"conversationDetails":{"conversationSection":"HighQuality"},"timelinesDetails":{"controllerData":"DAACDAAEDAABCgABFIAKiCQLAAUKAAIAAAAABAQgCAAAAAA="}}}}}],"displayType":"VerticalConversation","clientEventInfo":{"details":{"conversationDetails":{"conversationSection":"HighQuality"}}}}},{"entryId":"conversationthread-1682796145947430913","sortIndex":"7540825180044900479","content":{"entryType":"TimelineTimelineModule","__typename":"TimelineTimelineModule","items":[{"entryId":"conversationthread-1682796145947430913-tweet-1682796145947430913","item":{"itemContent":{"itemType":"TimelineTweet","__typename":"TimelineTweet","tweet_results":{"result":{"__typename":"Tweet","rest_id":"1682796145947430913","has_birdwatch_notes":false,"core":{"user_results":{"result":{"__typename":"User","id":"VXNlcjoxNDA0NjE5Nzk2NzgwNjYyNzg3","rest_id":"1404619796780662787","affiliates_highlighted_label":{},"has_graduated_access":true,"is_blue_verified":false,"legacy":{"can_dm":true,"can_media_tag":true,"created_at":"Tue Jun 15 02:03:58 +0000 2021","default_profile":true,"default_profile_image":false,"description":"","entities":{"description":{"urls":[]}},"fast_followers_count":0,"favourites_count":20979,"followers_count":86,"friends_count":339,"has_custom_timelines":true,"is_translator":false,"listed_count":1,"location":"Somewhere idk","media_count":126,"name":"TJR911","normal_followers_count":86,"pinned_tweet_ids_str":[],"possibly_sensitive":false,"profile_image_url_https":"https://pbs.twimg.com/profile_images/1477727452764033031/OpKjq5Jb_normal.jpg","profile_interstitial_type":"","screen_name":"TimGillis16","statuses_count":1187,"translator_type":"none","verified":false,"want_retweets":false,"withheld_in_countries":[]},"smart_blocked_by":false,"smart_blocking":false,"business_account":{}}}},"edit_control":{"edit_tweet_ids":["1682796145947430913"],"editable_until_msecs":"1690048440000","is_edit_eligible":false,"edits_remaining":"5"},"edit_perspective":{"favorited":false,"retweeted":false},"is_translatable":false,"views":{"count":"5","state":"EnabledWithCount"},"source":"<a href=\"http://twitter.com/download/iphone\" rel=\"nofollow\">Twitter for iPhone</a>","legacy":{"created_at":"Sat Jul 22 16:54:00 +0000 2023","conversation_id_str":"1682546856809873408","display_text_range":[17,139],"entities":{"user_mentions":[{"id_str":"918207822","name":"Shannonnn sharpes Burner (PARODY Account)","screen_name":"shannonsharpeee","indices":[0,16]}],"urls":[],"hashtags":[],"symbols":[]},"favorite_count":0,"favorited":false,"full_text":"@shannonsharpeee He said that long as he swim close to shore food comes in all shapes and sizes 😂 🤣😂🤣😂  keep messing around in them waters.","in_reply_to_screen_name":"shannonsharpeee","in_reply_to_status_id_str":"1682546856809873408","in_reply_to_user_id_str":"918207822","is_quote_status":false,"lang":"en","quote_count":0,"reply_count":0,"retweet_count":0,"retweeted":false,"user_id_str":"1404619796780662787","id_str":"1682796145947430913"},"quick_promote_eligibility":{"eligibility":"IneligibleNotProfessional"}}},"tweetDisplayType":"Tweet"},"clientEventInfo":{"details":{"conversationDetails":{"conversationSection":"HighQuality"},"timelinesDetails":{"controllerData":"DAACDAAEDAABCgABFIAaiCgLAAUKAAIAAAAABARACAAAAAA="}}}}}],"displayType":"VerticalConversation","clientEventInfo":{"details":{"conversationDetails":{"conversationSection":"HighQuality"}}}}},{"entryId":"conversationthread-1682745742723563522","sortIndex":"7540825180044900469","content":{"entryType":"TimelineTimelineModule","__typename":"TimelineTimelineModule","items":[{"entryId":"conversationthread-1682745742723563522-tweet-1682745742723563522","item":{"itemContent":{"itemType":"TimelineTweet","__typename":"TimelineTweet","tweet_results":{"result":{"__typename":"Tweet","rest_id":"1682745742723563522","has_birdwatch_notes":false,"core":{"user_results":{"result":{"__typename":"User","id":"VXNlcjoxNDg0OTg1NTYwMTc5NjU4NzUy","rest_id":"1484985560179658752","affiliates_highlighted_label":{},"has_graduated_access":true,"is_blue_verified":false,"legacy":{"can_dm":false,"can_media_tag":true,"created_at":"Sat Jan 22 20:25:38 +0000 2022","default_profile":true,"default_profile_image":false,"description":"@bass.ically_gvf on TikTok & insta | 18+ | top tier Danny girl | TOTS supremacy 🫶🏻","entities":{"description":{"urls":[]}},"fast_followers_count":0,"favourites_count":720,"followers_count":279,"friends_count":266,"has_custom_timelines":false,"is_translator":false,"listed_count":3,"location":"","media_count":62,"name":"bass.ically_gvf","normal_followers_count":279,"pinned_tweet_ids_str":[],"possibly_sensitive":false,"profile_banner_url":"https://pbs.twimg.com/profile_banners/1484985560179658752/1686091157","profile_image_url_https":"https://pbs.twimg.com/profile_images/1671239631608709121/RoUZ8YFD_normal.jpg","profile_interstitial_type":"","screen_name":"BASSically_gvf","statuses_count":371,"translator_type":"none","verified":false,"want_retweets":false,"withheld_in_countries":[]},"smart_blocked_by":false,"smart_blocking":false,"business_account":{}}}},"edit_control":{"edit_tweet_ids":["1682745742723563522"],"editable_until_msecs":"1690036423000","is_edit_eligible":false,"edits_remaining":"5"},"edit_perspective":{"favorited":false,"retweeted":false},"is_translatable":false,"views":{"count":"57","state":"EnabledWithCount"},"source":"<a href=\"http://twitter.com/download/iphone\" rel=\"nofollow\">Twitter for iPhone</a>","legacy":{"created_at":"Sat Jul 22 13:33:43 +0000 2023","conversation_id_str":"1682546856809873408","display_text_range":[17,153],"entities":{"user_mentions":[{"id_str":"918207822","name":"Shannonnn sharpes Burner (PARODY Account)","screen_name":"shannonsharpeee","indices":[0,16]}],"urls":[],"hashtags":[],"symbols":[]},"favorite_count":0,"favorited":false,"full_text":"@shannonsharpeee It is most likely a great hammerhead based on the location, dorsal fin size, and depth of water. They are very unlikely to bite a human…","in_reply_to_screen_name":"shannonsharpeee","in_reply_to_status_id_str":"1682546856809873408","in_reply_to_user_id_str":"918207822","is_quote_status":false,"lang":"en","quote_count":0,"reply_count":0,"retweet_count":0,"retweeted":false,"user_id_str":"1484985560179658752","id_str":"1682745742723563522"},"quick_promote_eligibility":{"eligibility":"IneligibleNotProfessional"}}},"tweetDisplayType":"Tweet"},"clientEventInfo":{"details":{"conversationDetails":{"conversationSection":"HighQuality"},"timelinesDetails":{"controllerData":"DAACDAAEDAABCgABFIAKiDALAAUKAAIAAAAABARACAAAAAA="}}}}}],"displayType":"VerticalConversation","clientEventInfo":{"details":{"conversationDetails":{"conversationSection":"HighQuality"}}}}},{"entryId":"conversationthread-1682611233634041857","sortIndex":"7540825180044900459","content":{"entryType":"TimelineTimelineModule","__typename":"TimelineTimelineModule","items":[{"entryId":"conversationthread-1682611233634041857-tweet-1682611233634041857","item":{"itemContent":{"itemType":"TimelineTweet","__typename":"TimelineTweet","tweet_results":{"result":{"__typename":"Tweet","rest_id":"1682611233634041857","has_birdwatch_notes":false,"core":{"user_results":{"result":{"__typename":"User","id":"VXNlcjo4OTk0NTE5MDcxMTAwMzk1NTI=","rest_id":"899451907110039552","affiliates_highlighted_label":{},"has_graduated_access":true,"is_blue_verified":false,"legacy":{"can_dm":true,"can_media_tag":false,"created_at":"Mon Aug 21 02:03:40 +0000 2017","default_profile":true,"default_profile_image":false,"description":"Living the Broom Life. ZphiB 💙","entities":{"description":{"urls":[]},"url":{"urls":[{"display_url":"morningbrew.com/daily/r/?kid=6…","expanded_url":"http://morningbrew.com/daily/r/?kid=6a42bd03","url":"https://t.co/JyY6fF9TEO","indices":[0,23]}]}},"fast_followers_count":0,"favourites_count":27754,"followers_count":1327,"friends_count":1357,"has_custom_timelines":true,"is_translator":false,"listed_count":3,"location":"North Carolina, USA","media_count":1119,"name":"The Dear Seer AKA Clair Lou","normal_followers_count":1327,"pinned_tweet_ids_str":["1627822924643151872"],"possibly_sensitive":false,"profile_banner_url":"https://pbs.twimg.com/profile_banners/899451907110039552/1509850665","profile_image_url_https":"https://pbs.twimg.com/profile_images/927006854546448384/uu5_Uw1p_normal.jpg","profile_interstitial_type":"","screen_name":"soprettyinlou","statuses_count":6216,"translator_type":"none","url":"https://t.co/JyY6fF9TEO","verified":false,"want_retweets":false,"withheld_in_countries":[]},"professional":{"rest_id":"1535344250099056640","professional_type":"Creator","category":[{"id":1010,"name":"Spiritual","icon_name":"IconBriefcaseStroke"}]},"smart_blocked_by":false,"smart_blocking":false,"business_account":{}}}},"edit_control":{"edit_tweet_ids":["1682611233634041857"],"editable_until_msecs":"1690004354000","is_edit_eligible":false,"edits_remaining":"5"},"edit_perspective":{"favorited":false,"retweeted":false},"is_translatable":false,"views":{"count":"144","state":"EnabledWithCount"},"source":"<a href=\"http://twitter.com/download/iphone\" rel=\"nofollow\">Twitter for iPhone</a>","legacy":{"created_at":"Sat Jul 22 04:39:14 +0000 2023","conversation_id_str":"1682546856809873408","display_text_range":[17,99],"entities":{"user_mentions":[{"id_str":"918207822","name":"Shannonnn sharpes Burner (PARODY Account)","screen_name":"shannonsharpeee","indices":[0,16]}],"urls":[],"hashtags":[],"symbols":[]},"favorite_count":0,"favorited":false,"full_text":"@shannonsharpeee So many questions. Does it’s belly itch? Is it trying to go viral on social media?","in_reply_to_screen_name":"shannonsharpeee","in_reply_to_status_id_str":"1682546856809873408","in_reply_to_user_id_str":"918207822","is_quote_status":false,"lang":"en","quote_count":0,"reply_count":0,"retweet_count":0,"retweeted":false,"user_id_str":"899451907110039552","id_str":"1682611233634041857"},"quick_promote_eligibility":{"eligibility":"IneligibleNotProfessional"}}},"tweetDisplayType":"Tweet"},"clientEventInfo":{"details":{"conversationDetails":{"conversationSection":"HighQuality"},"timelinesDetails":{"controllerData":"DAACDAAEDAABCgABFIAaCCALABUKAAIAAAAABARACAAAAAA="}}}}}],"displayType":"VerticalConversation","clientEventInfo":{"details":{"conversationDetails":{"conversationSection":"HighQuality"}}}}},{"entryId":"conversationthread-1682839420141961216","sortIndex":"7540825180044900449","content":{"entryType":"TimelineTimelineModule","__typename":"TimelineTimelineModule","items":[{"entryId":"conversationthread-1682839420141961216-tweet-1682839420141961216","item":{"itemContent":{"itemType":"TimelineTweet","__typename":"TimelineTweet","tweet_results":{"result":{"__typename":"Tweet","rest_id":"1682839420141961216","has_birdwatch_notes":false,"core":{"user_results":{"result":{"__typename":"User","id":"VXNlcjoxNTczMzc0NjEzMjUzMjc5NzYw","rest_id":"1573374613253279760","affiliates_highlighted_label":{},"has_graduated_access":true,"is_blue_verified":false,"legacy":{"can_dm":false,"can_media_tag":true,"created_at":"Fri Sep 23 18:12:01 +0000 2022","default_profile":true,"default_profile_image":false,"description":"RISP ❌\nSweep a series ❌\nGet a win streak ❌\nGood takes ❌\nPositive ❌\n\n(Padres/Chargers/Suns/Kings)\nAnyone who has an opposing view I OWN YOU HAHAH","entities":{"description":{"urls":[]}},"fast_followers_count":0,"favourites_count":67,"followers_count":13,"friends_count":40,"has_custom_timelines":false,"is_translator":false,"listed_count":0,"location":"Pain Diego","media_count":9,"name":"cereal man","normal_followers_count":13,"pinned_tweet_ids_str":["1676974429908381696"],"possibly_sensitive":false,"profile_banner_url":"https://pbs.twimg.com/profile_banners/1573374613253279760/1689885065","profile_image_url_https":"https://pbs.twimg.com/profile_images/1676066223057162248/SHdxXROB_normal.jpg","profile_interstitial_type":"","screen_name":"ughPadres","statuses_count":286,"translator_type":"none","verified":false,"want_retweets":false,"withheld_in_countries":[]},"smart_blocked_by":false,"smart_blocking":false,"business_account":{}}}},"edit_control":{"edit_tweet_ids":["1682839420141961216"],"editable_until_msecs":"1690058758000","is_edit_eligible":false,"edits_remaining":"5"},"edit_perspective":{"favorited":false,"retweeted":false},"is_translatable":false,"views":{"count":"8","state":"EnabledWithCount"},"source":"<a href=\"https://mobile.twitter.com\" rel=\"nofollow\">Twitter Web App</a>","legacy":{"created_at":"Sat Jul 22 19:45:58 +0000 2023","conversation_id_str":"1682546856809873408","display_text_range":[17,126],"entities":{"user_mentions":[{"id_str":"918207822","name":"Shannonnn sharpes Burner (PARODY Account)","screen_name":"shannonsharpeee","indices":[0,16]}],"urls":[],"hashtags":[],"symbols":[]},"favorite_count":0,"favorited":false,"full_text":"@shannonsharpeee What shark was it? Has to be a small one since so close to shore… Probably couldn’t do much if it did attack.","in_reply_to_screen_name":"shannonsharpeee","in_reply_to_status_id_str":"1682546856809873408","in_reply_to_user_id_str":"918207822","is_quote_status":false,"lang":"en","quote_count":0,"reply_count":0,"retweet_count":0,"retweeted":false,"user_id_str":"1573374613253279760","id_str":"1682839420141961216"},"quick_promote_eligibility":{"eligibility":"IneligibleNotProfessional"}}},"tweetDisplayType":"Tweet"},"clientEventInfo":{"details":{"conversationDetails":{"conversationSection":"HighQuality"},"timelinesDetails":{"controllerData":"DAACDAAEDAABCgABFIAKiCALAAUKAAIAAAAABARACAAAAAA="}}}}}],"displayType":"VerticalConversation","clientEventInfo":{"details":{"conversationDetails":{"conversationSection":"HighQuality"}}}}},{"entryId":"conversationthread-1682845378960404482","sortIndex":"7540825180044900439","content":{"entryType":"TimelineTimelineModule","__typename":"TimelineTimelineModule","items":[{"entryId":"conversationthread-1682845378960404482-tweet-1682845378960404482","item":{"itemContent":{"itemType":"TimelineTweet","__typename":"TimelineTweet","tweet_results":{"result":{"__typename":"Tweet","rest_id":"1682845378960404482","has_birdwatch_notes":false,"core":{"user_results":{"result":{"__typename":"User","id":"VXNlcjo1MDEzNzk1MA==","rest_id":"50137950","affiliates_highlighted_label":{},"has_graduated_access":true,"is_blue_verified":false,"legacy":{"can_dm":false,"can_media_tag":true,"created_at":"Tue Jun 23 23:23:38 +0000 2009","default_profile":false,"default_profile_image":false,"description":"I write screenplays, poetry, novels... My primary language is sarcasm, secondary is english.... Atheist","entities":{"description":{"urls":[]}},"fast_followers_count":0,"favourites_count":1303,"followers_count":94,"friends_count":435,"has_custom_timelines":false,"is_translator":false,"listed_count":0,"location":"FLA","media_count":624,"name":"UncleRicoDPrimo","normal_followers_count":94,"pinned_tweet_ids_str":["1661180746512445447"],"possibly_sensitive":false,"profile_banner_url":"https://pbs.twimg.com/profile_banners/50137950/1591254568","profile_image_url_https":"https://pbs.twimg.com/profile_images/1315919725281644544/gz02282A_normal.jpg","profile_interstitial_type":"","screen_name":"UncleRicoDPrimo","statuses_count":4047,"translator_type":"none","verified":false,"want_retweets":false,"withheld_in_countries":[]},"smart_blocked_by":false,"smart_blocking":false,"business_account":{}}}},"edit_control":{"edit_tweet_ids":["1682845378960404482"],"editable_until_msecs":"1690060178000","is_edit_eligible":false,"edits_remaining":"5"},"edit_perspective":{"favorited":false,"retweeted":false},"is_translatable":false,"views":{"state":"Enabled"},"source":"<a href=\"https://mobile.twitter.com\" rel=\"nofollow\">Twitter Web App</a>","legacy":{"created_at":"Sat Jul 22 20:09:38 +0000 2023","conversation_id_str":"1682546856809873408","display_text_range":[17,119],"entities":{"user_mentions":[{"id_str":"918207822","name":"Shannonnn sharpes Burner (PARODY Account)","screen_name":"shannonsharpeee","indices":[0,16]}],"urls":[],"hashtags":[],"symbols":[]},"favorite_count":0,"favorited":false,"full_text":"@shannonsharpeee They do this towards the end of every summer, they're looking for their food source which isn't humans","in_reply_to_screen_name":"shannonsharpeee","in_reply_to_status_id_str":"1682546856809873408","in_reply_to_user_id_str":"918207822","is_quote_status":false,"lang":"en","quote_count":0,"reply_count":0,"retweet_count":0,"retweeted":false,"user_id_str":"50137950","id_str":"1682845378960404482"},"quick_promote_eligibility":{"eligibility":"IneligibleNotProfessional"}}},"tweetDisplayType":"Tweet"},"clientEventInfo":{"details":{"conversationDetails":{"conversationSection":"HighQuality"},"timelinesDetails":{"controllerData":"DAACDAAEDAABCgABFIAaiCALAAUKAAIAAAAABARACAAAAAA="}}}}}],"displayType":"VerticalConversation","clientEventInfo":{"details":{"conversationDetails":{"conversationSection":"HighQuality"}}}}},{"entryId":"conversationthread-1682715668053884931","sortIndex":"7540825180044900429","content":{"entryType":"TimelineTimelineModule","__typename":"TimelineTimelineModule","items":[{"entryId":"conversationthread-1682715668053884931-tweet-1682715668053884931","item":{"itemContent":{"itemType":"TimelineTweet","__typename":"TimelineTweet","tweet_results":{"result":{"__typename":"Tweet","rest_id":"1682715668053884931","has_birdwatch_notes":false,"core":{"user_results":{"result":{"__typename":"User","id":"VXNlcjoxNTU5MzU5NTAzOTA0MTUzNjAw","rest_id":"1559359503904153600","affiliates_highlighted_label":{},"has_graduated_access":true,"is_blue_verified":false,"legacy":{"can_dm":false,"can_media_tag":true,"created_at":"Tue Aug 16 02:01:05 +0000 2022","default_profile":true,"default_profile_image":false,"description":"Liberal=blocked\nMy opinions, my thoughts, my feelings on tweets and sharing information, facts, and interesting happenings of new discoveries.","entities":{"description":{"urls":[]}},"fast_followers_count":0,"favourites_count":14387,"followers_count":222,"friends_count":390,"has_custom_timelines":true,"is_translator":false,"listed_count":1,"location":"","media_count":196,"name":"Prince4everPurpleYoda","normal_followers_count":222,"pinned_tweet_ids_str":["1664115441638203395"],"possibly_sensitive":false,"profile_banner_url":"https://pbs.twimg.com/profile_banners/1559359503904153600/1666940882","profile_image_url_https":"https://pbs.twimg.com/profile_images/1585891118977323009/KXWtp4Wt_normal.jpg","profile_interstitial_type":"","screen_name":"Christi57966479","statuses_count":12100,"translator_type":"none","verified":false,"want_retweets":false,"withheld_in_countries":[]},"smart_blocked_by":false,"smart_blocking":false,"business_account":{}}}},"edit_control":{"edit_tweet_ids":["1682715668053884931"],"editable_until_msecs":"1690029253000","is_edit_eligible":false,"edits_remaining":"5"},"edit_perspective":{"favorited":false,"retweeted":false},"is_translatable":false,"views":{"count":"248","state":"EnabledWithCount"},"source":"<a href=\"https://mobile.twitter.com\" rel=\"nofollow\">Twitter Web App</a>","legacy":{"created_at":"Sat Jul 22 11:34:13 +0000 2023","conversation_id_str":"1682546856809873408","display_text_range":[17,175],"entities":{"user_mentions":[{"id_str":"918207822","name":"Shannonnn sharpes Burner (PARODY Account)","screen_name":"shannonsharpeee","indices":[0,16]}],"urls":[],"hashtags":[],"symbols":[]},"favorite_count":1,"favorited":false,"full_text":"@shannonsharpeee It's amazing it didn't get stuck on the shore. He was really close to the land. Didn't seem like he was hunting for food cause he had chances to get many ppl.","in_reply_to_screen_name":"shannonsharpeee","in_reply_to_status_id_str":"1682546856809873408","in_reply_to_user_id_str":"918207822","is_quote_status":false,"lang":"en","quote_count":0,"reply_count":0,"retweet_count":0,"retweeted":false,"user_id_str":"1559359503904153600","id_str":"1682715668053884931"},"quick_promote_eligibility":{"eligibility":"IneligibleNotProfessional"}}},"tweetDisplayType":"Tweet"},"clientEventInfo":{"details":{"conversationDetails":{"conversationSection":"HighQuality"},"timelinesDetails":{"controllerData":"DAACDAAEDAABCgABFIAKiCALAAUKAAIAAAAABARACAAAAAA="}}}}}],"displayType":"VerticalConversation","clientEventInfo":{"details":{"conversationDetails":{"conversationSection":"HighQuality"}}}}},{"entryId":"conversationthread-1682858672232230919","sortIndex":"7540825180044900419","content":{"entryType":"TimelineTimelineModule","__typename":"TimelineTimelineModule","items":[{"entryId":"conversationthread-1682858672232230919-tweet-1682858672232230919","item":{"itemContent":{"itemType":"TimelineTweet","__typename":"TimelineTweet","tweet_results":{"result":{"__typename":"Tweet","rest_id":"1682858672232230919","has_birdwatch_notes":false,"core":{"user_results":{"result":{"__typename":"User","id":"VXNlcjoxNTQyMjczNDM4MzE1ODY0MDY0","rest_id":"1542273438315864064","affiliates_highlighted_label":{},"has_graduated_access":true,"is_blue_verified":false,"legacy":{"can_dm":false,"can_media_tag":true,"created_at":"Wed Jun 29 22:29:55 +0000 2022","default_profile":true,"default_profile_image":false,"description":"Native New Yorker. Pushing the agenda for the best franchise and best fan base in basketball #Knicks #NewYorkForever","entities":{"description":{"urls":[]}},"fast_followers_count":0,"favourites_count":2061,"followers_count":58,"friends_count":107,"has_custom_timelines":true,"is_translator":false,"listed_count":0,"location":"Central Harlem, Manhattan","media_count":139,"name":"Knicks Agenda","normal_followers_count":58,"pinned_tweet_ids_str":[],"possibly_sensitive":false,"profile_image_url_https":"https://pbs.twimg.com/profile_images/1652044019780792320/uXLdeeyS_normal.jpg","profile_interstitial_type":"","screen_name":"Knicksagenda","statuses_count":4244,"translator_type":"none","verified":false,"want_retweets":false,"withheld_in_countries":[]},"professional":{"rest_id":"1565455050016804864","professional_type":"Creator","category":[{"id":800,"name":"Sports, Fitness & Recreation","icon_name":"IconBriefcaseStroke"}]},"smart_blocked_by":false,"smart_blocking":false,"business_account":{}}}},"edit_control":{"edit_tweet_ids":["1682858672232230919"],"editable_until_msecs":"1690063348000","is_edit_eligible":false,"edits_remaining":"5"},"edit_perspective":{"favorited":false,"retweeted":false},"is_translatable":false,"views":{"count":"4","state":"EnabledWithCount"},"source":"<a href=\"https://mobile.twitter.com\" rel=\"nofollow\">Twitter Web App</a>","legacy":{"created_at":"Sat Jul 22 21:02:28 +0000 2023","conversation_id_str":"1682546856809873408","display_text_range":[17,146],"entities":{"user_mentions":[{"id_str":"918207822","name":"Shannonnn sharpes Burner (PARODY Account)","screen_name":"shannonsharpeee","indices":[0,16]}],"urls":[],"hashtags":[],"symbols":[]},"favorite_count":0,"favorited":false,"full_text":"@shannonsharpeee I know you not supposed to panic and splash too much but they moving too slow for me. I would’ve thrown my kids on to that beach.","in_reply_to_screen_name":"shannonsharpeee","in_reply_to_status_id_str":"1682546856809873408","in_reply_to_user_id_str":"918207822","is_quote_status":false,"lang":"en","quote_count":0,"reply_count":0,"retweet_count":0,"retweeted":false,"user_id_str":"1542273438315864064","id_str":"1682858672232230919"},"quick_promote_eligibility":{"eligibility":"IneligibleNotProfessional"}}},"tweetDisplayType":"Tweet"},"clientEventInfo":{"details":{"conversationDetails":{"conversationSection":"HighQuality"},"timelinesDetails":{"controllerData":"DAACDAAEDAABCgABFIAaiCALAAUKAAIAAAAABARACAAAAAA="}}}}}],"displayType":"VerticalConversation","clientEventInfo":{"details":{"conversationDetails":{"conversationSection":"HighQuality"}}}}},{"entryId":"cursor-bottom-7785789981964995627","sortIndex":"7540825180044900418","content":{"entryType":"TimelineTimelineItem","__typename":"TimelineTimelineItem","itemContent":{"itemType":"TimelineTimelineCursor","__typename":"TimelineTimelineCursor","value":"AgcAAPAPHBn2xgGAgLax5fiE2i6CwLPN4af82S6AgLONkaPOCQBQvJ2E8cUbAPARvYWzspfaLoDA0M2fps_ZLoKAsOWvyqbaLoTA0OXNmJYJAPAI05njx5TaLoyA0qmP3r3aLoCAsLmr4tI2AOCz0aXAu9ougoC83ciOwhIAUL2h1IupEgDhseHW76raLoSAscnCu882AEDNhO3rCQBQvqHnwa8JAFDUzdnZ1GMAUL6Rz4LNEgBRsbnLhrWQAEHZqJHUkABA8aSrsxsAUNPZzpzmCQBQvLG50dgJAFDQoejY4AkAUL3FnvfDCQBQtu2z6LJ-AFG-7cDtqnUAQdmPsKstANHR1LH12S6CwL793fviSAAxyebpWgBAse2QgNgAUcC-zfjRNgBRsfWq9c0tAEH5oZCZWgBC5Zuj1yQAMJTcsQ4BUbz58PC_GwBBsZDo5DYAQJGalsLzAEG-pfrFaAHgvem29fPZLoSAtsmZt9BxAVG-7b3tqwkAUdHB2JnacQEw_Mnp6gDgtuHYudfaLoaAvemoiccbAOHSkbmI69kuhoC2iZPfj34AQZHo1M6ZADGVuoloAVCzzcvvyH4AULO1jM_SGwBRvaXHxbxoAUHNzcmhXwFA8fK1qC0AUNDRjrKzEgBRvYGm_uTCAUHBpZTUMgHR3fPYs9ouiIC83cKjoWwAMcmjw6cBULat_NCk8wDSsKHZwbXaLoqAtoHg7gECQOWijLO0AFGwxYK_mgUBQIXJ14xjAFGzkf7avH8CQfH8h9wbAEHlz9n0FwFBmc77lUgAQK3Jt9t-AFG2sYyTrkkCQdmJh8UBAtKB6-Lm2i6GwLOltLDWsAExs6XTEgBA-fP7sKsAUb6Z7Y3J3QFBgYfCsmMAQfHagqZ_AjLB4K-5ATGVwb4yAWC9larB5dmZAEHNm_7TMgFBjcaRxMYAQaXPq6s2ANH9wqni2i6OwL3F7sDTGwBBtYjIpcYAQKXdkqIkAFDUkbvN35UBYLOt-dXO2cYAQbGn2spEAUCNx43X2ABQsfnLna5IAEGz2frC4QBgvcnWidXZUQAxye7wZAJRs6W31sX8AEGZ1cmoPANC-feG15UBMvHx420CMb3RyxcBQZnmgqLPAEDRpuHfzwBBs7HphFYBUtLtw6LXbQIxzuijPwAyqZOaDwNB8YnryOcDQfGO46HhADGt-KvdAVGzsYbroTwDQf32v4xfAUChheXN2ABRvY2fiNbHAkDt3vnGCQBRvdGa4tZIAEDBtrXUPwBQ0YX2xO_PAFHR2c6IsqsAQIXV_IQJAFHSreXkr20CUtnjju_ZaAEgy6WwAVGw4YSS0JoCQbmViOg_AEGFvbToXwFBgb_isQUBQZX0gbDLAUGBppSEKQFBqZyNpDYAQd2goZhNAUK5i4yYtQIx07vQVgFApd7X6UgAUdChl9jjxgBBsZ7d6JkAMfXa_Q4BUb7R796d8wBA6d6o63IDQbz9haL1BFG9rdfBtCQAQZXMiqRkAkDFg9KnywFRvrX50rJFA0GFmvHeRAFBmazo3w4BQPnTwv4_AOHS9fif09kuisCz4ZTtxtoEMf2xm90BUbDdssy8tABBgeW77bkBQcHkt8ACBEGdqYfVjAFBrdOv4gkAQY2QrNsbADHJuYtcBOG99cyIqtoupoCxkbbnzFEAQa3j8cJfATHhtu_GAFLTwYqurWQCMYvvokQBQL2C0cmxA1Gz7Yys3QoCQYG4-M75A0GNmL3V7wFB6bisufMAQf2BpLsbAEH5xKCCkQJAvZGA67kBQrHVj58BAkGdtcmlogAyodmJAwZB_cPu0NoEQKXMlagkAFGzxdH-jloAQrWg99nsBCDuoXwFYsDTnd6w42kDIpWCcgMhseyIAmGAtuHlzoBRADHFjrBuBFGx_ZOU0BAFQeWv2OCHAELxiPO2rAIxmPuO1AFBmYSutZkAQbHZoK5IANC9_P302S4lAhIVBAAA","cursorType":"Bottom"}}}]},{"type":"TimelineTerminateTimeline","direction":"Top"}]}}}