{"data":{"threaded_conversation_with_injections_v2":{"instructions":[{"type":"TimelineAddEntries","entries":[{"entryId":"conversationthread-1682567844045930496","sortIndex":"7540825180044902039","content":{"entryType":"TimelineTimelineModule","__typename":"TimelineTimelineModule","items":[{"entryId":"conversationthread-1682567844045930496-tweet-1682567844045930496","item":{"itemContent":{"itemType":"TimelineTweet","__typename":"TimelineTweet","tweet_results":{"result":{"__typename":"Tweet","rest_id":"1682567844045930496","has_birdwatch_notes":false,"core":{"user_results":{"result":{"__typename":"User","id":"VXNlcjo1NjI2NzU5NTc=","rest_id":"562675957","affiliates_highlighted_label":{},"has_graduated_access":true,"is_blue_verified":true,"legacy":{"can_dm":true,"can_media_tag":false,"created_at":"Wed Apr 25 07:26:37 +0000 2012","default_profile":true,"default_profile_image":false,"description":"here for the laughs. if ya chuckled give me a follow, I got way more stupid things to say!","entities":{"description":{"urls":[]}},"fast_followers_count":0,"favourites_count":1254,"followers_count":53,"friends_count":118,"has_custom_timelines":true,"is_translator":false,"listed_count":2,"location":"Lost","media_count":231,"name":"Kuki","normal_followers_count":53,"pinned_tweet_ids_str":[],"possibly_sensitive":true,"profile_banner_url":"https://pbs.twimg.com/profile_banners/562675957/1598638496","profile_image_url_https":"https://pbs.twimg.com/profile_images/1299410146733350913/4LLhJD8c_normal.jpg","profile_interstitial_type":"","screen_name":"Sackunit","statuses_count":1865,"translator_type":"none","verified":false,"want_retweets":false,"withheld_in_countries":[]},"professional":{"rest_id":"1652534159288717315","professional_type":"Creator","category":[{"id":935,"name":"Comedian","icon_name":"IconBriefcaseStroke"}]},"smart_blocked_by":false,"smart_blocking":false,"business_account":{}}}},"edit_control":{"edit_tweet_ids":["1682567844045930496"],"editable_until_msecs":"1689994009000","is_edit_eligible":false,"edits_remaining":"5"},"edit_perspective":{"favorited":false,"retweeted":false},"is_translatable":false,"views":{"count":"50646","state":"EnabledWithCount"},"source":"<a href=\"http://twitter.com/download/iphone\" rel=\"nofollow\">Twitter for iPhone</a>","legacy":{"created_at":"Sat Jul 22 01:46:49 +0000 2023","conversation_id_str":"1682546856809873408","display_text_range":[17,56],"entities":{"user_mentions":[{"id_str":"918207822","name":"Shannonnn sharpes Burner (PARODY Account)","screen_name":"shannonsharpeee","indices":[0,16]}],"urls":[],"hashtags":[],"symbols":[]},"favorite_count":171,"favorited":false,"full_text":"@shannonsharpeee Cocaine sharks be a real thing in Miami","in_reply_to_screen_name":"shannonsharpeee","in_reply_to_status_id_str":"1682546856809873408","in_reply_to_user_id_str":"918207822","is_quote_status":false,"lang":"en","quote_count":1,"reply_count":6,"retweet_count":2,"retweeted":false,"user_id_str":"562675957","id_str":"1682567844045930496"},"quick_promote_eligibility":{"eligibility":"IneligibleNotProfessional"}}},"tweetDisplayType":"Tweet"},"clientEventInfo":{"details":{"conversationDetails":{"conversationSection":"HighQuality"},"timelinesDetails":{"controllerData":"DAACDAAEDAABCgABFIAaCCAPABUKAAIAAAAAFQRACAAAAAA="}}}}},{"entryId":"conversationthread-1682567844045930496-cursor-showmore-538159306318919440","item":{"itemContent":{"itemType":"TimelineTimelineCursor","__typename":"TimelineTimelineCursor","value":"PAAAAPAtPBwcFoCA0u3DotfZLhUCAAAYJmNvbnZlcnNhdGlvbnRocmVhZC0xNjgyNTY3ODQ0MDQ1OTMwNDk2IgAA","cursorType":"ShowMore","displayTreatment":{"actionText":"Show replies"}},"clientEventInfo":{"details":{"conversationDetails":{"conversationSection":"HighQuality"}}}}}],"displayType":"VerticalConversation","clientEventInfo":{"details":{"conversationDetails":{"conversationSection":"HighQuality"}}}}},{"entryId":"conversationthread-1682548533512028160","sortIndex":"7540825180044902029","content":{"entryType":"TimelineTimelineModule","__typename":"TimelineTimelineModule","items":[{"entryId":"conversationthread-1682548533512028160-tweet-1682548533512028160","item":{"itemContent":{"itemType":"TimelineTweet","__typename":"TimelineTweet","tweet_results":{"result":{"__typename":"Tweet","rest_id":"1682548533512028160","has_birdwatch_notes":false,"core":{"user_results":{"result":{"__typename":"User","id":"VXNlcjoxNDIyMDEwNzMxODAxODU4MDUz","rest_id":"1422010731801858053","affiliates_highlighted_label":{},"has_graduated_access":true,"is_blue_verified":false,"legacy":{"can_dm":false,"can_media_tag":true,"created_at":"Mon Aug 02 01:46:00 +0000 2021","default_profile":true,"default_profile_image":false,"description":"Host of MostlyEverythingPodcast. Listen on @Soundcloud, @ApplePodcast, @Stitcher, @Spotify, @GooglePlay & @Anchor. #Jaguars","entities":{"description":{"urls":[]},"url":{"urls":[{"display_url":"itunes.apple.com/us/podcast/mos…","expanded_url":"https://itunes.apple.com/us/podcast/mostlyeverythingpodcast/id1366012920?mt=2","url":"https://t.co/g6PVhgxH2J","indices":[0,23]}]}},"fast_followers_count":0,"favourites_count":38107,"followers_count":363,"friends_count":922,"has_custom_timelines":true,"is_translator":false,"listed_count":3,"location":"Brooklyn, NY","media_count":2819,"name":"Reece 🇻🇨","normal_followers_count":363,"pinned_tweet_ids_str":[],"possibly_sensitive":false,"profile_banner_url":"https://pbs.twimg.com/profile_banners/1422010731801858053/1627870804","profile_image_url_https":"https://pbs.twimg.com/profile_images/1480577056106860549/g4vQn8xy_normal.jpg","profile_interstitial_type":"","screen_name":"nupersona","statuses_count":13278,"translator_type":"none","url":"https://t.co/g6PVhgxH2J","verified":false,"want_retweets":false,"withheld_in_countries":[]},"professional":{"rest_id":"1528583169783603203","professional_type":"Creator","category":[{"id":15,"name":"Entertainment & Recreation","icon_name":"IconBriefcaseStroke"}]},"smart_blocked_by":false,"smart_blocking":false,"business_account":{}}}},"edit_control":{"edit_tweet_ids":["1682548533512028160"],"editable_until_msecs":"1689989405000","is_edit_eligible":false,"edits_remaining":"5"},"edit_perspective":{"favorited":false,"retweeted":false},"is_translatable":false,"views":{"count":"297040","state":"EnabledWithCount"},"source":"<a href=\"http://twitter.com/download/iphone\" rel=\"nofollow\">Twitter for iPhone</a>","legacy":{"created_at":"Sat Jul 22 00:30:05 +0000 2023","conversation_id_str":"1682546856809873408","display_text_range":[17,40],"entities":{"user_mentions":[{"id_str":"918207822","name":"Shannonnn sharpes Burner (PARODY Account)","screen_name":"shannonsharpeee","indices":[0,16]}],"urls":[],"hashtags":[],"symbols":[]},"favorite_count":3317,"favorited":false,"full_text":"@shannonsharpeee Bro trying to see Messi","in_reply_to_screen_name":"shannonsharpeee","in_reply_to_status_id_str":"1682546856809873408","in_reply_to_user_id_str":"918207822","is_quote_status":false,"lang":"en","quote_count":16,"reply_count":26,"retweet_count":126,"retweeted":false,"user_id_str":"1422010731801858053","id_str":"1682548533512028160"},"quick_promote_eligibility":{"eligibility":"IneligibleNotProfessional"}}},"tweetDisplayType":"Tweet"},"clientEventInfo":{"details":{"conversationDetails":{"conversationSection":"HighQuality"},"timelinesDetails":{"controllerData":"DAACDAAEDAABCgABFIAKCCILABUKAAIAAAAABARACAAAAAA="}}}}},{"entryId":"conversationthread-1682548533512028160-tweet-1682581444277977088","item":{"itemContent":{"itemType":"TimelineTweet","__typename":"TimelineTweet","tweet_results":{"result":{"__typename":"Tweet","rest_id":"1682581444277977088","has_birdwatch_notes":false,"core":{"user_results":{"result":{"__typename":"User","id":"VXNlcjoxNTY3MTgxOTAyNzc1NDg0NDIw","rest_id":"1567181902775484420","affiliates_highlighted_label":{},"has_graduated_access":true,"is_blue_verified":true,"legacy":{"can_dm":false,"can_media_tag":true,"created_at":"Tue Sep 06 16:04:32 +0000 2022","default_profile":true,"default_profile_image":false,"description":"Lakers Nation!! The official Twitter of Lakers Over Everything. PURPLE & GOLD TIL WE DIE, PURPLE & GOLD WE RIDE. I BLEED PURPLE, MY HEART BEATS GOLD. IT'S LOE","entities":{"description":{"urls":[]},"url":{"urls":[{"display_url":"youtube.com/c/LakersOverEv…","expanded_url":"https://youtube.com/c/LakersOverEverything","url":"https://t.co/75NsJHCyey","indices":[0,23]}]}},"fast_followers_count":0,"favourites_count":3453,"followers_count":272,"friends_count":345,"has_custom_timelines":false,"is_translator":false,"listed_count":1,"location":"Los Angeles, CA","media_count":362,"name":"LAKERS OVER EVERYTHING (LOE)","normal_followers_count":272,"pinned_tweet_ids_str":[],"possibly_sensitive":false,"profile_banner_url":"https://pbs.twimg.com/profile_banners/1567181902775484420/1665087615","profile_image_url_https":"https://pbs.twimg.com/profile_images/1658288854280073217/9ATRoork_normal.jpg","profile_interstitial_type":"","screen_name":"thee1LOE","statuses_count":4720,"translator_type":"none","url":"https://t.co/75NsJHCyey","verified":false,"want_retweets":false,"withheld_in_countries":[]},"professional":{"rest_id":"1567186647766421504","professional_type":"Creator","category":[{"id":579,"name":"Media & News","icon_name":"IconBriefcaseStroke"}]},"smart_blocked_by":false,"smart_blocking":false,"business_account":{}}}},"edit_control":{"edit_tweet_ids":["1682581444277977088"],"editable_until_msecs":"1689997251000","is_edit_eligible":false,"edits_remaining":"5"},"edit_perspective":{"favorited":false,"retweeted":false},"is_translatable":false,"views":{"count":"270349","state":"EnabledWithCount"},"source":"<a href=\"http://twitter.com/download/iphone\" rel=\"nofollow\">Twitter for iPhone</a>","legacy":{"created_at":"Sat Jul 22 02:40:51 +0000 2023","conversation_id_str":"1682546856809873408","display_text_range":[28,43],"entities":{"user_mentions":[{"id_str":"1422010731801858053","name":"Reece 🇻🇨","screen_name":"nupersona","indices":[0,10]},{"id_str":"918207822","name":"Shannonnn sharpes Burner (PARODY Account)","screen_name":"shannonsharpeee","indices":[11,27]}],"urls":[],"hashtags":[],"symbols":[]},"favorite_count":125,"favorited":false,"full_text":"@nupersona @shannonsharpeee You won!!!! 😂 😂","in_reply_to_screen_name":"nupersona","in_reply_to_status_id_str":"1682548533512028160","in_reply_to_user_id_str":"1422010731801858053","is_quote_status":false,"lang":"en","quote_count":0,"reply_count":0,"retweet_count":0,"retweeted":false,"user_id_str":"1567181902775484420","id_str":"1682581444277977088"},"quick_promote_eligibility":{"eligibility":"IneligibleNotProfessional"}}},"tweetDisplayType":"Tweet"},"clientEventInfo":{"details":{"conversationDetails":{"conversationSection":"HighQuality"},"timelinesDetails":{"controllerData":"DAACDAAEDAABCgABFIAKkCQLAAEKAAIAAAAAFARACAAAAAA="}}}}}],"displayType":"VerticalConversation","clientEventInfo":{"details":{"conversationDetails":{"conversationSection":"HighQuality"}}}}},{"entryId":"conversationthread-1682811877082931200","sortIndex":"7540825180044902019","content":{"entryType":"TimelineTimelineModule","__typename":"TimelineTimelineModule","items":[{"entryId":"conversationthread-1682811877082931200-tweet-1682811877082931200","item":{"itemContent":{"itemType":"TimelineTweet","__typename":"TimelineTweet","tweet_results":{"result":{"__typename":"Tweet","rest_id":"1682811877082931200","has_birdwatch_notes":false,"core":{"user_results":{"result":{"__typename":"User","id":"VXNlcjo3NDg3OTc4OQ==","rest_id":"74879789","affiliates_highlighted_label":{},"has_graduated_access":true,"is_blue_verified":true,"legacy":{"can_dm":true,"can_media_tag":true,"created_at":"Thu Sep 17 00:06:28 +0000 2009","default_profile":false,"default_profile_image":false,"description":"Co-Founder at @harbour_fi \"Not A Bank, It is Better. One Account For Fiat & Crypto\" - Co-Founder @mcgillprod - Beautiful Videos That Deliver Results","entities":{"description":{"urls":[]},"url":{"urls":[{"display_url":"mcgillproductions.co.uk","expanded_url":"http://www.mcgillproductions.co.uk","url":"https://t.co/YSqnyMNAdv","indices":[0,23]}]}},"fast_followers_count":0,"favourites_count":9245,"followers_count":15215,"friends_count":820,"has_custom_timelines":true,"is_translator":false,"listed_count":24,"location":"United kingdom, England","media_count":751,"name":"Shane Ogley","normal_followers_count":15215,"pinned_tweet_ids_str":[],"possibly_sensitive":false,"profile_banner_url":"https://pbs.twimg.com/profile_banners/74879789/1612816981","profile_image_url_https":"https://pbs.twimg.com/profile_images/1460174482568531968/CGQUMrWY_normal.jpg","profile_interstitial_type":"","screen_name":"ShaneOgley","statuses_count":10531,"translator_type":"none","url":"https://t.co/YSqnyMNAdv","verified":false,"want_retweets":false,"withheld_in_countries":[]},"professional":{"rest_id":"1482654266942705671","professional_type":"Creator","category":[]},"smart_blocked_by":false,"smart_blocking":false,"business_account":{}}}},"edit_control":{"edit_tweet_ids":["1682811877082931200"],"editable_until_msecs":"1690052191000","is_edit_eligible":false,"edits_remaining":"5"},"edit_perspective":{"favorited":false,"retweeted":false},"is_translatable":false,"views":{"count":"777","state":"EnabledWithCount"},"source":"<a href=\"http://twitter.com/download/iphone\" rel=\"nofollow\">Twitter for iPhone</a>","legacy":{"created_at":"Sat Jul 22 17:56:31 +0000 2023","conversation_id_str":"1682546856809873408","display_text_range":[17,26],"entities":{"user_mentions":[{"id_str":"918207822","name":"Shannonnn sharpes Burner (PARODY Account)","screen_name":"shannonsharpeee","indices":[0,16]}],"urls":[],"hashtags":[],"symbols":[]},"favorite_count":1,"favorited":false,"full_text":"@shannonsharpeee Sack that","in_reply_to_screen_name":"shannonsharpeee","in_reply_to_status_id_str":"1682546856809873408","in_reply_to_user_id_str":"918207822","is_quote_status":false,"lang":"en","quote_count":0,"reply_count":0,"retweet_count":0,"retweeted":false,"user_id_str":"74879789","id_str":"1682811877082931200"},"quick_promote_eligibility":{"eligibility":"IneligibleNotProfessional"}}},"tweetDisplayType":"Tweet"},"clientEventInfo":{"details":{"conversationDetails":{"conversationSection":"HighQuality"},"timelinesDetails":{"controllerData":"DAACDAAEDAABCgABFIAKiCgLAAUKAAIAAAAAFARACAAAAAA="}}}}}],"displayType":"VerticalConversation","clientEventInfo":{"details":{"conversationDetails":{"conversationSection":"HighQuality"}}}}},{"entryId":"conversationthread-1682790664650489857","sortIndex":"7540825180044902009","content":{"entryType":"TimelineTimelineModule","__typename":"TimelineTimelineModule","items":[{"entryId":"conversationthread-1682790664650489857-tweet-1682790664650489857","item":{"itemContent":{"itemType":"TimelineTweet","__typename":"TimelineTweet","tweet_results":{"result":{"__typename":"Tweet","rest_id":"1682790664650489857","has_birdwatch_notes":false,"core":{"user_results":{"result":{"__typename":"User","id":"VXNlcjozMzIwMzcyMzc=","rest_id":"332037237","affiliates_highlighted_label":{},"has_graduated_access":true,"is_blue_verified":true,"legacy":{"can_dm":false,"can_media_tag":true,"created_at":"Sat Jul 09 03:38:01 +0000 2011","default_profile":true,"default_profile_image":false,"description":"still kicking\n#LetsGoVCURams","entities":{"description":{"urls":[]}},"fast_followers_count":0,"favourites_count":8332,"followers_count":470,"friends_count":94,"has_custom_timelines":false,"is_translator":false,"listed_count":6,"location":"USA","media_count":148,"name":"Jim Johnson✝️🐘🏀","normal_followers_count":470,"pinned_tweet_ids_str":[],"possibly_sensitive":false,"profile_banner_url":"https://pbs.twimg.com/profile_banners/332037237/1689445270","profile_image_url_https":"https://pbs.twimg.com/profile_images/1861119930/santa_paws_2011_normal.jpg","profile_interstitial_type":"","screen_name":"celticguyva","statuses_count":10561,"translator_type":"none","verified":false,"want_retweets":false,"withheld_in_countries":[]},"smart_blocked_by":false,"smart_blocking":false,"business_account":{}}}},"edit_control":{"edit_tweet_ids":["1682790664650489857"],"editable_until_msecs":"1690047133000","is_edit_eligible":false,"edits_remaining":"5"},"edit_perspective":{"favorited":false,"retweeted":false},"is_translatable":false,"views":{"count":"7177","state":"EnabledWithCount"},"source":"<a href=\"https://mobile.twitter.com\" rel=\"nofollow\">Twitter Web App</a>","legacy":{"created_at":"Sat Jul 22 16:32:13 +0000 2023","conversation_id_str":"1682546856809873408","display_text_range":[17,38],"entities":{"user_mentions":[{"id_str":"918207822","name":"Shannonnn sharpes Burner (PARODY Account)","screen_name":"shannonsharpeee","indices":[0,16]}],"urls":[],"hashtags":[],"symbols":[]},"favorite_count":4,"favorited":false,"full_text":"@shannonsharpeee thats a big boy too !","in_reply_to_screen_name":"shannonsharpeee","in_reply_to_status_id_str":"1682546856809873408","in_reply_to_user_id_str":"918207822","is_quote_status":false,"lang":"en","quote_count":0,"reply_count":0,"retweet_count":0,"retweeted":false,"user_id_str":"332037237","id_str":"1682790664650489857"},"quick_promote_eligibility":{"eligibility":"IneligibleNotProfessional"}}},"tweetDisplayType":"Tweet"},"clientEventInfo":{"details":{"conversationDetails":{"conversationSection":"HighQuality"},"timelinesDetails":{"controllerData":"DAACDAAEDAABCgABFIAKiDALAAUKAAIAAAAAFARACAAAAAA="}}}}}],"displayType":"VerticalConversation","clientEventInfo":{"details":{"conversationDetails":{"conversationSection":"HighQuality"}}}}},{"entryId":"conversationthread-1682548936190353411","sortIndex":"7540825180044901999","content":{"entryType":"TimelineTimelineModule","__typename":"TimelineTimelineModule","items":[{"entryId":"conversationthread-1682548936190353411-tweet-1682548936190353411","item":{"itemContent":{"itemType":"TimelineTweet","__typename":"TimelineTweet","tweet_results":{"result":{"__typename":"Tweet","rest_id":"1682548936190353411","has_birdwatch_notes":false,"core":{"user_results":{"result":{"__typename":"User","id":"VXNlcjo0MTM2MTMwNTI=","rest_id":"413613052","affiliates_highlighted_label":{},"has_graduated_access":true,"is_blue_verified":false,"legacy":{"can_dm":true,"can_media_tag":false,"created_at":"Wed Nov 16 02:31:57 +0000 2011","default_profile":false,"default_profile_image":false,"description":"Muslim first. Winning is a habit... unofficial ESPN contributor Celts & Patriots Banners 18 & 7","entities":{"description":{"urls":[]},"url":{"urls":[{"display_url":"youtube.com/@hassanhits","expanded_url":"https://youtube.com/@hassanhits","url":"https://t.co/IdhzEuQPdb","indices":[0,23]}]}},"fast_followers_count":0,"favourites_count":15363,"followers_count":1087,"friends_count":427,"has_custom_timelines":true,"is_translator":false,"listed_count":22,"location":"Boston, MA","media_count":13750,"name":"Hassan 🇸🇴","normal_followers_count":1087,"pinned_tweet_ids_str":["1682544744629411841"],"possibly_sensitive":false,"profile_banner_url":"https://pbs.twimg.com/profile_banners/413613052/1678624995","profile_image_url_https":"https://pbs.twimg.com/profile_images/1679677129372385280/qV3CEtOI_normal.jpg","profile_interstitial_type":"","screen_name":"TherealHassanO","statuses_count":39849,"translator_type":"none","url":"https://t.co/IdhzEuQPdb","verified":false,"want_retweets":false,"withheld_in_countries":[]},"smart_blocked_by":false,"smart_blocking":false,"business_account":{}}}},"edit_control":{"edit_tweet_ids":["1682548936190353411"],"editable_until_msecs":"1689989501000","is_edit_eligible":false,"edits_remaining":"5"},"edit_perspective":{"favorited":false,"retweeted":false},"is_translatable":false,"views":{"count":"205853","state":"EnabledWithCount"},"source":"<a href=\"http://twitter.com/download/iphone\" rel=\"nofollow\">Twitter for iPhone</a>","legacy":{"created_at":"Sat Jul 22 00:31:41 +0000 2023","conversation_id_str":"1682546856809873408","display_text_range":[17,35],"entities":{"media":[{"display_url":"pic.twitter.com/UW1gFIsiSC","expanded_url":"https://twitter.com/TherealHassanO/status/1682548936190353411/video/1","id_str":"1682548924639223809","indices":[36,59],"media_url_https":"https://pbs.twimg.com/ext_tw_video_thumb/1682548924639223809/pu/img/goD2-Er0ldUC4VjF.jpg","type":"photo","url":"https://t.co/UW1gFIsiSC","features":{},"sizes":{"large":{"h":360,"w":640,"resize":"fit"},"medium":{"h":360,"w":640,"resize":"fit"},"small":{"h":360,"w":640,"resize":"fit"},"thumb":{"h":150,"w":150,"resize":"crop"}},"original_info":{"height":360,"width":640}}],"user_mentions":[{"id_str":"918207822","name":"Shannonnn sharpes Burner (PARODY Account)","screen_name":"shannonsharpeee","indices":[0,16]}],"urls":[],"hashtags":[],"symbols":[]},"extended_entities":{"media":[{"display_url":"pic.twitter.com/UW1gFIsiSC","expanded_url":"https://twitter.com/TherealHassanO/status/1682548936190353411/video/1","id_str":"1682548924639223809","indices":[36,59],"media_key":"7_1682548924639223809","media_url_https":"https://pbs.twimg.com/ext_tw_video_thumb/1682548924639223809/pu/img/goD2-Er0ldUC4VjF.jpg","type":"video","url":"https://t.co/UW1gFIsiSC","additional_media_info":{"monetizable":false},"mediaStats":{"viewCount":98149},"ext_media_availability":{"status":"Available"},"features":{},"sizes":{"large":{"h":360,"w":640,"resize":"fit"},"medium":{"h":360,"w":640,"resize":"fit"},"small":{"h":360,"w":640,"resize":"fit"},"thumb":{"h":150,"w":150,"resize":"crop"}},"original_info":{"height":360,"width":640},"video_info":{"aspect_ratio":[16,9],"duration_millis":7511,"variants":[{"content_type":"application/x-mpegURL","url":"https://video.twimg.com/ext_tw_video/1682548924639223809/pu/pl/_EftSfyxzmJ1RtrH.m3u8?tag=12&container=fmp4"},{"bitrate":832000,"content_type":"video/mp4","url":"https://video.twimg.com/ext_tw_video/1682548924639223809/pu/vid/640x360/AQhes7abRQlV1wKs.mp4?tag=12"},{"bitrate":256000,"content_type":"video/mp4","url":"https://video.twimg.com/ext_tw_video/1682548924639223809/pu/vid/480x270/5vqRI866LOV8G_Lk.mp4?tag=12"}]}}]},"favorite_count":1888,"favorited":false,"full_text":"@shannonsharpeee Shark really said: https://t.co/UW1gFIsiSC","in_reply_to_screen_name":"shannonsharpeee","in_reply_to_status_id_str":"1682546856809873408","in_reply_to_user_id_str":"918207822","is_quote_status":false,"lang":"en","possibly_sensitive":false,"possibly_sensitive_editable":true,"quote_count":15,"reply_count":31,"retweet_count":94,"retweeted":false,"user_id_str":"413613052","id_str":"1682548936190353411"},"quick_promote_eligibility":{"eligibility":"IneligibleNotProfessional"}}},"tweetDisplayType":"Tweet"},"clientEventInfo":{"details":{"conversationDetails":{"conversationSection":"HighQuality"},"timelinesDetails":{"controllerData":"DAACDAAEDAABCgABFIAKCCBbABUKAAIAAAAABQRACAAAAAA="}}}}},{"entryId":"conversationthread-1682548936190353411-tweet-1682607968922087425","item":{"itemContent":{"itemType":"TimelineTweet","__typename":"TimelineTweet","tweet_results":{"result":{"__typename":"Tweet","rest_id":"1682607968922087425","has_birdwatch_notes":false,"core":{"user_results":{"result":{"__typename":"User","id":"VXNlcjoxNTg2NjYxMzIwNjk0NDA3MTY4","rest_id":"1586661320694407168","affiliates_highlighted_label":{},"has_graduated_access":true,"is_blue_verified":true,"legacy":{"can_dm":false,"can_media_tag":true,"created_at":"Sun Oct 30 10:08:36 +0000 2022","default_profile":true,"default_profile_image":false,"description":"Unbias Sports opinion & news.\n\nContact Us at sportssteady@protonmail.com","entities":{"description":{"urls":[]},"url":{"urls":[{"display_url":"youtube.com/@SportsSteadyTv","expanded_url":"https://www.youtube.com/@SportsSteadyTv","url":"https://t.co/qe4eBXth6M","indices":[0,23]}]}},"fast_followers_count":0,"favourites_count":487,"followers_count":46,"friends_count":8,"has_custom_timelines":false,"is_translator":false,"listed_count":1,"location":"USA","media_count":121,"name":"Sports Steady Tv","normal_followers_count":46,"pinned_tweet_ids_str":[],"possibly_sensitive":false,"profile_banner_url":"https://pbs.twimg.com/profile_banners/1586661320694407168/1672536537","profile_image_url_https":"https://pbs.twimg.com/profile_images/1609360994328788992/giKH61V__normal.jpg","profile_interstitial_type":"","screen_name":"SportsSteadyTV","statuses_count":567,"translator_type":"none","url":"https://t.co/qe4eBXth6M","verified":false,"want_retweets":false,"withheld_in_countries":[]},"smart_blocked_by":false,"smart_blocking":false,"business_account":{}}}},"edit_control":{"edit_tweet_ids":["1682607968922087425"],"editable_until_msecs":"1690003575000","is_edit_eligible":false,"edits_remaining":"5"},"edit_perspective":{"favorited":false,"retweeted":false},"is_translatable":false,"views":{"count":"167806","state":"EnabledWithCount"},"source":"<a href=\"https://mobile.twitter.com\" rel=\"nofollow\">Twitter Web App</a>","legacy":{"created_at":"Sat Jul 22 04:26:15 +0000 2023","conversation_id_str":"1682546856809873408","display_text_range":[33,36],"entities":{"user_mentions":[{"id_str":"413613052","name":"Hassan 🇸🇴","screen_name":"TherealHassanO","indices":[0,15]},{"id_str":"918207822","name":"Shannonnn sharpes Burner (PARODY Account)","screen_name":"shannonsharpeee","indices":[16,32]}],"urls":[],"hashtags":[],"symbols":[]},"favorite_count":38,"favorited":false,"full_text":"@TherealHassanO @shannonsharpeee 🤣🤣🤣","in_reply_to_screen_name":"TherealHassanO","in_reply_to_status_id_str":"1682548936190353411","in_reply_to_user_id_str":"413613052","is_quote_status":false,"lang":"qme","quote_count":0,"reply_count":0,"retweet_count":3,"retweeted":false,"user_id_str":"1586661320694407168","id_str":"1682607968922087425"},"quick_promote_eligibility":{"eligibility":"IneligibleNotProfessional"}}},"tweetDisplayType":"Tweet"},"clientEventInfo":{"details":{"conversationDetails":{"conversationSection":"HighQuality"},"timelinesDetails":{"controllerData":"DAACDAAEDAABCgABFIACkCALAAEKAAIAAAAAFQRACAAAAAA="}}}}}],"displayType":"VerticalConversation","clientEventInfo":{"details":{"conversationDetails":{"conversationSection":"HighQuality"}}}}},{"entryId":"conversationthread-1682759127599128578","sortIndex":"7540825180044901989","content":{"entryType":"TimelineTimelineModule","__typename":"TimelineTimelineModule","items":[{"entryId":"conversationthread-1682759127599128578-tweet-1682759127599128578","item":{"itemContent":{"itemType":"TimelineTweet","__typename":"TimelineTweet","tweet_results":{"result":{"__typename":"Tweet","rest_id":"1682759127599128578","has_birdwatch_notes":false,"core":{"user_results":{"result":{"__typename":"User","id":"VXNlcjoxMjEzNTQ1MDA3ODI4NzE3NTY4","rest_id":"1213545007828717568","affiliates_highlighted_label":{},"has_graduated_access":true,"is_blue_verified":true,"legacy":{"can_dm":false,"can_media_tag":true,"created_at":"Sat Jan 04 19:37:55 +0000 2020","default_profile":true,"default_profile_image":false,"description":"Content @FinalFormHQ | business email: mrmills248@gmail.com | Pro Aimer Goals | player of all games | Content Creator | #kick Vadasz","entities":{"description":{"urls":[]},"url":{"urls":[{"display_url":"kick.com/Vadasz","expanded_url":"http://kick.com/Vadasz","url":"https://t.co/ztQ0RW19RC","indices":[0,23]}]}},"fast_followers_count":0,"favourites_count":5706,"followers_count":403,"friends_count":273,"has_custom_timelines":true,"is_translator":false,"listed_count":3,"location":"Atlanta, GA","media_count":1200,"name":"Final Vadasz","normal_followers_count":403,"pinned_tweet_ids_str":[],"possibly_sensitive":false,"profile_banner_url":"https://pbs.twimg.com/profile_banners/1213545007828717568/1686549991","profile_image_url_https":"https://pbs.twimg.com/profile_images/1668137641080922112/M7KdiUK2_normal.jpg","profile_interstitial_type":"","screen_name":"VadaszGaming","statuses_count":7156,"translator_type":"none","url":"https://t.co/ztQ0RW19RC","verified":false,"want_retweets":false,"withheld_in_countries":[]},"professional":{"rest_id":"1476955290562088961","professional_type":"Creator","category":[{"id":959,"name":"Gamer","icon_name":"IconBriefcaseStroke"}]},"smart_blocked_by":false,"smart_blocking":false,"business_account":{}}}},"edit_control":{"edit_tweet_ids":["1682759127599128578"],"editable_until_msecs":"1690039614000","is_edit_eligible":false,"edits_remaining":"5"},"edit_perspective":{"favorited":false,"retweeted":false},"is_translatable":false,"views":{"count":"21713","state":"EnabledWithCount"},"source":"<a href=\"http://twitter.com/download/iphone\" rel=\"nofollow\">Twitter for iPhone</a>","legacy":{"created_at":"Sat Jul 22 14:26:54 +0000 2023","conversation_id_str":"1682546856809873408","display_text_range":[17,96],"entities":{"user_mentions":[{"id_str":"918207822","name":"Shannonnn sharpes Burner (PARODY Account)","screen_name":"shannonsharpeee","indices":[0,16]}],"urls":[],"hashtags":[],"symbols":[]},"favorite_count":16,"favorited":false,"full_text":"@shannonsharpeee I think I’m done with beaches. Over fishing is pushing sharks closer to shores.","in_reply_to_screen_name":"shannonsharpeee","in_reply_to_status_id_str":"1682546856809873408","in_reply_to_user_id_str":"918207822","is_quote_status":false,"lang":"en","quote_count":0,"reply_count":1,"retweet_count":1,"retweeted":false,"user_id_str":"1213545007828717568","id_str":"1682759127599128578"},"quick_promote_eligibility":{"eligibility":"IneligibleNotProfessional"}}},"tweetDisplayType":"Tweet"},"clientEventInfo":{"details":{"conversationDetails":{"conversationSection":"HighQuality"},"timelinesDetails":{"controllerData":"DAACDAAEDAABCgABFIAKiCALAAUKAAIAAAAAFARACAAAAAA="}}}}},{"entryId":"conversationthread-1682759127599128578-cursor-showmore-4102643068769182267","item":{"itemContent":{"itemType":"TimelineTimelineCursor","__typename":"TimelineTimelineCursor","value":"PAAAAPAfPBwcFoSAvbHZoK7aLhUCAAAYJmNvbnZlcnNhdGlvbnRocmVhZC0xNjgyNzU5MQUAoDkxMjg1NzgiAAA","cursorType":"ShowMore","displayTreatment":{"actionText":"Show replies"}},"clientEventInfo":{"details":{"conversationDetails":{"conversationSection":"HighQuality"}}}}}],"displayType":"VerticalConversation","clientEventInfo":{"details":{"conversationDetails":{"conversationSection":"HighQuality"}}}}},{"entryId":"conversationthread-1682710758663110656","sortIndex":"7540825180044901979","content":{"entryType":"TimelineTimelineModule","__typename":"TimelineTimelineModule","items":[{"entryId":"conversationthread-1682710758663110656-tweet-1682710758663110656","item":{"itemContent":{"itemType":"TimelineTweet","__typename":"TimelineTweet","tweet_results":{"result":{"__typename":"Tweet","rest_id":"1682710758663110656","has_birdwatch_notes":false,"core":{"user_results":{"result":{"__typename":"User","id":"VXNlcjoxMzU0ODgwODM3NjkxNDI4ODY2","rest_id":"1354880837691428866","affiliates_highlighted_label":{},"has_graduated_access":true,"is_blue_verified":true,"legacy":{"can_dm":false,"can_media_tag":true,"created_at":"Thu Jan 28 19:55:48 +0000 2021","default_profile":true,"default_profile_image":false,"description":"spicy designer who loves art, boardsports, and gaming 🟠","entities":{"description":{"urls":[]},"url":{"urls":[{"display_url":"linktr.ee/honeypepp3r","expanded_url":"https://linktr.ee/honeypepp3r","url":"https://t.co/mqSlQnrJ3D","indices":[0,23]}]}},"fast_followers_count":0,"favourites_count":67782,"followers_count":4017,"friends_count":3468,"has_custom_timelines":true,"is_translator":false,"listed_count":42,"location":"Fuchsia City","media_count":2270,"name":"honeypepp3r","normal_followers_count":4017,"pinned_tweet_ids_str":["1680100639580254208"],"possibly_sensitive":false,"profile_banner_url":"https://pbs.twimg.com/profile_banners/1354880837691428866/1681250559","profile_image_url_https":"https://pbs.twimg.com/profile_images/1672823080912297985/zoDMYdz4_normal.jpg","profile_interstitial_type":"","screen_name":"honeypepp3r","statuses_count":16984,"translator_type":"none","url":"https://t.co/mqSlQnrJ3D","verified":false,"want_retweets":false,"withheld_in_countries":[]},"professional":{"rest_id":"1461863041054564356","professional_type":"Creator","category":[]},"smart_blocked_by":false,"smart_blocking":false,"business_account":{}}}},"edit_control":{"edit_tweet_ids":["1682710758663110656"],"editable_until_msecs":"1690028082000","is_edit_eligible":false,"edits_remaining":"5"},"edit_perspective":{"favorited":false,"retweeted":false},"is_translatable":false,"views":{"count":"21730","state":"EnabledWithCount"},"source":"<a href=\"http://twitter.com/download/iphone\" rel=\"nofollow\">Twitter for iPhone</a>","legacy":{"created_at":"Sat Jul 22 11:14:42 +0000 2023","conversation_id_str":"1682546856809873408","display_text_range":[17,50],"entities":{"user_mentions":[{"id_str":"918207822","name":"Shannonnn sharpes Burner (PARODY Account)","screen_name":"shannonsharpeee","indices":[0,16]}],"urls":[],"hashtags":[],"symbols":[]},"favorite_count":4,"favorited":false,"full_text":"@shannonsharpeee Wait there is sharks in the ocean","in_reply_to_screen_name":"shannonsharpeee","in_reply_to_status_id_str":"1682546856809873408","in_reply_to_user_id_str":"918207822","is_quote_status":false,"lang":"en","quote_count":0,"reply_count":1,"retweet_count":1,"retweeted":false,"user_id_str":"1354880837691428866","id_str":"1682710758663110656"},"quick_promote_eligibility":{"eligibility":"IneligibleNotProfessional"}}},"tweetDisplayType":"Tweet"},"clientEventInfo":{"details":{"conversationDetails":{"conversationSection":"HighQuality"},"timelinesDetails":{"controllerData":"DAACDAAEDAABCgABFIAKCCALABUKAAIAAAAAFARACAAAAAA="}}}}},{"entryId":"conversationthread-1682710758663110656-cursor-showmore-8170834942229356383","item":{"itemContent":{"itemType":"TimelineTimelineCursor","__typename":"TimelineTimelineCursor","value":"PAAAAPAtPBwcFoCAvt2goZjaLhUCAAAYJmNvbnZlcnNhdGlvbnRocmVhZC0xNjgyNzEwNzU4NjYzMTEwNjU2IgAA","cursorType":"ShowMore","displayTreatment":{"actionText":"Show replies"}},"clientEventInfo":{"details":{"conversationDetails":{"conversationSection":"HighQuality"}}}}}],"displayType":"VerticalConversation","clientEventInfo":{"details":{"conversationDetails":{"conversationSection":"HighQuality"}}}}},{"entryId":"cursor-bottom-5169899474878931171","sortIndex":"7540825180044901978","content":{"entryType":"TimelineTimelineItem","__typename":"TimelineTimelineItem","itemContent":{"itemType":"TimelineTimelineCursor","__typename":"TimelineTimelineCursor","value":"jgEAAPAgHBn2K4CAs42Ro87ZLoTA05njx5TaLoKAvN3IjsLaLoSAscnCu8_aLoCAsbnLhrUJAFC9xZ73wwkAULbts-iyCQBQvMnm6bM2AOCw5fzJ6dkugoC24di51xsAULO1jM_SWgDhvvHytajaLoDAs-WijLNRANGFydeM2i6EwLOR_tq8UQDwEZXBvs7ZLo7AvcXuwNPaLoaAs6351c7ZLoCA0u3DotfZPwBAqZOaw2wAUbGt-KuhUQBBsYbroYcA0KGF5c3ZLoaAvY2fiNa9AFC90Zri1i0A4dDZ447v2S6IgLDhhJLQfgBAgaaUhAkAUL7doKGYJABBvbmLjAkAUb7d07vQbADQpd7X6dougsDQoZfY49gAULz9haLPkABR1P2xm8XzAEDdssy8JABRs8Hkt8ASAEGt4_HCzwBBgbj4zmwAQNWPn8YJAECw_cPuWgBhgLDFjrCvogDQsdmgrtouJQISFQQAAA","cursorType":"Bottom"}}}]},{"type":"TimelineTerminateTimeline","direction":"Top"}]}}}