{"data":{"threaded_conversation_with_injections_v2":{"instructions":[{"type":"TimelineAddEntries","entries":[{"entryId":"conversationthread-1682748630917079041","sortIndex":"7540637877146237705","content":{"entryType":"TimelineTimelineModule","__typename":"TimelineTimelineModule","items":[{"entryId":"conversationthread-1682748630917079041-tweet-1682748630917079041","item":{"itemContent":{"itemType":"TimelineTweet","__typename":"TimelineTweet","tweet_results":{"result":{"__typename":"Tweet","rest_id":"1682748630917079041","has_birdwatch_notes":false,"core":{"user_results":{"result":{"__typename":"User","id":"VXNlcjo5NDczMjY0MDg3NDA3NTc1MDQ=","rest_id":"947326408740757504","affiliates_highlighted_label":{},"has_graduated_access":true,"is_blue_verified":false,"legacy":{"can_dm":true,"can_media_tag":true,"created_at":"Sun Dec 31 04:39:51 +0000 2017","default_profile":true,"default_profile_image":false,"description":"Law⚖️ | Business | Heritage Network ❤️ | Humanitarian | YBNL","entities":{"description":{"urls":[]}},"fast_followers_count":0,"favourites_count":9795,"followers_count":2702,"friends_count":2016,"has_custom_timelines":true,"is_translator":false,"listed_count":0,"location":"behind you","media_count":248,"name":"𝕂.𝔸.𝔹.𝕀.ℝ🦁👑","normal_followers_count":2702,"pinned_tweet_ids_str":["1334501786556751886"],"possibly_sensitive":false,"profile_banner_url":"https://pbs.twimg.com/profile_banners/947326408740757504/1648098010","profile_image_url_https":"https://pbs.twimg.com/profile_images/1586055718708420608/MZOxupQM_normal.jpg","profile_interstitial_type":"","screen_name":"heritageyy","statuses_count":2856,"translator_type":"none","verified":false,"want_retweets":false,"withheld_in_countries":[]},"professional":{"rest_id":"1506758575879766022","professional_type":"Creator","category":[{"id":486,"name":"Entertainment Lawyer","icon_name":"IconBriefcaseStroke"}]},"smart_blocked_by":false,"smart_blocking":false,"business_account":{}}}},"edit_control":{"edit_tweet_ids":["1682748630917079041"],"editable_until_msecs":"1690037112000","is_edit_eligible":false,"edits_remaining":"5"},"edit_perspective":{"favorited":false,"retweeted":false},"is_translatable":false,"views":{"count":"728","state":"EnabledWithCount"},"source":"<a href=\"http://twitter.com/download/android\" rel=\"nofollow\">Twitter for Android</a>","legacy":{"created_at":"Sat Jul 22 13:45:12 +0000 2023","conversation_id_str":"1682734159708536832","display_text_range":[12,288],"entities":{"user_mentions":[{"id_str":"1177132853487951873","name":"Amber_Jay 🦋🐶🦋","screen_name":"_Copah_Jay","indices":[0,11]}],"urls":[],"hashtags":[],"symbols":[]},"favorite_count":2,"favorited":false,"full_text":"@_Copah_Jay 1. Is this inside the mosque?\n\n2. You should know better that this mode of dressing is the 'Culture' of the Arabians. It's not just about religion for them. With all certainty, these sets of people you see here can never make the MISTAKE of recreating this in a 'Prayer arena'","in_reply_to_screen_name":"_Copah_Jay","in_reply_to_status_id_str":"1682734159708536832","in_reply_to_user_id_str":"1177132853487951873","is_quote_status":false,"lang":"en","quote_count":0,"reply_count":0,"retweet_count":0,"retweeted":false,"user_id_str":"947326408740757504","id_str":"1682748630917079041"},"quick_promote_eligibility":{"eligibility":"IneligibleNotProfessional"}}},"tweetDisplayType":"Tweet"},"clientEventInfo":{"details":{"conversationDetails":{"conversationSection":"HighQuality"},"timelinesDetails":{"controllerData":"DAACDAAEDAABCgABFIAKiCAHAAUKAAIAAAAABAQQCAAAAAA="}}}}}],"displayType":"VerticalConversation","clientEventInfo":{"details":{"conversationDetails":{"conversationSection":"HighQuality"}}}}},{"entryId":"conversationthread-1682746787398926337","sortIndex":"7540637877146237695","content":{"entryType":"TimelineTimelineModule","__typename":"TimelineTimelineModule","items":[{"entryId":"conversationthread-1682746787398926337-tweet-1682746787398926337","item":{"itemContent":{"itemType":"TimelineTweet","__typename":"TimelineTweet","tweet_results":{"result":{"__typename":"Tweet","rest_id":"1682746787398926337","has_birdwatch_notes":false,"core":{"user_results":{"result":{"__typename":"User","id":"VXNlcjoxMjc3ODg4MTA0MDY2Njk5MjY0","rest_id":"1277888104066699264","affiliates_highlighted_label":{},"has_graduated_access":true,"is_blue_verified":false,"legacy":{"can_dm":true,"can_media_tag":true,"created_at":"Tue Jun 30 08:54:15 +0000 2020","default_profile":true,"default_profile_image":false,"description":"Vibes and insha'Allah","entities":{"description":{"urls":[]}},"fast_followers_count":0,"favourites_count":272,"followers_count":43,"friends_count":73,"has_custom_timelines":true,"is_translator":false,"listed_count":0,"location":"Osun State","media_count":43,"name":"ZharnTech","normal_followers_count":43,"pinned_tweet_ids_str":[],"possibly_sensitive":false,"profile_banner_url":"https://pbs.twimg.com/profile_banners/1277888104066699264/1674921433","profile_image_url_https":"https://pbs.twimg.com/profile_images/1564524271292088321/xg88Mlrt_normal.jpg","profile_interstitial_type":"","screen_name":"Sanusi24457291","statuses_count":618,"translator_type":"none","verified":false,"want_retweets":false,"withheld_in_countries":[]},"professional":{"rest_id":"1564522419922010112","professional_type":"Creator","category":[{"id":983,"name":"Technology-Security Company","icon_name":"IconBriefcaseStroke"}]},"smart_blocked_by":false,"smart_blocking":false,"business_account":{}}}},"edit_control":{"edit_tweet_ids":["1682746787398926337"],"editable_until_msecs":"1690036672000","is_edit_eligible":false,"edits_remaining":"5"},"edit_perspective":{"favorited":false,"retweeted":false},"is_translatable":false,"views":{"count":"553","state":"EnabledWithCount"},"source":"<a href=\"https://mobile.twitter.com\" rel=\"nofollow\">Twitter Web App</a>","legacy":{"created_at":"Sat Jul 22 13:37:52 +0000 2023","conversation_id_str":"1682734159708536832","display_text_range":[12,175],"entities":{"user_mentions":[{"id_str":"1177132853487951873","name":"Amber_Jay 🦋🐶🦋","screen_name":"_Copah_Jay","indices":[0,11]}],"urls":[],"hashtags":[],"symbols":[]},"favorite_count":0,"favorited":false,"full_text":"@_Copah_Jay Saudi nah country guy!!!same thing they did there fit happen I Nigeria.\nAt least they didn't do their own video inside the mosque or around the mosque environment.","in_reply_to_screen_name":"_Copah_Jay","in_reply_to_status_id_str":"1682734159708536832","in_reply_to_user_id_str":"1177132853487951873","is_quote_status":false,"lang":"en","quote_count":0,"reply_count":0,"retweet_count":0,"retweeted":false,"user_id_str":"1277888104066699264","id_str":"1682746787398926337"},"quick_promote_eligibility":{"eligibility":"IneligibleNotProfessional"}}},"tweetDisplayType":"Tweet"},"clientEventInfo":{"details":{"conversationDetails":{"conversationSection":"HighQuality"},"timelinesDetails":{"controllerData":"DAACDAAEDAABCgABFIAKiCIDAAUKAAIAAAAABARACAAAAAA="}}}}}],"displayType":"VerticalConversation","clientEventInfo":{"details":{"conversationDetails":{"conversationSection":"HighQuality"}}}}},{"entryId":"conversationthread-1682795868033015808","sortIndex":"7540637877146237685","content":{"entryType":"TimelineTimelineModule","__typename":"TimelineTimelineModule","items":[{"entryId":"conversationthread-1682795868033015808-tweet-1682795868033015808","item":{"itemContent":{"itemType":"TimelineTweet","__typename":"TimelineTweet","tweet_results":{"result":{"__typename":"Tweet","rest_id":"1682795868033015808","has_birdwatch_notes":false,"core":{"user_results":{"result":{"__typename":"User","id":"VXNlcjoxMzQwMjIyNTM=","rest_id":"134022253","affiliates_highlighted_label":{},"has_graduated_access":true,"is_blue_verified":false,"legacy":{"can_dm":false,"can_media_tag":false,"created_at":"Sat Apr 17 07:18:46 +0000 2010","default_profile":false,"default_profile_image":false,"description":"Forbes verified💰 | Analytical Thinking 💡| Liverpool ⚽🏆 | Philanthropist 🤝🏼 | Algorithm 📊 Analysis | Entrepreneur | Data Analyst | Cloud ☁️ Data","entities":{"description":{"urls":[]},"url":{"urls":[{"display_url":"facebook.com/iamfayvorite","expanded_url":"http://www.facebook.com/iamfayvorite","url":"https://t.co/ZQ5klvVrBs","indices":[0,23]}]}},"fast_followers_count":0,"favourites_count":1522,"followers_count":505,"friends_count":658,"has_custom_timelines":true,"is_translator":false,"listed_count":17,"location":"#Lagos#Nigeria#Africa","media_count":245,"name":"🌠❤️King 👑Favour💰🤍","normal_followers_count":505,"pinned_tweet_ids_str":["1403476230066868228"],"possibly_sensitive":false,"profile_banner_url":"https://pbs.twimg.com/profile_banners/134022253/1660985655","profile_image_url_https":"https://pbs.twimg.com/profile_images/1546392720004063232/kjiHFwa7_normal.jpg","profile_interstitial_type":"","screen_name":"Iam_fayvorite","statuses_count":25992,"translator_type":"none","url":"https://t.co/ZQ5klvVrBs","verified":false,"want_retweets":false,"withheld_in_countries":[]},"professional":{"rest_id":"1630334995502858242","professional_type":"Business","category":[{"id":1049,"name":"Data scientist","icon_name":"IconBriefcaseStroke"}]},"smart_blocked_by":false,"smart_blocking":false,"business_account":{}}}},"edit_control":{"edit_tweet_ids":["1682795868033015808"],"editable_until_msecs":"1690048374000","is_edit_eligible":false,"edits_remaining":"5"},"edit_perspective":{"favorited":false,"retweeted":false},"is_translatable":false,"views":{"count":"69","state":"EnabledWithCount"},"source":"<a href=\"http://twitter.com/download/iphone\" rel=\"nofollow\">Twitter for iPhone</a>","legacy":{"created_at":"Sat Jul 22 16:52:54 +0000 2023","conversation_id_str":"1682734159708536832","display_text_range":[12,119],"entities":{"user_mentions":[{"id_str":"1177132853487951873","name":"Amber_Jay 🦋🐶🦋","screen_name":"_Copah_Jay","indices":[0,11]}],"urls":[],"hashtags":[],"symbols":[]},"favorite_count":0,"favorited":false,"full_text":"@_Copah_Jay The true is Religious in Africa is totally different, we discriminate against each other especially Nigeria","in_reply_to_screen_name":"_Copah_Jay","in_reply_to_status_id_str":"1682734159708536832","in_reply_to_user_id_str":"1177132853487951873","is_quote_status":false,"lang":"en","quote_count":0,"reply_count":0,"retweet_count":0,"retweeted":false,"user_id_str":"134022253","id_str":"1682795868033015808"},"quick_promote_eligibility":{"eligibility":"IneligibleNotProfessional"}}},"tweetDisplayType":"Tweet"},"clientEventInfo":{"details":{"conversationDetails":{"conversationSection":"HighQuality"},"timelinesDetails":{"controllerData":"DAACDAAEDAABCgABFIAKiCQDAAUKAAIAAAAABARACAAAAAA="}}}}}],"displayType":"VerticalConversation","clientEventInfo":{"details":{"conversationDetails":{"conversationSection":"HighQuality"}}}}},{"entryId":"conversationthread-1682788691901665280","sortIndex":"7540637877146237675","content":{"entryType":"TimelineTimelineModule","__typename":"TimelineTimelineModule","items":[{"entryId":"conversationthread-1682788691901665280-tweet-1682788691901665280","item":{"itemContent":{"itemType":"TimelineTweet","__typename":"TimelineTweet","tweet_results":{"result":{"__typename":"Tweet","rest_id":"1682788691901665280","has_birdwatch_notes":false,"core":{"user_results":{"result":{"__typename":"User","id":"VXNlcjo4ODU1ODI1MzczNTkyODIxNzY=","rest_id":"885582537359282176","affiliates_highlighted_label":{},"has_graduated_access":true,"is_blue_verified":false,"legacy":{"can_dm":true,"can_media_tag":false,"created_at":"Thu Jul 13 19:31:45 +0000 2017","default_profile":true,"default_profile_image":false,"description":"💡","entities":{"description":{"urls":[]}},"fast_followers_count":0,"favourites_count":32273,"followers_count":792,"friends_count":786,"has_custom_timelines":true,"is_translator":false,"listed_count":1,"location":"Somwhere Close","media_count":197,"name":"Same_Ola","normal_followers_count":792,"pinned_tweet_ids_str":["1555292290670895104"],"possibly_sensitive":false,"profile_banner_url":"https://pbs.twimg.com/profile_banners/885582537359282176/1688991756","profile_image_url_https":"https://pbs.twimg.com/profile_images/1629098588952268801/WhIYHFoF_normal.jpg","profile_interstitial_type":"","screen_name":"Claimaxx","statuses_count":31509,"translator_type":"none","verified":false,"want_retweets":false,"withheld_in_countries":[]},"smart_blocked_by":false,"smart_blocking":false,"business_account":{}}}},"edit_control":{"edit_tweet_ids":["1682788691901665280"],"editable_until_msecs":"1690046663000","is_edit_eligible":false,"edits_remaining":"5"},"edit_perspective":{"favorited":false,"retweeted":false},"is_translatable":false,"views":{"count":"46","state":"EnabledWithCount"},"source":"<a href=\"http://twitter.com/download/iphone\" rel=\"nofollow\">Twitter for iPhone</a>","legacy":{"created_at":"Sat Jul 22 16:24:23 +0000 2023","conversation_id_str":"1682734159708536832","display_text_range":[12,88],"entities":{"user_mentions":[{"id_str":"1177132853487951873","name":"Amber_Jay 🦋🐶🦋","screen_name":"_Copah_Jay","indices":[0,11]}],"urls":[],"hashtags":[],"symbols":[]},"favorite_count":1,"favorited":false,"full_text":"@_Copah_Jay It’s not that difficult to understand these are to very different situations","in_reply_to_screen_name":"_Copah_Jay","in_reply_to_status_id_str":"1682734159708536832","in_reply_to_user_id_str":"1177132853487951873","is_quote_status":false,"lang":"en","quote_count":0,"reply_count":0,"retweet_count":0,"retweeted":false,"user_id_str":"885582537359282176","id_str":"1682788691901665280"},"quick_promote_eligibility":{"eligibility":"IneligibleNotProfessional"}}},"tweetDisplayType":"Tweet"},"clientEventInfo":{"details":{"conversationDetails":{"conversationSection":"HighQuality"},"timelinesDetails":{"controllerData":"DAACDAAEDAABCgABFIAKiCgDAAUKAAIAAAAABARACAAAAAA="}}}}}],"displayType":"VerticalConversation","clientEventInfo":{"details":{"conversationDetails":{"conversationSection":"HighQuality"}}}}},{"entryId":"conversationthread-1682857725452058624","sortIndex":"7540637877146237665","content":{"entryType":"TimelineTimelineModule","__typename":"TimelineTimelineModule","items":[{"entryId":"conversationthread-1682857725452058624-tweet-1682857725452058624","item":{"itemContent":{"itemType":"TimelineTweet","__typename":"TimelineTweet","tweet_results":{"result":{"__typename":"Tweet","rest_id":"1682857725452058624","has_birdwatch_notes":false,"core":{"user_results":{"result":{"__typename":"User","id":"VXNlcjoxNDgyMzcxNTExMzYxMTgzNzQ2","rest_id":"1482371511361183746","affiliates_highlighted_label":{},"has_graduated_access":true,"is_blue_verified":false,"legacy":{"can_dm":false,"can_media_tag":true,"created_at":"Sat Jan 15 15:18:31 +0000 2022","default_profile":true,"default_profile_image":false,"description":"","entities":{"description":{"urls":[]}},"fast_followers_count":0,"favourites_count":21534,"followers_count":617,"friends_count":632,"has_custom_timelines":true,"is_translator":false,"listed_count":0,"location":"","media_count":1050,"name":"Paul","normal_followers_count":617,"pinned_tweet_ids_str":[],"possibly_sensitive":false,"profile_image_url_https":"https://pbs.twimg.com/profile_images/1613959278678708225/6wt5ob8__normal.jpg","profile_interstitial_type":"","screen_name":"Paul_lyric007","statuses_count":6239,"translator_type":"none","verified":false,"want_retweets":false,"withheld_in_countries":[]},"smart_blocked_by":false,"smart_blocking":false,"business_account":{}}}},"edit_control":{"edit_tweet_ids":["1682857725452058624"],"editable_until_msecs":"1690063122000","is_edit_eligible":false,"edits_remaining":"5"},"edit_perspective":{"favorited":false,"retweeted":false},"is_translatable":false,"views":{"count":"24","state":"EnabledWithCount"},"source":"<a href=\"http://twitter.com/download/android\" rel=\"nofollow\">Twitter for Android</a>","legacy":{"created_at":"Sat Jul 22 20:58:42 +0000 2023","conversation_id_str":"1682734159708536832","display_text_range":[12,34],"entities":{"media":[{"display_url":"pic.twitter.com/iPFRmSNhU6","expanded_url":"https://twitter.com/Paul_lyric007/status/1682857725452058624/photo/1","id_str":"1682857715658309632","indices":[35,58],"media_url_https":"https://pbs.twimg.com/media/F1q2LR1WwAAve8t.jpg","type":"photo","url":"https://t.co/iPFRmSNhU6","features":{"large":{"faces":[{"x":334,"y":640,"h":207,"w":207}]},"medium":{"faces":[{"x":334,"y":640,"h":207,"w":207}]},"small":{"faces":[{"x":214,"y":410,"h":132,"w":132}]},"orig":{"faces":[{"x":334,"y":640,"h":207,"w":207}]}},"sizes":{"large":{"h":1061,"w":836,"resize":"fit"},"medium":{"h":1061,"w":836,"resize":"fit"},"small":{"h":680,"w":536,"resize":"fit"},"thumb":{"h":150,"w":150,"resize":"crop"}},"original_info":{"height":1061,"width":836,"focus_rects":[{"x":0,"y":429,"w":836,"h":468},{"x":0,"y":225,"w":836,"h":836},{"x":0,"y":108,"w":836,"h":953},{"x":292,"y":0,"w":531,"h":1061},{"x":0,"y":0,"w":836,"h":1061}]}}],"user_mentions":[{"id_str":"1177132853487951873","name":"Amber_Jay 🦋🐶🦋","screen_name":"_Copah_Jay","indices":[0,11]}],"urls":[],"hashtags":[],"symbols":[]},"extended_entities":{"media":[{"display_url":"pic.twitter.com/iPFRmSNhU6","expanded_url":"https://twitter.com/Paul_lyric007/status/1682857725452058624/photo/1","id_str":"1682857715658309632","indices":[35,58],"media_key":"3_1682857715658309632","media_url_https":"https://pbs.twimg.com/media/F1q2LR1WwAAve8t.jpg","type":"photo","url":"https://t.co/iPFRmSNhU6","ext_media_availability":{"status":"Available"},"features":{"large":{"faces":[{"x":334,"y":640,"h":207,"w":207}]},"medium":{"faces":[{"x":334,"y":640,"h":207,"w":207}]},"small":{"faces":[{"x":214,"y":410,"h":132,"w":132}]},"orig":{"faces":[{"x":334,"y":640,"h":207,"w":207}]}},"sizes":{"large":{"h":1061,"w":836,"resize":"fit"},"medium":{"h":1061,"w":836,"resize":"fit"},"small":{"h":680,"w":536,"resize":"fit"},"thumb":{"h":150,"w":150,"resize":"crop"}},"original_info":{"height":1061,"width":836,"focus_rects":[{"x":0,"y":429,"w":836,"h":468},{"x":0,"y":225,"w":836,"h":836},{"x":0,"y":108,"w":836,"h":953},{"x":292,"y":0,"w":531,"h":1061},{"x":0,"y":0,"w":836,"h":1061}]}}]},"favorite_count":0,"favorited":false,"full_text":"@_Copah_Jay It's called God's plan https://t.co/iPFRmSNhU6","in_reply_to_screen_name":"_Copah_Jay","in_reply_to_status_id_str":"1682734159708536832","in_reply_to_user_id_str":"1177132853487951873","is_quote_status":false,"lang":"en","possibly_sensitive":false,"possibly_sensitive_editable":true,"quote_count":0,"reply_count":0,"retweet_count":0,"retweeted":false,"user_id_str":"1482371511361183746","id_str":"1682857725452058624"},"quick_promote_eligibility":{"eligibility":"IneligibleNotProfessional"}}},"tweetDisplayType":"Tweet"},"clientEventInfo":{"details":{"conversationDetails":{"conversationSection":"HighQuality"},"timelinesDetails":{"controllerData":"DAACDAAEDAABCgABFIAKiDBjAAUKAAIAAAAABARACAAAAAA="}}}}}],"displayType":"VerticalConversation","clientEventInfo":{"details":{"conversationDetails":{"conversationSection":"HighQuality"}}}}},{"entryId":"conversationthread-1682745176433860617","sortIndex":"7540637877146237655","content":{"entryType":"TimelineTimelineModule","__typename":"TimelineTimelineModule","items":[{"entryId":"conversationthread-1682745176433860617-tweet-1682745176433860617","item":{"itemContent":{"itemType":"TimelineTweet","__typename":"TimelineTweet","tweet_results":{"result":{"__typename":"Tweet","rest_id":"1682745176433860617","has_birdwatch_notes":false,"core":{"user_results":{"result":{"__typename":"User","id":"VXNlcjoxNTM3MTY1NDQzMzk1NDYxMTIy","rest_id":"1537165443395461122","affiliates_highlighted_label":{},"has_graduated_access":true,"is_blue_verified":false,"legacy":{"can_dm":false,"can_media_tag":true,"created_at":"Wed Jun 15 20:12:02 +0000 2022","default_profile":true,"default_profile_image":false,"description":"Let’s chase the Bag 💯","entities":{"description":{"urls":[]}},"fast_followers_count":0,"favourites_count":75853,"followers_count":1355,"friends_count":1952,"has_custom_timelines":true,"is_translator":false,"listed_count":0,"location":"Lagos, Nigeria","media_count":27,"name":"Opolo baba 90","normal_followers_count":1355,"pinned_tweet_ids_str":["1545342500847734784"],"possibly_sensitive":false,"profile_banner_url":"https://pbs.twimg.com/profile_banners/1537165443395461122/1655410396","profile_image_url_https":"https://pbs.twimg.com/profile_images/1632649161857290241/HnxHtMyG_normal.jpg","profile_interstitial_type":"","screen_name":"Chriz_lynx1","statuses_count":2695,"translator_type":"none","verified":false,"want_retweets":false,"withheld_in_countries":[]},"smart_blocked_by":false,"smart_blocking":false,"business_account":{}}}},"edit_control":{"edit_tweet_ids":["1682745176433860617"],"editable_until_msecs":"1690036288000","is_edit_eligible":false,"edits_remaining":"5"},"edit_perspective":{"favorited":false,"retweeted":false},"is_translatable":false,"views":{"count":"410","state":"EnabledWithCount"},"source":"<a href=\"http://twitter.com/download/iphone\" rel=\"nofollow\">Twitter for iPhone</a>","legacy":{"created_at":"Sat Jul 22 13:31:28 +0000 2023","conversation_id_str":"1682734159708536832","display_text_range":[12,63],"entities":{"user_mentions":[{"id_str":"1177132853487951873","name":"Amber_Jay 🦋🐶🦋","screen_name":"_Copah_Jay","indices":[0,11]}],"urls":[],"hashtags":[],"symbols":[]},"favorite_count":1,"favorited":false,"full_text":"@_Copah_Jay No mind them mumu people….religion don wound them.🤣","in_reply_to_screen_name":"_Copah_Jay","in_reply_to_status_id_str":"1682734159708536832","in_reply_to_user_id_str":"1177132853487951873","is_quote_status":false,"lang":"en","quote_count":0,"reply_count":0,"retweet_count":1,"retweeted":false,"user_id_str":"1537165443395461122","id_str":"1682745176433860617"},"quick_promote_eligibility":{"eligibility":"IneligibleNotProfessional"}}},"tweetDisplayType":"Tweet"},"clientEventInfo":{"details":{"conversationDetails":{"conversationSection":"HighQuality"},"timelinesDetails":{"controllerData":"DAACDAAEDAABCgABFIAaiCADAAUKAAIAAAAABARACAAAAAA="}}}}}],"displayType":"VerticalConversation","clientEventInfo":{"details":{"conversationDetails":{"conversationSection":"HighQuality"}}}}},{"entryId":"conversationthread-1682833504361381894","sortIndex":"7540637877146237645","content":{"entryType":"TimelineTimelineModule","__typename":"TimelineTimelineModule","items":[{"entryId":"conversationthread-1682833504361381894-tweet-1682833504361381894","item":{"itemContent":{"itemType":"TimelineTweet","__typename":"TimelineTweet","tweet_results":{"result":{"__typename":"Tweet","rest_id":"1682833504361381894","has_birdwatch_notes":false,"core":{"user_results":{"result":{"__typename":"User","id":"VXNlcjoxNjExMzk3MjAzMzg1MzU2Mjg4","rest_id":"1611397203385356288","affiliates_highlighted_label":{},"has_graduated_access":true,"is_blue_verified":false,"legacy":{"can_dm":true,"can_media_tag":true,"created_at":"Fri Jan 06 16:20:22 +0000 2023","default_profile":true,"default_profile_image":false,"description":"Love and light \nSport enthusiast (football majorly)\nTech guy in view (data analyst) ||","entities":{"description":{"urls":[]}},"fast_followers_count":0,"favourites_count":274,"followers_count":11,"friends_count":85,"has_custom_timelines":true,"is_translator":false,"listed_count":0,"location":"","media_count":15,"name":"Bukunmi Joseph","normal_followers_count":11,"pinned_tweet_ids_str":[],"possibly_sensitive":false,"profile_banner_url":"https://pbs.twimg.com/profile_banners/1611397203385356288/1675241268","profile_image_url_https":"https://pbs.twimg.com/profile_images/1620705258195353605/z8dQ1pkE_normal.jpg","profile_interstitial_type":"","screen_name":"Bukunmijoseph07","statuses_count":263,"translator_type":"none","verified":false,"want_retweets":false,"withheld_in_countries":[]},"smart_blocked_by":false,"smart_blocking":false,"business_account":{}}}},"edit_control":{"edit_tweet_ids":["1682833504361381894"],"editable_until_msecs":"1690057347000","is_edit_eligible":false,"edits_remaining":"5"},"edit_perspective":{"favorited":false,"retweeted":false},"is_translatable":false,"views":{"count":"44","state":"EnabledWithCount"},"source":"<a href=\"http://twitter.com/download/iphone\" rel=\"nofollow\">Twitter for iPhone</a>","legacy":{"created_at":"Sat Jul 22 19:22:27 +0000 2023","conversation_id_str":"1682734159708536832","display_text_range":[12,116],"entities":{"user_mentions":[{"id_str":"1177132853487951873","name":"Amber_Jay 🦋🐶🦋","screen_name":"_Copah_Jay","indices":[0,11]}],"urls":[],"hashtags":[],"symbols":[]},"favorite_count":1,"favorited":false,"full_text":"@_Copah_Jay I remembered when I wore Jalabia to a bar and one Muslim guy said what I did was wrong.\n\nI was shocked 😮","in_reply_to_screen_name":"_Copah_Jay","in_reply_to_status_id_str":"1682734159708536832","in_reply_to_user_id_str":"1177132853487951873","is_quote_status":false,"lang":"en","quote_count":0,"reply_count":0,"retweet_count":0,"retweeted":false,"user_id_str":"1611397203385356288","id_str":"1682833504361381894"},"quick_promote_eligibility":{"eligibility":"IneligibleNotProfessional"}}},"tweetDisplayType":"Tweet"},"clientEventInfo":{"details":{"conversationDetails":{"conversationSection":"HighQuality"},"timelinesDetails":{"controllerData":"DAACDAAEDAABCgABFIAKiCADAAUKAAIAAAAABARACAAAAAA="}}}}}],"displayType":"VerticalConversation","clientEventInfo":{"details":{"conversationDetails":{"conversationSection":"HighQuality"}}}}},{"entryId":"conversationthread-1682825290471415809","sortIndex":"7540637877146237635","content":{"entryType":"TimelineTimelineModule","__typename":"TimelineTimelineModule","items":[{"entryId":"conversationthread-1682825290471415809-tweet-1682825290471415809","item":{"itemContent":{"itemType":"TimelineTweet","__typename":"TimelineTweet","tweet_results":{"result":{"__typename":"Tweet","rest_id":"1682825290471415809","has_birdwatch_notes":false,"core":{"user_results":{"result":{"__typename":"User","id":"VXNlcjoxNTk1MDUwOTQ4NjY1MTQ3Mzk2","rest_id":"1595050948665147396","affiliates_highlighted_label":{},"has_graduated_access":true,"is_blue_verified":false,"legacy":{"can_dm":false,"can_media_tag":true,"created_at":"Tue Nov 22 13:46:06 +0000 2022","default_profile":true,"default_profile_image":false,"description":"💼","entities":{"description":{"urls":[]}},"fast_followers_count":0,"favourites_count":35753,"followers_count":68,"friends_count":570,"has_custom_timelines":true,"is_translator":false,"listed_count":0,"location":"Lagos","media_count":7,"name":"Samuel","normal_followers_count":68,"pinned_tweet_ids_str":[],"possibly_sensitive":false,"profile_image_url_https":"https://pbs.twimg.com/profile_images/1637827732171096067/Jw9QsCB__normal.jpg","profile_interstitial_type":"","screen_name":"SOshodipe","statuses_count":1474,"translator_type":"none","verified":false,"want_retweets":false,"withheld_in_countries":[]},"smart_blocked_by":false,"smart_blocking":false,"business_account":{}}}},"edit_control":{"edit_tweet_ids":["1682825290471415809"],"editable_until_msecs":"1690055389000","is_edit_eligible":false,"edits_remaining":"5"},"edit_perspective":{"favorited":false,"retweeted":false},"is_translatable":false,"views":{"count":"5","state":"EnabledWithCount"},"source":"<a href=\"http://twitter.com/download/iphone\" rel=\"nofollow\">Twitter for iPhone</a>","legacy":{"created_at":"Sat Jul 22 18:49:49 +0000 2023","conversation_id_str":"1682734159708536832","display_text_range":[12,76],"entities":{"user_mentions":[{"id_str":"1177132853487951873","name":"Amber_Jay 🦋🐶🦋","screen_name":"_Copah_Jay","indices":[0,11]}],"urls":[],"hashtags":[],"symbols":[]},"favorite_count":2,"favorited":false,"full_text":"@_Copah_Jay An Islam that doesn’t see sin in the mass poverty in the north 💔","in_reply_to_screen_name":"_Copah_Jay","in_reply_to_status_id_str":"1682734159708536832","in_reply_to_user_id_str":"1177132853487951873","is_quote_status":false,"lang":"en","quote_count":0,"reply_count":0,"retweet_count":0,"retweeted":false,"user_id_str":"1595050948665147396","id_str":"1682825290471415809"},"quick_promote_eligibility":{"eligibility":"IneligibleNotProfessional"}}},"tweetDisplayType":"Tweet"},"clientEventInfo":{"details":{"conversationDetails":{"conversationSection":"HighQuality"},"timelinesDetails":{"controllerData":"DAACDAAEDAABCgABFIAaiCADAAUKAAIAAAAABARACAAAAAA="}}}}}],"displayType":"VerticalConversation","clientEventInfo":{"details":{"conversationDetails":{"conversationSection":"HighQuality"}}}}},{"entryId":"conversationthread-1682843200321355778","sortIndex":"7540637877146237625","content":{"entryType":"TimelineTimelineModule","__typename":"TimelineTimelineModule","items":[{"entryId":"conversationthread-1682843200321355778-tweet-1682843200321355778","item":{"itemContent":{"itemType":"TimelineTweet","__typename":"TimelineTweet","tweet_results":{"result":{"__typename":"Tweet","rest_id":"1682843200321355778","has_birdwatch_notes":false,"core":{"user_results":{"result":{"__typename":"User","id":"VXNlcjoyNTQzNjYwNzQx","rest_id":"2543660741","affiliates_highlighted_label":{},"has_graduated_access":true,"is_blue_verified":false,"legacy":{"can_dm":false,"can_media_tag":true,"created_at":"Mon May 12 20:10:40 +0000 2014","default_profile":true,"default_profile_image":false,"description":"Mobile phone technician, IPhone guru,specialist on Repair and sales of Apple’s🍏products. The gentle soul, striver of Aljanah firdaus,Epitome of Allah’s grace","entities":{"description":{"urls":[]}},"fast_followers_count":0,"favourites_count":149,"followers_count":199,"friends_count":2218,"has_custom_timelines":true,"is_translator":false,"listed_count":0,"location":"Ibadan","media_count":86,"name":"YOUR IPHONE🔌","normal_followers_count":199,"pinned_tweet_ids_str":["1486263344940163072"],"possibly_sensitive":false,"profile_banner_url":"https://pbs.twimg.com/profile_banners/2543660741/1655890465","profile_image_url_https":"https://pbs.twimg.com/profile_images/1520061503415717889/vR2wH6ki_normal.jpg","profile_interstitial_type":"","screen_name":"sirmorefilm","statuses_count":1996,"translator_type":"none","verified":false,"want_retweets":false,"withheld_in_countries":[]},"professional":{"rest_id":"1503123162602651654","professional_type":"Creator","category":[{"id":477,"name":"Professional Services","icon_name":"IconBriefcaseStroke"}]},"smart_blocked_by":false,"smart_blocking":false,"business_account":{}}}},"edit_control":{"edit_tweet_ids":["1682843200321355778"],"editable_until_msecs":"1690059659000","is_edit_eligible":false,"edits_remaining":"5"},"edit_perspective":{"favorited":false,"retweeted":false},"is_translatable":false,"views":{"count":"10","state":"EnabledWithCount"},"source":"<a href=\"http://twitter.com/download/iphone\" rel=\"nofollow\">Twitter for iPhone</a>","legacy":{"created_at":"Sat Jul 22 20:00:59 +0000 2023","conversation_id_str":"1682734159708536832","display_text_range":[12,90],"entities":{"user_mentions":[{"id_str":"1177132853487951873","name":"Amber_Jay 🦋🐶🦋","screen_name":"_Copah_Jay","indices":[0,11]}],"urls":[],"hashtags":[],"symbols":[]},"favorite_count":0,"favorited":false,"full_text":"@_Copah_Jay Perhaps did they portray any kind of observing prayer here, say another things","in_reply_to_screen_name":"_Copah_Jay","in_reply_to_status_id_str":"1682734159708536832","in_reply_to_user_id_str":"1177132853487951873","is_quote_status":false,"lang":"en","quote_count":0,"reply_count":0,"retweet_count":0,"retweeted":false,"user_id_str":"2543660741","id_str":"1682843200321355778"},"quick_promote_eligibility":{"eligibility":"IneligibleNotProfessional"}}},"tweetDisplayType":"Tweet"},"clientEventInfo":{"details":{"conversationDetails":{"conversationSection":"HighQuality"},"timelinesDetails":{"controllerData":"DAACDAAEDAABCgABFIAKiCADAAUKAAIAAAAABARACAAAAAA="}}}}}],"displayType":"VerticalConversation","clientEventInfo":{"details":{"conversationDetails":{"conversationSection":"HighQuality"}}}}},{"entryId":"conversationthread-1682840731386363913","sortIndex":"7540637877146237615","content":{"entryType":"TimelineTimelineModule","__typename":"TimelineTimelineModule","items":[{"entryId":"conversationthread-1682840731386363913-tweet-1682840731386363913","item":{"itemContent":{"itemType":"TimelineTweet","__typename":"TimelineTweet","tweet_results":{"result":{"__typename":"Tweet","rest_id":"1682840731386363913","has_birdwatch_notes":false,"core":{"user_results":{"result":{"__typename":"User","id":"VXNlcjoxNjA4ODM5ODI0MDQzMDMyNTgy","rest_id":"1608839824043032582","affiliates_highlighted_label":{},"has_graduated_access":true,"is_blue_verified":false,"legacy":{"can_dm":true,"can_media_tag":true,"created_at":"Fri Dec 30 14:58:26 +0000 2022","default_profile":true,"default_profile_image":false,"description":"#Dubnation | #CFC | 449","entities":{"description":{"urls":[]}},"fast_followers_count":0,"favourites_count":14804,"followers_count":1232,"friends_count":969,"has_custom_timelines":false,"is_translator":false,"listed_count":3,"location":"My House","media_count":531,"name":"Jingo🔰","normal_followers_count":1232,"pinned_tweet_ids_str":[],"possibly_sensitive":false,"profile_banner_url":"https://pbs.twimg.com/profile_banners/1608839824043032582/1680902931","profile_image_url_https":"https://pbs.twimg.com/profile_images/1668181037292179456/2XmGqq1e_normal.jpg","profile_interstitial_type":"","screen_name":"JingoTheDon","statuses_count":10296,"translator_type":"none","verified":false,"want_retweets":false,"withheld_in_countries":[]},"smart_blocked_by":false,"smart_blocking":false,"business_account":{}}}},"edit_control":{"edit_tweet_ids":["1682840731386363913"],"editable_until_msecs":"1690059070000","is_edit_eligible":false,"edits_remaining":"5"},"edit_perspective":{"favorited":false,"retweeted":false},"is_translatable":false,"views":{"count":"44","state":"EnabledWithCount"},"source":"<a href=\"http://twitter.com/download/android\" rel=\"nofollow\">Twitter for Android</a>","legacy":{"created_at":"Sat Jul 22 19:51:10 +0000 2023","conversation_id_str":"1682734159708536832","display_text_range":[12,139],"entities":{"user_mentions":[{"id_str":"1177132853487951873","name":"Amber_Jay 🦋🐶🦋","screen_name":"_Copah_Jay","indices":[0,11]}],"urls":[],"hashtags":[],"symbols":[]},"favorite_count":1,"favorited":false,"full_text":"@_Copah_Jay Brooo, this is the exact song I was listening to right now on Spotify when I clicked on this video to watch it, that's WILD!!😳🤣","in_reply_to_screen_name":"_Copah_Jay","in_reply_to_status_id_str":"1682734159708536832","in_reply_to_user_id_str":"1177132853487951873","is_quote_status":false,"lang":"en","quote_count":0,"reply_count":0,"retweet_count":0,"retweeted":false,"user_id_str":"1608839824043032582","id_str":"1682840731386363913"},"quick_promote_eligibility":{"eligibility":"IneligibleNotProfessional"}}},"tweetDisplayType":"Tweet"},"clientEventInfo":{"details":{"conversationDetails":{"conversationSection":"HighQuality"},"timelinesDetails":{"controllerData":"DAACDAAEDAABCgABFIAKiCADAAUKAAIAAAAABARACAAAAAA="}}}}}],"displayType":"VerticalConversation","clientEventInfo":{"details":{"conversationDetails":{"conversationSection":"HighQuality"}}}}},{"entryId":"cursor-bottom-3936474072949653438","sortIndex":"7540637877146237614","content":{"entryType":"TimelineTimelineItem","__typename":"TimelineTimelineItem","itemContent":{"itemType":"TimelineTimelineCursor","__typename":"TimelineTimelineCursor","value":"1AQAAPAPHBn2iAGGgL2NzsW72i6AwNH9sZHj2i6CgL713661CQDhvaHt5MbaLoSAs-nl7dIbAPEHxYbm5NougIC8veDD3dougsC-odbmpC0AQMn348gSAFCzmZHW0CQAUb6xusXbCQBA0fT91GMAUL7h9ZbqEgBRsa2ssroSADHNyNl-AECzsaWPSABgwL2F2OKvEgBQvZ3BssAtAFDQnYKx0YcAUbHt6vG5GwAwwf-WCQBhgL218KnYNgDQ6cj5o9oujICwuf-J0AkAULyZ-Yy9mQBQsMGa5cUtAOHRlaS7xtoukoC-_dSu01EAQI2byNEkAFDUvcK05gkAUbO9hYW2mQAw3dTutABggLal4aGzGwBRtqXhh7QpAUCdhvHiPwBRto3OhckOAUDdkKfBEgBRvN2ImLsOAUCZ8avMEgBRvo2tkNWrAEG987e2hwBAoafCwYcAUL2N0fSnLQBBsf3ixWMAUb3d2sW4LQBA0Z_-pwkA4bP1iIjT2i6GgLG986nLLQBB1byUuqsAQcHyucv8AEGB18--GwAxscbwMgFQvtnV8rR-AEGw_a--xgBRsNGut6YkAEGhuafXhwBB-fWC4dQBQb239NF1AEHZhIa-ngHRnZLx3NouiICz3eSUwlEAQf2llqQbAEHFkcjEgwFBmfjUqBIAMfHe7zcCQrHN7OoBAsGR0cHD2i6QwL3plKQ3AlC8-f_czZAA4b3NlvSy2i6KgLb1lq7DVgFC7ebBxkQBIYjKpwFRsMH9mbBIADHBn9guAkC2sbiVdgJhwNDRtpfrSABBqdfXvZkAQPWAm6MJAFHSiZXN2pAAMaX6zxwCUbzF1LW66gBBgeSPuGwAQbHkicUXATHJxoI_AFG2tbnxxGwAMaW-yxcBUbGJ9Lm7HAIx3auovgJBsfWJ5awCQbOphfOiAFC89eaN18YAQbOt1d83AkGwrcO2zwBRvLXav6sJAMH9nP6v2i6EwLOF7Md1AFGxmd31srABQPHpur8gAVC-neTL4lEAUNP5ovu-tQJRsZm4mMdsAEHt5dK0WgBB1YzzqQkAMd2DrmgBUbDR16m9JABAkcejvIcAQbHV4aHPAFG9pcP32IwBMMnm0VYBYcDUmaGK7OYBMd2z0rABUdO94YDgPwBB0dK40FsCMYGPggYDUbONh7jPCQBBgdu9qTsBQN3do8CZAOGzybT_1doujoCzlbmi0AECQq2kw6h1ACHI7SUCMrOJnLoDUb71-vTbYwBBlaqduCYEQYHnlL1oAUC9z-_SdQBCvYHR8KcBQdHsi9t1AEDht5S8NgBR0uG8iLJ3BEGlsf2ozwAx6Y3a5gFQs-HwqLBWAVK98ce8vFwEwJzoptouJQISFQQAAA","cursorType":"Bottom"}}}]},{"type":"TimelineTerminateTimeline","direction":"Top"}]}}}