{"data":{"threaded_conversation_with_injections_v2":{"instructions":[{"type":"TimelineAddEntries","entries":[{"entryId":"conversationthread-1673154617864077313","sortIndex":"7550299442313269106","content":{"entryType":"TimelineTimelineModule","__typename":"TimelineTimelineModule","items":[{"entryId":"conversationthread-1673154617864077313-tweet-1673154617864077313","item":{"itemContent":{"itemType":"TimelineTweet","__typename":"TimelineTweet","tweet_results":{"result":{"__typename":"Tweet","rest_id":"1673154617864077313","has_birdwatch_notes":false,"core":{"user_results":{"result":{"__typename":"User","id":"VXNlcjo5Mjc0NzAy","rest_id":"9274702","affiliates_highlighted_label":{},"has_graduated_access":true,"is_blue_verified":true,"legacy":{"can_dm":true,"can_media_tag":false,"created_at":"Sat Oct 06 03:35:26 +0000 2007","default_profile":false,"default_profile_image":false,"description":"Multifaceted Creator: Film/Video Editor | Website Builder | Marketing Strategist | IG Reels Specialist | Making social content @socialvidpro |🇺🇸 🇩🇿 ⵣ","entities":{"description":{"urls":[]},"url":{"urls":[{"display_url":"socialvidpro.com","expanded_url":"https://socialvidpro.com","url":"https://t.co/b8S1RWBNue","indices":[0,23]}]}},"fast_followers_count":0,"favourites_count":10536,"followers_count":862,"friends_count":778,"has_custom_timelines":true,"is_translator":false,"listed_count":64,"location":"Dallas, TX","media_count":542,"name":"Mike Nease","normal_followers_count":862,"pinned_tweet_ids_str":[],"possibly_sensitive":false,"profile_banner_url":"https://pbs.twimg.com/profile_banners/9274702/1681540333","profile_image_url_https":"https://pbs.twimg.com/profile_images/1643051656915943425/zzZCUH_s_normal.jpg","profile_interstitial_type":"","screen_name":"nease","statuses_count":6869,"translator_type":"none","url":"https://t.co/b8S1RWBNue","verified":false,"want_retweets":false,"withheld_in_countries":[]},"professional":{"rest_id":"1590734268078215169","professional_type":"Creator","category":[{"id":1032,"name":"Filmmaker","icon_name":"IconBriefcaseStroke"}]},"smart_blocked_by":false,"smart_blocking":false,"business_account":{}}}},"edit_control":{"edit_tweet_ids":["1673154617864077313"],"editable_until_msecs":"1687749721000","is_edit_eligible":false,"edits_remaining":"5"},"edit_perspective":{"favorited":false,"retweeted":false},"is_translatable":false,"views":{"count":"2353","state":"EnabledWithCount"},"source":"<a href=\"https://mobile.twitter.com\" rel=\"nofollow\">Twitter Web App</a>","legacy":{"created_at":"Mon Jun 26 02:22:01 +0000 2023","conversation_id_str":"1673072594541506561","display_text_range":[15,47],"entities":{"user_mentions":[{"id_str":"243013409","name":"Sawyer Merritt","screen_name":"SawyerMerritt","indices":[0,14]}],"urls":[],"hashtags":[],"symbols":[]},"favorite_count":3,"favorited":false,"full_text":"@SawyerMerritt Does it come with a trench coat?","in_reply_to_screen_name":"SawyerMerritt","in_reply_to_status_id_str":"1673072594541506561","in_reply_to_user_id_str":"243013409","is_quote_status":false,"lang":"en","quote_count":0,"reply_count":1,"retweet_count":1,"retweeted":false,"user_id_str":"9274702","id_str":"1673154617864077313"},"quick_promote_eligibility":{"eligibility":"IneligibleNotProfessional"}}},"tweetDisplayType":"Tweet"},"clientEventInfo":{"details":{"conversationDetails":{"conversationSection":"HighQuality"},"timelinesDetails":{"controllerData":"DAACDAAEDAABCgABFKACCCAHAAUKAAIAAAAAGAJACAAAAAA="}}}}},{"entryId":"conversationthread-1673154617864077313-cursor-showmore-2315303868824477805","item":{"itemContent":{"itemType":"TimelineTimelineCursor","__typename":"TimelineTimelineCursor","value":"PAAAAPAtPBwcFoKAvsHT0J64LhUCAAAYJmNvbnZlcnNhdGlvbnRocmVhZC0xNjczMTU0NjE3ODY0MDc3MzEzIgAA","cursorType":"ShowMore","displayTreatment":{"actionText":"Show replies"}},"clientEventInfo":{"details":{"conversationDetails":{"conversationSection":"HighQuality"}}}}}],"displayType":"VerticalConversation","clientEventInfo":{"details":{"conversationDetails":{"conversationSection":"HighQuality"}}}}},{"entryId":"conversationthread-1673170625160945664","sortIndex":"7550299442313269096","content":{"entryType":"TimelineTimelineModule","__typename":"TimelineTimelineModule","items":[{"entryId":"conversationthread-1673170625160945664-tweet-1673170625160945664","item":{"itemContent":{"itemType":"TimelineTweet","__typename":"TimelineTweet","tweet_results":{"result":{"__typename":"Tweet","rest_id":"1673170625160945664","has_birdwatch_notes":false,"core":{"user_results":{"result":{"__typename":"User","id":"VXNlcjoxNTE5MTIzNDgzNDAxMjgxNTM2","rest_id":"1519123483401281536","affiliates_highlighted_label":{},"has_graduated_access":true,"is_blue_verified":true,"legacy":{"can_dm":true,"can_media_tag":false,"created_at":"Wed Apr 27 01:20:05 +0000 2022","default_profile":true,"default_profile_image":false,"description":"a joke to a jester","entities":{"description":{"urls":[]}},"fast_followers_count":0,"favourites_count":9314,"followers_count":717,"friends_count":110,"has_custom_timelines":true,"is_translator":false,"listed_count":6,"location":"West Virginia, USA","media_count":685,"name":"Strips4Monero","normal_followers_count":717,"pinned_tweet_ids_str":["1664785939615342593"],"possibly_sensitive":false,"profile_banner_url":"https://pbs.twimg.com/profile_banners/1519123483401281536/1658696587","profile_image_url_https":"https://pbs.twimg.com/profile_images/1519126401659682816/QpI4av2d_normal.jpg","profile_interstitial_type":"","screen_name":"Strips4Monero","statuses_count":7906,"translator_type":"none","verified":false,"want_retweets":false,"withheld_in_countries":[]},"smart_blocked_by":false,"smart_blocking":false,"business_account":{}}}},"edit_control":{"edit_tweet_ids":["1673170625160945664"],"editable_until_msecs":"1687753537000","is_edit_eligible":false,"edits_remaining":"5"},"edit_perspective":{"favorited":false,"retweeted":false},"is_translatable":false,"views":{"count":"1244","state":"EnabledWithCount"},"source":"<a href=\"http://twitter.com/download/iphone\" rel=\"nofollow\">Twitter for iPhone</a>","legacy":{"created_at":"Mon Jun 26 03:25:37 +0000 2023","conversation_id_str":"1673072594541506561","display_text_range":[15,41],"entities":{"user_mentions":[{"id_str":"243013409","name":"Sawyer Merritt","screen_name":"SawyerMerritt","indices":[0,14]}],"urls":[],"hashtags":[],"symbols":[]},"favorite_count":1,"favorited":false,"full_text":"@SawyerMerritt Surely you mean all-wheel?","in_reply_to_screen_name":"SawyerMerritt","in_reply_to_status_id_str":"1673072594541506561","in_reply_to_user_id_str":"243013409","is_quote_status":false,"lang":"en","quote_count":0,"reply_count":1,"retweet_count":1,"retweeted":false,"user_id_str":"1519123483401281536","id_str":"1673170625160945664"},"quick_promote_eligibility":{"eligibility":"IneligibleNotProfessional"}}},"tweetDisplayType":"Tweet"},"clientEventInfo":{"details":{"conversationDetails":{"conversationSection":"HighQuality"},"timelinesDetails":{"controllerData":"DAACDAAEDAABCgABFKACCCIDAAUKAAIAAAAAGAJACAAAAAA="}}}}},{"entryId":"conversationthread-1673170625160945664-cursor-showmore-1506221424601968511","item":{"itemContent":{"itemType":"TimelineTimelineCursor","__typename":"TimelineTimelineCursor","value":"PAAAAPAtPBwcFoCAsZWz9KW4LhUCAAAYJmNvbnZlcnNhdGlvbnRocmVhZC0xNjczMTcwNjI1MTYwOTQ1NjY0IgAA","cursorType":"ShowMore","displayTreatment":{"actionText":"Show replies"}},"clientEventInfo":{"details":{"conversationDetails":{"conversationSection":"HighQuality"}}}}}],"displayType":"VerticalConversation","clientEventInfo":{"details":{"conversationDetails":{"conversationSection":"HighQuality"}}}}},{"entryId":"conversationthread-1673302674815557632","sortIndex":"7550299442313269086","content":{"entryType":"TimelineTimelineModule","__typename":"TimelineTimelineModule","items":[{"entryId":"conversationthread-1673302674815557632-tweet-1673302674815557632","item":{"itemContent":{"itemType":"TimelineTweet","__typename":"TimelineTweet","tweet_results":{"result":{"__typename":"Tweet","rest_id":"1673302674815557632","has_birdwatch_notes":false,"core":{"user_results":{"result":{"__typename":"User","id":"VXNlcjo4ODI4NDM0OA==","rest_id":"88284348","affiliates_highlighted_label":{},"has_graduated_access":true,"is_blue_verified":true,"legacy":{"can_dm":true,"can_media_tag":true,"created_at":"Sat Nov 07 22:13:35 +0000 2009","default_profile":true,"default_profile_image":false,"description":"Award Winning Journalist, Boxer, UFO Aficionado, University of Paris, Betty White College of Journalism, Best stories over a cold beer, No Budweiser….. please","entities":{"description":{"urls":[]}},"fast_followers_count":0,"favourites_count":1600,"followers_count":312,"friends_count":771,"has_custom_timelines":true,"is_translator":false,"listed_count":5,"location":"Chicago, IL","media_count":121,"name":"Franc Pea","normal_followers_count":312,"pinned_tweet_ids_str":[],"possibly_sensitive":false,"profile_banner_url":"https://pbs.twimg.com/profile_banners/88284348/1680524125","profile_image_url_https":"https://pbs.twimg.com/profile_images/1641375585988386816/3OwBUqIQ_normal.jpg","profile_interstitial_type":"","screen_name":"Doubleraise","statuses_count":2325,"translator_type":"none","verified":false,"want_retweets":false,"withheld_in_countries":[]},"professional":{"rest_id":"1592410322559803394","professional_type":"Business","category":[{"id":933,"name":"Media Personality","icon_name":"IconBriefcaseStroke"}]},"smart_blocked_by":false,"smart_blocking":false,"business_account":{}}}},"edit_control":{"edit_tweet_ids":["1673302674815557632"],"editable_until_msecs":"1687785020000","is_edit_eligible":false,"edits_remaining":"5"},"edit_perspective":{"favorited":false,"retweeted":false},"is_translatable":false,"views":{"count":"1381","state":"EnabledWithCount"},"source":"<a href=\"http://twitter.com/download/iphone\" rel=\"nofollow\">Twitter for iPhone</a>","legacy":{"created_at":"Mon Jun 26 12:10:20 +0000 2023","conversation_id_str":"1673072594541506561","display_text_range":[15,53],"entities":{"user_mentions":[{"id_str":"243013409","name":"Sawyer Merritt","screen_name":"SawyerMerritt","indices":[0,14]}],"urls":[],"hashtags":[],"symbols":[]},"favorite_count":5,"favorited":false,"full_text":"@SawyerMerritt Can I get it in the gasoline version ?","in_reply_to_screen_name":"SawyerMerritt","in_reply_to_status_id_str":"1673072594541506561","in_reply_to_user_id_str":"243013409","is_quote_status":false,"lang":"en","quote_count":0,"reply_count":1,"retweet_count":1,"retweeted":false,"user_id_str":"88284348","id_str":"1673302674815557632"},"quick_promote_eligibility":{"eligibility":"IneligibleNotProfessional"}}},"tweetDisplayType":"Tweet"},"clientEventInfo":{"details":{"conversationDetails":{"conversationSection":"HighQuality"},"timelinesDetails":{"controllerData":"DAACDAAEDAABCgABFKACCCQDAAUKAAIAAAAAGAJACAAAAAA="}}}}},{"entryId":"conversationthread-1673302674815557632-cursor-showmore-4763814397501588008","item":{"itemContent":{"itemType":"TimelineTimelineCursor","__typename":"TimelineTimelineCursor","value":"PAAAAPAtPBwcFoCAveHZ-uG4LhUCAAAYJmNvbnZlcnNhdGlvbnRocmVhZC0xNjczMzAyNjc0ODE1NTU3NjMyIgAA","cursorType":"ShowMore","displayTreatment":{"actionText":"Show replies"}},"clientEventInfo":{"details":{"conversationDetails":{"conversationSection":"HighQuality"}}}}}],"displayType":"VerticalConversation","clientEventInfo":{"details":{"conversationDetails":{"conversationSection":"HighQuality"}}}}},{"entryId":"conversationthread-1673370084683792385","sortIndex":"7550299442313269076","content":{"entryType":"TimelineTimelineModule","__typename":"TimelineTimelineModule","items":[{"entryId":"conversationthread-1673370084683792385-tweet-1673370084683792385","item":{"itemContent":{"itemType":"TimelineTweet","__typename":"TimelineTweet","tweet_results":{"result":{"__typename":"Tweet","rest_id":"1673370084683792385","has_birdwatch_notes":false,"core":{"user_results":{"result":{"__typename":"User","id":"VXNlcjoyNTQ5Mzg1Mg==","rest_id":"25493852","affiliates_highlighted_label":{},"has_graduated_access":true,"is_blue_verified":true,"legacy":{"can_dm":false,"can_media_tag":true,"created_at":"Fri Mar 20 12:13:05 +0000 2009","default_profile":false,"default_profile_image":false,"description":"","entities":{"description":{"urls":[]}},"fast_followers_count":0,"favourites_count":92139,"followers_count":548,"friends_count":2191,"has_custom_timelines":true,"is_translator":false,"listed_count":9,"location":"london, UK","media_count":359,"name":"Anthony","normal_followers_count":548,"pinned_tweet_ids_str":[],"possibly_sensitive":false,"profile_banner_url":"https://pbs.twimg.com/profile_banners/25493852/1616442699","profile_image_url_https":"https://pbs.twimg.com/profile_images/1673751814284406785/PBUX-Dt8_normal.jpg","profile_interstitial_type":"","screen_name":"cuernogroup","statuses_count":4554,"translator_type":"none","verified":false,"want_retweets":false,"withheld_in_countries":[]},"smart_blocked_by":false,"smart_blocking":false,"business_account":{}}}},"edit_control":{"edit_tweet_ids":["1673370084683792385"],"editable_until_msecs":"1687801092000","is_edit_eligible":false,"edits_remaining":"5"},"edit_perspective":{"favorited":false,"retweeted":false},"is_translatable":false,"views":{"count":"2534","state":"EnabledWithCount"},"source":"<a href=\"https://mobile.twitter.com\" rel=\"nofollow\">Twitter Web App</a>","legacy":{"created_at":"Mon Jun 26 16:38:12 +0000 2023","conversation_id_str":"1673072594541506561","display_text_range":[15,150],"entities":{"user_mentions":[{"id_str":"243013409","name":"Sawyer Merritt","screen_name":"SawyerMerritt","indices":[0,14]}],"urls":[],"hashtags":[],"symbols":[]},"favorite_count":230,"favorited":false,"full_text":"@SawyerMerritt This is not a city vehicle. visibility is dreadful and your situational awareness is seriously impeded by the clunky design of the car.","in_reply_to_screen_name":"SawyerMerritt","in_reply_to_status_id_str":"1673072594541506561","in_reply_to_user_id_str":"243013409","is_quote_status":false,"lang":"en","quote_count":0,"reply_count":2,"retweet_count":1,"retweeted":false,"user_id_str":"25493852","id_str":"1673370084683792385"},"quick_promote_eligibility":{"eligibility":"IneligibleNotProfessional"}}},"tweetDisplayType":"Tweet"},"clientEventInfo":{"details":{"conversationDetails":{"conversationSection":"HighQuality"},"timelinesDetails":{"controllerData":"DAACDAAEDAABCgABFKACCCgDAAUKAAIAAAAAGAJACAAAAAA="}}}}},{"entryId":"conversationthread-1673370084683792385-cursor-showmore-2801255266966660039","item":{"itemContent":{"itemType":"TimelineTimelineCursor","__typename":"TimelineTimelineCursor","value":"PAAAAPAtPBwcFoKAvrW8zoC5LhUCAAAYJmNvbnZlcnNhdGlvbnRocmVhZC0xNjczMzcwMDg0NjgzNzkyMzg1IgAA","cursorType":"ShowMore","displayTreatment":{"actionText":"Show replies"}},"clientEventInfo":{"details":{"conversationDetails":{"conversationSection":"HighQuality"}}}}}],"displayType":"VerticalConversation","clientEventInfo":{"details":{"conversationDetails":{"conversationSection":"HighQuality"}}}}},{"entryId":"conversationthread-1673076897016860672","sortIndex":"7550299442313269066","content":{"entryType":"TimelineTimelineModule","__typename":"TimelineTimelineModule","items":[{"entryId":"conversationthread-1673076897016860672-tweet-1673076897016860672","item":{"itemContent":{"itemType":"TimelineTweet","__typename":"TimelineTweet","tweet_results":{"result":{"__typename":"Tweet","rest_id":"1673076897016860672","has_birdwatch_notes":false,"core":{"user_results":{"result":{"__typename":"User","id":"VXNlcjo4ODI4MDk3OTI=","rest_id":"882809792","affiliates_highlighted_label":{},"has_graduated_access":true,"is_blue_verified":true,"legacy":{"can_dm":false,"can_media_tag":true,"created_at":"Mon Oct 15 18:01:15 +0000 2012","default_profile":true,"default_profile_image":false,"description":"long time tech investor, entrepreneur, tech background, new to Twitter, runs million members FB group with friends.","entities":{"description":{"urls":[]},"url":{"urls":[{"display_url":"facebook.com/groups/1242309…","expanded_url":"https://www.facebook.com/groups/1242309506256283/?ref=share_group_link","url":"https://t.co/xSapp4mhEX","indices":[0,23]}]}},"fast_followers_count":0,"favourites_count":1409,"followers_count":194,"friends_count":189,"has_custom_timelines":false,"is_translator":false,"listed_count":5,"location":"Thousand Oaks, CA","media_count":126,"name":"SpringTesla","normal_followers_count":194,"pinned_tweet_ids_str":["1662796027295076354"],"possibly_sensitive":false,"profile_banner_url":"https://pbs.twimg.com/profile_banners/882809792/1675054891","profile_image_url_https":"https://pbs.twimg.com/profile_images/1625253182749446144/YuxuThGK_normal.jpg","profile_interstitial_type":"","screen_name":"SpringTesla","statuses_count":965,"translator_type":"none","url":"https://t.co/xSapp4mhEX","verified":false,"want_retweets":false,"withheld_in_countries":[]},"professional":{"rest_id":"1633739470553092096","professional_type":"Business","category":[{"id":958,"name":"Entrepreneur","icon_name":"IconBriefcaseStroke"}]},"smart_blocked_by":false,"smart_blocking":false,"business_account":{}}}},"edit_control":{"edit_tweet_ids":["1673076897016860672"],"editable_until_msecs":"1687731191000","is_edit_eligible":false,"edits_remaining":"5"},"edit_perspective":{"favorited":false,"retweeted":false},"is_translatable":false,"views":{"count":"8030","state":"EnabledWithCount"},"source":"<a href=\"http://twitter.com/download/iphone\" rel=\"nofollow\">Twitter for iPhone</a>","legacy":{"created_at":"Sun Jun 25 21:13:11 +0000 2023","conversation_id_str":"1673072594541506561","display_text_range":[15,101],"entities":{"user_mentions":[{"id_str":"243013409","name":"Sawyer Merritt","screen_name":"SawyerMerritt","indices":[0,14]}],"urls":[],"hashtags":[],"symbols":[]},"favorite_count":6,"favorited":false,"full_text":"@SawyerMerritt Geez it’s everywhere now, but there are still many people saying it’s not happening Q3","in_reply_to_screen_name":"SawyerMerritt","in_reply_to_status_id_str":"1673072594541506561","in_reply_to_user_id_str":"243013409","is_quote_status":false,"lang":"en","quote_count":0,"reply_count":1,"retweet_count":1,"retweeted":false,"user_id_str":"882809792","id_str":"1673076897016860672"},"quick_promote_eligibility":{"eligibility":"IneligibleNotProfessional"}}},"tweetDisplayType":"Tweet"},"clientEventInfo":{"details":{"conversationDetails":{"conversationSection":"HighQuality"},"timelinesDetails":{"controllerData":"DAACDAAEDAABCgABFKACCDADAAUKAAIAAAAAGAJACAAAAAA="}}}}}],"displayType":"VerticalConversation","clientEventInfo":{"details":{"conversationDetails":{"conversationSection":"HighQuality"}}}}},{"entryId":"conversationthread-1673106113225535492","sortIndex":"7550299442313269056","content":{"entryType":"TimelineTimelineModule","__typename":"TimelineTimelineModule","items":[{"entryId":"conversationthread-1673106113225535492-tweet-1673106113225535492","item":{"itemContent":{"itemType":"TimelineTweet","__typename":"TimelineTweet","tweet_results":{"result":{"__typename":"Tweet","rest_id":"1673106113225535492","has_birdwatch_notes":false,"core":{"user_results":{"result":{"__typename":"User","id":"VXNlcjozNzAxMTAxMA==","rest_id":"37011010","affiliates_highlighted_label":{},"has_graduated_access":true,"is_blue_verified":true,"legacy":{"can_dm":false,"can_media_tag":true,"created_at":"Fri May 01 18:49:37 +0000 2009","default_profile":true,"default_profile_image":false,"description":"Thinker, writer, teacher, trader. Crazy about Evolution, Neuroscience, Econ and any other story we tell to explain how we got here and why we act the way we do.","entities":{"description":{"urls":[]},"url":{"urls":[{"display_url":"medium.com/@KevinBCook","expanded_url":"https://medium.com/@KevinBCook","url":"https://t.co/NPVKuisa2j","indices":[0,23]}]}},"fast_followers_count":0,"favourites_count":23951,"followers_count":4850,"friends_count":5325,"has_custom_timelines":true,"is_translator":false,"listed_count":230,"location":"Chicago","media_count":879,"name":"Kevin Brent Cook","normal_followers_count":4850,"pinned_tweet_ids_str":["1611018579276709890"],"possibly_sensitive":false,"profile_banner_url":"https://pbs.twimg.com/profile_banners/37011010/1460672944","profile_image_url_https":"https://pbs.twimg.com/profile_images/720740481362210816/HqrSUPaC_normal.jpg","profile_interstitial_type":"","screen_name":"KevinBCook","statuses_count":17874,"translator_type":"none","url":"https://t.co/NPVKuisa2j","verified":false,"want_retweets":false,"withheld_in_countries":[]},"smart_blocked_by":false,"smart_blocking":false,"business_account":{}}}},"card":{"rest_id":"https://t.co/VXA3A6rp51","legacy":{"binding_values":[{"key":"player_url","value":{"string_value":"https://www.youtube.com/embed/tJ1iIov1cUU","type":"STRING"}},{"key":"player_image_large","value":{"image_value":{"height":320,"width":569,"url":"https://pbs.twimg.com/card_img/1678199844077199362/k_Xms10b?format=jpg&name=800x320_1"},"type":"IMAGE"}},{"key":"player_image","value":{"image_value":{"height":158,"width":280,"url":"https://pbs.twimg.com/card_img/1678199844077199362/k_Xms10b?format=jpg&name=280x280"},"type":"IMAGE"}},{"key":"app_star_rating","value":{"string_value":"4.67955","type":"STRING"}},{"key":"description","value":{"string_value":"Imagine contractors adopting the power tools of the F-150 EV and turning heads across America.","type":"STRING"}},{"key":"player_width","value":{"string_value":"1280","type":"STRING"}},{"key":"domain","value":{"string_value":"www.youtube.com","type":"STRING"}},{"key":"app_is_free","value":{"string_value":"true","type":"STRING"}},{"key":"site","value":{"scribe_key":"publisher_id","type":"USER","user_value":{"id_str":"10228272","path":[]}}},{"key":"player_image_original","value":{"image_value":{"height":720,"width":1280,"url":"https://pbs.twimg.com/card_img/1678199844077199362/k_Xms10b?format=jpg&name=orig"},"type":"IMAGE"}},{"key":"app_num_ratings","value":{"string_value":"31,608,946","type":"STRING"}},{"key":"app_price_amount","value":{"string_value":"0.0","type":"STRING"}},{"key":"player_height","value":{"string_value":"720","type":"STRING"}},{"key":"vanity_url","value":{"scribe_key":"vanity_url","string_value":"youtube.com","type":"STRING"}},{"key":"app_name","value":{"string_value":"YouTube: Watch, Listen, Stream","type":"STRING"}},{"key":"player_image_small","value":{"image_value":{"height":81,"width":144,"url":"https://pbs.twimg.com/card_img/1678199844077199362/k_Xms10b?format=jpg&name=144x144"},"type":"IMAGE"}},{"key":"title","value":{"string_value":"The F-150 Lightning Will Crush the Tesla Cybertruck","type":"STRING"}},{"key":"app_price_currency","value":{"string_value":"USD","type":"STRING"}},{"key":"card_url","value":{"scribe_key":"card_url","string_value":"https://t.co/VXA3A6rp51","type":"STRING"}},{"key":"player_image_color","value":{"image_color_value":{"palette":[{"rgb":{"blue":79,"green":142,"red":222},"percentage":47.94},{"rgb":{"blue":99,"green":102,"red":103},"percentage":31.6},{"rgb":{"blue":97,"green":136,"red":178},"percentage":11.04},{"rgb":{"blue":180,"green":181,"red":192},"percentage":5.7},{"rgb":{"blue":78,"green":219,"red":230},"percentage":0.9}]},"type":"IMAGE_COLOR"}},{"key":"player_image_x_large","value":{"image_value":{"height":720,"width":1280,"url":"https://pbs.twimg.com/card_img/1678199844077199362/k_Xms10b?format=png&name=2048x2048_2_exp"},"type":"IMAGE"}}],"card_platform":{"platform":{"audience":{"name":"production"},"device":{"name":"Swift","version":"12"}}},"name":"player","url":"https://t.co/VXA3A6rp51","user_refs_results":[{"result":{"__typename":"User","id":"VXNlcjoxMDIyODI3Mg==","rest_id":"10228272","affiliates_highlighted_label":{},"has_graduated_access":true,"is_blue_verified":true,"legacy":{"can_dm":false,"can_media_tag":true,"created_at":"Tue Nov 13 21:43:46 +0000 2007","default_profile":false,"default_profile_image":false,"description":"like and subscribe.","entities":{"description":{"urls":[]},"url":{"urls":[{"display_url":"youtube.com","expanded_url":"http://youtube.com","url":"https://t.co/bUisN3YzpE","indices":[0,23]}]}},"fast_followers_count":0,"favourites_count":6169,"followers_count":78943283,"friends_count":1185,"has_custom_timelines":true,"is_translator":false,"listed_count":80185,"location":"San Bruno, CA","media_count":15649,"name":"YouTube","normal_followers_count":78943283,"pinned_tweet_ids_str":[],"possibly_sensitive":false,"profile_banner_url":"https://pbs.twimg.com/profile_banners/10228272/1688574812","profile_image_url_https":"https://pbs.twimg.com/profile_images/1427292844612595720/RC1YSvuT_normal.jpg","profile_interstitial_type":"","screen_name":"YouTube","statuses_count":55257,"translator_type":"regular","url":"https://t.co/bUisN3YzpE","verified":false,"verified_type":"Business","want_retweets":false,"withheld_in_countries":[]},"smart_blocked_by":false,"smart_blocking":false,"business_account":{"affiliates_count":1}}}]}},"unified_card":{"card_fetch_state":"NoCard"},"edit_control":{"edit_tweet_ids":["1673106113225535492"],"editable_until_msecs":"1687738156000","is_edit_eligible":false,"edits_remaining":"5"},"edit_perspective":{"favorited":false,"retweeted":false},"is_translatable":false,"views":{"count":"5069","state":"EnabledWithCount"},"source":"<a href=\"http://twitter.com/download/iphone\" rel=\"nofollow\">Twitter for iPhone</a>","legacy":{"created_at":"Sun Jun 25 23:09:16 +0000 2023","conversation_id_str":"1673072594541506561","display_text_range":[15,38],"entities":{"user_mentions":[{"id_str":"243013409","name":"Sawyer Merritt","screen_name":"SawyerMerritt","indices":[0,14]}],"urls":[{"display_url":"youtu.be/tJ1iIov1cUU","expanded_url":"https://youtu.be/tJ1iIov1cUU","url":"https://t.co/VXA3A6rp51","indices":[15,38]}],"hashtags":[],"symbols":[]},"favorite_count":2,"favorited":false,"full_text":"@SawyerMerritt https://t.co/VXA3A6rp51","in_reply_to_screen_name":"SawyerMerritt","in_reply_to_status_id_str":"1673072594541506561","in_reply_to_user_id_str":"243013409","is_quote_status":false,"lang":"qme","possibly_sensitive":false,"possibly_sensitive_editable":true,"quote_count":0,"reply_count":0,"retweet_count":2,"retweeted":false,"user_id_str":"37011010","id_str":"1673106113225535492"},"quick_promote_eligibility":{"eligibility":"IneligibleNotProfessional"}}},"tweetDisplayType":"Tweet"},"clientEventInfo":{"details":{"conversationDetails":{"conversationSection":"HighQuality"},"timelinesDetails":{"controllerData":"DAACDAAEDAABCgABFKACCCADAAUKAAIAAAAAGAJACAAAAAA="}}}}}],"displayType":"VerticalConversation","clientEventInfo":{"details":{"conversationDetails":{"conversationSection":"HighQuality"}}}}},{"entryId":"conversationthread-1673161853407580160","sortIndex":"7550299442313269046","content":{"entryType":"TimelineTimelineModule","__typename":"TimelineTimelineModule","items":[{"entryId":"conversationthread-1673161853407580160-tweet-1673161853407580160","item":{"itemContent":{"itemType":"TimelineTweet","__typename":"TimelineTweet","tweet_results":{"result":{"__typename":"Tweet","rest_id":"1673161853407580160","has_birdwatch_notes":false,"core":{"user_results":{"result":{"__typename":"User","id":"VXNlcjoxMzEzNDAyMjAzNTIxMTM0NTky","rest_id":"1313402203521134592","affiliates_highlighted_label":{},"has_graduated_access":true,"is_blue_verified":true,"legacy":{"can_dm":false,"can_media_tag":true,"created_at":"Tue Oct 06 08:54:40 +0000 2020","default_profile":true,"default_profile_image":false,"description":"right of center, likes wild flowers, rural life, kids and dogs. British Royal gossip, a little nutty.","entities":{"description":{"urls":[]},"url":{"urls":[{"display_url":"betsysfudge.com","expanded_url":"http://www.betsysfudge.com","url":"https://t.co/J0udo3HQd9","indices":[0,23]}]}},"fast_followers_count":0,"favourites_count":9573,"followers_count":129,"friends_count":588,"has_custom_timelines":true,"is_translator":false,"listed_count":2,"location":"Maine, USA","media_count":32,"name":"Aunt Georgie","normal_followers_count":129,"pinned_tweet_ids_str":[],"possibly_sensitive":false,"profile_banner_url":"https://pbs.twimg.com/profile_banners/1313402203521134592/1669202569","profile_image_url_https":"https://pbs.twimg.com/profile_images/1639230144291254273/GIa19x38_normal.jpg","profile_interstitial_type":"","screen_name":"georgieana4","statuses_count":2714,"translator_type":"none","url":"https://t.co/J0udo3HQd9","verified":false,"want_retweets":false,"withheld_in_countries":[]},"smart_blocked_by":false,"smart_blocking":false,"business_account":{}}}},"edit_control":{"edit_tweet_ids":["1673161853407580160"],"editable_until_msecs":"1687751446000","is_edit_eligible":false,"edits_remaining":"5"},"edit_perspective":{"favorited":false,"retweeted":false},"is_translatable":false,"views":{"count":"1216","state":"EnabledWithCount"},"source":"<a href=\"http://twitter.com/download/iphone\" rel=\"nofollow\">Twitter for iPhone</a>","legacy":{"created_at":"Mon Jun 26 02:50:46 +0000 2023","conversation_id_str":"1673072594541506561","display_text_range":[15,134],"entities":{"user_mentions":[{"id_str":"243013409","name":"Sawyer Merritt","screen_name":"SawyerMerritt","indices":[0,14]}],"urls":[],"hashtags":[],"symbols":[]},"favorite_count":3,"favorited":false,"full_text":"@SawyerMerritt I had a Chevy Silverado Quadrasteer. It would turn into a tight parking spot as well as any car. Too bad GM gave it up.","in_reply_to_screen_name":"SawyerMerritt","in_reply_to_status_id_str":"1673072594541506561","in_reply_to_user_id_str":"243013409","is_quote_status":false,"lang":"en","quote_count":0,"reply_count":0,"retweet_count":1,"retweeted":false,"user_id_str":"1313402203521134592","id_str":"1673161853407580160"},"quick_promote_eligibility":{"eligibility":"IneligibleNotProfessional"}}},"tweetDisplayType":"Tweet"},"clientEventInfo":{"details":{"conversationDetails":{"conversationSection":"HighQuality"},"timelinesDetails":{"controllerData":"DAACDAAEDAABCgABFKACCCADAAUKAAIAAAAAGAJACAAAAAA="}}}}}],"displayType":"VerticalConversation","clientEventInfo":{"details":{"conversationDetails":{"conversationSection":"HighQuality"}}}}},{"entryId":"conversationthread-1673193319780831232","sortIndex":"7550299442313269036","content":{"entryType":"TimelineTimelineModule","__typename":"TimelineTimelineModule","items":[{"entryId":"conversationthread-1673193319780831232-tweet-1673193319780831232","item":{"itemContent":{"itemType":"TimelineTweet","__typename":"TimelineTweet","tweet_results":{"result":{"__typename":"Tweet","rest_id":"1673193319780831232","has_birdwatch_notes":false,"core":{"user_results":{"result":{"__typename":"User","id":"VXNlcjoyNTI4NzcxNDU=","rest_id":"252877145","affiliates_highlighted_label":{},"has_graduated_access":true,"is_blue_verified":true,"legacy":{"can_dm":false,"can_media_tag":false,"created_at":"Wed Feb 16 02:57:10 +0000 2011","default_profile":false,"default_profile_image":false,"description":"I lost my twin girls & then my wife. Wrote a blog about the ordeal. Now I blog about everything. It's good. Dad to 4 boys! @UFAlumni #GoGators #finsup","entities":{"description":{"urls":[]},"url":{"urls":[{"display_url":"christopherfusaro.blogspot.com","expanded_url":"http://www.christopherfusaro.blogspot.com","url":"https://t.co/TIkaie8NbJ","indices":[0,23]}]}},"fast_followers_count":0,"favourites_count":4853,"followers_count":809,"friends_count":613,"has_custom_timelines":true,"is_translator":false,"listed_count":12,"location":"Anytown, USA","media_count":2667,"name":"Christopher Fusaro","normal_followers_count":809,"pinned_tweet_ids_str":["1667608881252429824"],"possibly_sensitive":false,"profile_banner_url":"https://pbs.twimg.com/profile_banners/252877145/1567277883","profile_image_url_https":"https://pbs.twimg.com/profile_images/888159039997317122/K3ZOlFZw_normal.jpg","profile_interstitial_type":"","screen_name":"FusaCmee","statuses_count":20568,"translator_type":"none","url":"https://t.co/TIkaie8NbJ","verified":false,"want_retweets":false,"withheld_in_countries":[]},"smart_blocked_by":false,"smart_blocking":false,"business_account":{}}}},"edit_control":{"edit_tweet_ids":["1673193319780831232"],"editable_until_msecs":"1687758948000","is_edit_eligible":false,"edits_remaining":"5"},"edit_perspective":{"favorited":false,"retweeted":false},"is_translatable":false,"views":{"count":"2626","state":"EnabledWithCount"},"source":"<a href=\"http://twitter.com/download/iphone\" rel=\"nofollow\">Twitter for iPhone</a>","legacy":{"created_at":"Mon Jun 26 04:55:48 +0000 2023","conversation_id_str":"1673072594541506561","display_text_range":[15,82],"entities":{"media":[{"display_url":"pic.twitter.com/NF7Sj9iryS","expanded_url":"https://twitter.com/FusaCmee/status/1673193319780831232/photo/1","id_str":"1673193294531268608","indices":[83,106],"media_url_https":"https://pbs.twimg.com/tweet_video_thumb/Fzhgb7kaEAAzaEu.jpg","type":"photo","url":"https://t.co/NF7Sj9iryS","features":{},"sizes":{"large":{"h":498,"w":460,"resize":"fit"},"medium":{"h":498,"w":460,"resize":"fit"},"small":{"h":498,"w":460,"resize":"fit"},"thumb":{"h":150,"w":150,"resize":"crop"}},"original_info":{"height":498,"width":460}}],"user_mentions":[{"id_str":"243013409","name":"Sawyer Merritt","screen_name":"SawyerMerritt","indices":[0,14]}],"urls":[],"hashtags":[],"symbols":[]},"extended_entities":{"media":[{"display_url":"pic.twitter.com/NF7Sj9iryS","expanded_url":"https://twitter.com/FusaCmee/status/1673193319780831232/photo/1","ext_alt_text":"Wtf Back To The Future GIF","id_str":"1673193294531268608","indices":[83,106],"media_key":"16_1673193294531268608","media_url_https":"https://pbs.twimg.com/tweet_video_thumb/Fzhgb7kaEAAzaEu.jpg","type":"animated_gif","url":"https://t.co/NF7Sj9iryS","ext_media_availability":{"status":"Available"},"features":{},"sizes":{"large":{"h":498,"w":460,"resize":"fit"},"medium":{"h":498,"w":460,"resize":"fit"},"small":{"h":498,"w":460,"resize":"fit"},"thumb":{"h":150,"w":150,"resize":"crop"}},"original_info":{"height":498,"width":460},"video_info":{"aspect_ratio":[230,249],"variants":[{"bitrate":0,"content_type":"video/mp4","url":"https://video.twimg.com/tweet_video/Fzhgb7kaEAAzaEu.mp4"}]}}]},"favorite_count":1,"favorited":false,"full_text":"@SawyerMerritt “You mean to tell me. You made a Time Machine…out of a Cybertruck?” https://t.co/NF7Sj9iryS","in_reply_to_screen_name":"SawyerMerritt","in_reply_to_status_id_str":"1673072594541506561","in_reply_to_user_id_str":"243013409","is_quote_status":false,"lang":"en","possibly_sensitive":false,"possibly_sensitive_editable":true,"quote_count":0,"reply_count":0,"retweet_count":1,"retweeted":false,"user_id_str":"252877145","id_str":"1673193319780831232"},"quick_promote_eligibility":{"eligibility":"IneligibleNotProfessional"}}},"tweetDisplayType":"Tweet"},"clientEventInfo":{"details":{"conversationDetails":{"conversationSection":"HighQuality"},"timelinesDetails":{"controllerData":"DAACDAAEDAABCgABFKACCCADAAUKAAIAAAAAGAJACAAAAAA="}}}}}],"displayType":"VerticalConversation","clientEventInfo":{"details":{"conversationDetails":{"conversationSection":"HighQuality"}}}}},{"entryId":"conversationthread-1673422634686509067","sortIndex":"7550299442313269026","content":{"entryType":"TimelineTimelineModule","__typename":"TimelineTimelineModule","items":[{"entryId":"conversationthread-1673422634686509067-tweet-1673422634686509067","item":{"itemContent":{"itemType":"TimelineTweet","__typename":"TimelineTweet","tweet_results":{"result":{"__typename":"Tweet","rest_id":"1673422634686509067","has_birdwatch_notes":false,"core":{"user_results":{"result":{"__typename":"User","id":"VXNlcjoyMTA3ODgxOA==","rest_id":"21078818","affiliates_highlighted_label":{},"has_graduated_access":true,"is_blue_verified":true,"legacy":{"can_dm":true,"can_media_tag":true,"created_at":"Tue Feb 17 10:28:50 +0000 2009","default_profile":false,"default_profile_image":false,"description":"English/Swedish. Contagious contemporary contrarian commentary. Read my blog: https://t.co/nt8rVH10e5","entities":{"description":{"urls":[{"display_url":"avancemang.com","expanded_url":"http://avancemang.com","url":"https://t.co/nt8rVH10e5","indices":[78,101]}]}},"fast_followers_count":0,"favourites_count":2037,"followers_count":1626,"friends_count":1671,"has_custom_timelines":false,"is_translator":false,"listed_count":6,"location":"Pannonia Valeria","media_count":278,"name":"Fulvius Baxter","normal_followers_count":1626,"pinned_tweet_ids_str":["1679394760417595392"],"possibly_sensitive":false,"profile_banner_url":"https://pbs.twimg.com/profile_banners/21078818/1688497160","profile_image_url_https":"https://pbs.twimg.com/profile_images/1491892139713830915/GcBRS2pa_normal.jpg","profile_interstitial_type":"","screen_name":"avancemang","statuses_count":3452,"translator_type":"none","verified":false,"want_retweets":false,"withheld_in_countries":[]},"professional":{"rest_id":"1659612781832814615","professional_type":"Creator","category":[{"id":954,"name":"Blogger","icon_name":"IconBriefcaseStroke"}]},"smart_blocked_by":false,"smart_blocking":false,"business_account":{}}}},"edit_control":{"edit_tweet_ids":["1673422634686509067"],"editable_until_msecs":"1687813621000","is_edit_eligible":false,"edits_remaining":"5"},"edit_perspective":{"favorited":false,"retweeted":false},"is_translatable":false,"views":{"count":"329","state":"EnabledWithCount"},"source":"<a href=\"https://mobile.twitter.com\" rel=\"nofollow\">Twitter Web App</a>","legacy":{"created_at":"Mon Jun 26 20:07:01 +0000 2023","conversation_id_str":"1673072594541506561","display_text_range":[15,19],"entities":{"user_mentions":[{"id_str":"243013409","name":"Sawyer Merritt","screen_name":"SawyerMerritt","indices":[0,14]}],"urls":[],"hashtags":[],"symbols":[]},"favorite_count":1,"favorited":false,"full_text":"@SawyerMerritt Boxy","in_reply_to_screen_name":"SawyerMerritt","in_reply_to_status_id_str":"1673072594541506561","in_reply_to_user_id_str":"243013409","is_quote_status":false,"lang":"en","quote_count":0,"reply_count":0,"retweet_count":1,"retweeted":false,"user_id_str":"21078818","id_str":"1673422634686509067"},"quick_promote_eligibility":{"eligibility":"IneligibleNotProfessional"}}},"tweetDisplayType":"Tweet"},"clientEventInfo":{"details":{"conversationDetails":{"conversationSection":"HighQuality"},"timelinesDetails":{"controllerData":"DAACDAAEDAABCgABFKACCCADAAUKAAIAAAAAGAJACAAAAAA="}}}}}],"displayType":"VerticalConversation","clientEventInfo":{"details":{"conversationDetails":{"conversationSection":"HighQuality"}}}}},{"entryId":"conversationthread-1673073413617860612","sortIndex":"7550299442313269016","content":{"entryType":"TimelineTimelineModule","__typename":"TimelineTimelineModule","items":[{"entryId":"conversationthread-1673073413617860612-tweet-1673073413617860612","item":{"itemContent":{"itemType":"TimelineTweet","__typename":"TimelineTweet","tweet_results":{"result":{"__typename":"Tweet","rest_id":"1673073413617860612","has_birdwatch_notes":false,"core":{"user_results":{"result":{"__typename":"User","id":"VXNlcjoxNjMzNDk5Ng==","rest_id":"16334996","affiliates_highlighted_label":{},"has_graduated_access":true,"is_blue_verified":true,"legacy":{"can_dm":true,"can_media_tag":false,"created_at":"Wed Sep 17 19:21:38 +0000 2008","default_profile":true,"default_profile_image":false,"description":"Tweets are my own views (he/him)","entities":{"description":{"urls":[]}},"fast_followers_count":0,"favourites_count":14147,"followers_count":1312,"friends_count":748,"has_custom_timelines":true,"is_translator":false,"listed_count":23,"location":"Orlando, FL","media_count":1556,"name":"Real Patrick Kling","normal_followers_count":1312,"pinned_tweet_ids_str":[],"possibly_sensitive":false,"profile_banner_url":"https://pbs.twimg.com/profile_banners/16334996/1682049150","profile_image_url_https":"https://pbs.twimg.com/profile_images/1445624447650598920/pi7Lxw5j_normal.jpg","profile_interstitial_type":"","screen_name":"PatrickSKling","statuses_count":9851,"translator_type":"none","verified":false,"want_retweets":false,"withheld_in_countries":[]},"smart_blocked_by":false,"smart_blocking":false,"business_account":{}}}},"edit_control":{"edit_tweet_ids":["1673073413617860612"],"editable_until_msecs":"1687730360000","is_edit_eligible":false,"edits_remaining":"5"},"edit_perspective":{"favorited":false,"retweeted":false},"is_translatable":false,"views":{"count":"8626","state":"EnabledWithCount"},"source":"<a href=\"http://twitter.com/download/iphone\" rel=\"nofollow\">Twitter for iPhone</a>","legacy":{"created_at":"Sun Jun 25 20:59:20 +0000 2023","conversation_id_str":"1673072594541506561","display_text_range":[15,120],"entities":{"user_mentions":[{"id_str":"243013409","name":"Sawyer Merritt","screen_name":"SawyerMerritt","indices":[0,14]}],"urls":[],"hashtags":[],"symbols":[]},"favorite_count":5,"favorited":false,"full_text":"@SawyerMerritt Any chance if you know if there is official confirmation that you can pull a fifth wheel trailer with it?","in_reply_to_screen_name":"SawyerMerritt","in_reply_to_status_id_str":"1673072594541506561","in_reply_to_user_id_str":"243013409","is_quote_status":false,"lang":"en","quote_count":0,"reply_count":1,"retweet_count":1,"retweeted":false,"user_id_str":"16334996","id_str":"1673073413617860612"},"quick_promote_eligibility":{"eligibility":"IneligibleNotProfessional"}}},"tweetDisplayType":"Tweet"},"clientEventInfo":{"details":{"conversationDetails":{"conversationSection":"HighQuality"},"timelinesDetails":{"controllerData":"DAACDAAEDAABCgABFKACCCADAAUKAAIAAAAAGAJACAAAAAA="}}}}},{"entryId":"conversationthread-1673073413617860612-cursor-showmore-6958697891507455801","item":{"itemContent":{"itemType":"TimelineTimelineCursor","__typename":"TimelineTimelineCursor","value":"PAAAAPAtPBwcFoiAvt342fm3LhUCAAAYJmNvbnZlcnNhdGlvbnRocmVhZC0xNjczMDczNDEzNjE3ODYwNjEyIgAA","cursorType":"ShowMore","displayTreatment":{"actionText":"Show replies"}},"clientEventInfo":{"details":{"conversationDetails":{"conversationSection":"HighQuality"}}}}}],"displayType":"VerticalConversation","clientEventInfo":{"details":{"conversationDetails":{"conversationSection":"HighQuality"}}}}},{"entryId":"cursor-bottom-6962936279246627995","sortIndex":"7550299442313269015","content":{"entryType":"TimelineTimelineItem","__typename":"TimelineTimelineItem","itemContent":{"itemType":"TimelineTimelineCursor","__typename":"TimelineTimelineCursor","value":"2gAAAPAPHBn2F4KAvtnlmr66LoKAvsHT0J64LoiAsc2eg5y5EgDwGbW8zoC5LoiAvt342fm3Lo6AvenUpfq3LoKAseG7w_y3LoCA0unTuPoJAPAIveHZ-uG4LoSAvuW8wPO4LoDA0b3C14MJAPARs-XOwv23LojAveWnyYi4LpDA1LGI4ua4LoCAsZWz9KUkAFDSidqk-0gA8AiwjeHU-bcujIC28b3__bcuhICw2azalCQAUb7B6PWhCQDgobOdsLgulsCzuaTBmLl-ANCVi9jkuC4lAhIVBAAA","cursorType":"Bottom"}}}]},{"type":"TimelineTerminateTimeline","direction":"Top"}]}}}